Workbook

Sheet Customer Input Screen
A2: Crystal Customer Input Screen | C2: MUST ENTER COUNTY OF RESIDENCE
A4: Customer Phone Number | D4: Perform Search by either phone number or first part of name, but not both. Try phone number first
A5: Customer Search First Part of Business Name or Last Name | D5: If you do not get the name you are looking for, then, clear and enter manually
A7: Search Result | C7: =IF(AND(C4="",C5=""),"No Search Entered",IFERROR(VLOOKUP(C4,'Customer List'!A:C,3,FALSE),IFERROR(VLOOKUP(C5,'Customer List'!B:C,2,FALSE),"Not Found Enter Manually"))) -> No Search Entered | I7: Data Used for Invoice
A9: Customer Number | I9: =IF(C9<>0,C9,"") | M9: =IF(C9="","")
A10: Consolidated or Business Name | I10: =IF(C10<>0,C10,"") | M10: =IF(C10="","",C10)
A11: First Name | I11: =IF(C11<>0,C11,"") | M11: =IF(C11="","",C11)
A12: Middle Name | I12: =IF(C12<>0,C12,"") | M12: =IF(C12="","",C12)
A13: Last Name | I13: =IF(C13<>0,C13,"") | M13: =IF(C13="","",C13)
A14: Customer Address | I14: =IF(C14<>0,C14,"") | M14: =IF(C14="","",C14)
A15: Customer Address 2 | I15: =IF(C15<>0,C15,"") | M15: =IF(C15="","",C15)
A16: Customer City | I16: =IF(C16<>0,C16,"") | M16: =IF(C16="","",C16)
A17: Customer State | I17: =IF(C17<>0,C17,"") | M17: =IF(C17="","",C17)
A18: Customer Zip Code | I18: =IF(C18<>0,C18,"") | M18: =IF(C18="","",C18)
A19: Customer Florida County | I19: =IF(C19<>0,C19,"") | M19: =IF(C19="","",C19)
A20: Customer Georgia County | I20: =IF(C20<>0,C20,"") | M20: =IF(C20="","",C20)
A21: Customer Email | I21: =IF(C21<>0,C21,"") | M21: =IF(C21="","",C21)
A22: Customer Cell | I22: =IF(C22<>0,C22,"")
A23: Customer Home | I23: =IF(C23<>0,C23,"") | M23: =IF(C23="",0,C23) -> 0 | P23: =VALUE(Q23) -> 0 | Q23: =IFERROR(VLOOKUP(C$7,'Customer List'!C:AB,14,FALSE),M23) -> 0
A24: Customer Work | I24: =IF(C24<>0,C24,"") | M24: =IF(C24="",0,C24) -> 0
A25: Customer Tax Exempt Number | I25: =IF(C25<>0,C25,"") | M25: =IF(C25="","")
A26: Customer Insurance Company | I26: =IF(C26<>0,C26,"")
A27: Customer Insurance Policy Number | I27: =IF(C27<>0,C27,"")
A28: Customer Insurance Expiration | I28: =IF(C28<>0,C28,"")
A32: Customer Signature | C32: [Customer Signature]
A33: Company Signature | C33: [Company Signature]

Sheet Inventory Look UP
E4: Make | F4: Mod | G4: Desc | H4: Machine Serial # | I4: Group Code
A5: Enter Stock Number | E5: =IFERROR(VLOOKUP($C5,'Inventory Data'!$B$1:$I$9000,3,FALSE),"Not Found") -> Not Found | F5: =IF($E5="Not Found","",IFERROR(VLOOKUP($C5,'Inventory Data'!$B$1:$I$9000,4,FALSE),"Not Found")) | G5: =IF($E5="Not Found","",IFERROR(VLOOKUP($C5,'Inventory Data'!$B$1:$I$9000,5,FALSE),"Not Found")) | H5: =IF($E5="Not Found","",IFERROR(VLOOKUP($C5,'Inventory Data'!$B$1:$I$9000,6,FALSE),"Not Found")) | I5: =IF($E5="Not Found","",IFERROR(VLOOKUP($C5,'Inventory Data'!$B$1:$I$9000,7,FALSE),"Not Found"))
A6: Enter Stock Number | E6: =IFERROR(VLOOKUP($C6,'Inventory Data'!$B$1:$I$9000,3,FALSE),"Not Found") -> Not Found | F6: =IF($E6="Not Found","",IFERROR(VLOOKUP($C6,'Inventory Data'!$B$1:$I$9000,4,FALSE),"Not Found")) | G6: =IF($E6="Not Found","",IFERROR(VLOOKUP($C6,'Inventory Data'!$B$1:$I$9000,5,FALSE),"Not Found")) | H6: =IF($E6="Not Found","",IFERROR(VLOOKUP($C6,'Inventory Data'!$B$1:$I$9000,6,FALSE),"Not Found")) | I6: =IF($E6="Not Found","",IFERROR(VLOOKUP($C6,'Inventory Data'!$B$1:$I$9000,7,FALSE),"Not Found"))
A7: Enter Stock Number | E7: =IFERROR(VLOOKUP($C7,'Inventory Data'!$B$1:$I$9000,3,FALSE),"Not Found") -> Not Found | F7: =IF($E7="Not Found","",IFERROR(VLOOKUP($C7,'Inventory Data'!$B$1:$I$9000,4,FALSE),"Not Found")) | G7: =IF($E7="Not Found","",IFERROR(VLOOKUP($C7,'Inventory Data'!$B$1:$I$9000,5,FALSE),"Not Found")) | H7: =IF($E7="Not Found","",IFERROR(VLOOKUP($C7,'Inventory Data'!$B$1:$I$9000,6,FALSE),"Not Found")) | I7: =IF($E7="Not Found","",IFERROR(VLOOKUP($C7,'Inventory Data'!$B$1:$I$9000,7,FALSE),"Not Found"))
A8: Enter Stock Number | E8: =IFERROR(VLOOKUP($C8,'Inventory Data'!$B$1:$I$9000,3,FALSE),"Not Found") -> Not Found | F8: =IF($E8="Not Found","",IFERROR(VLOOKUP($C8,'Inventory Data'!$B$1:$I$9000,4,FALSE),"Not Found")) | G8: =IF($E8="Not Found","",IFERROR(VLOOKUP($C8,'Inventory Data'!$B$1:$I$9000,5,FALSE),"Not Found")) | H8: =IF($E8="Not Found","",IFERROR(VLOOKUP($C8,'Inventory Data'!$B$1:$I$9000,6,FALSE),"Not Found")) | I8: =IF($E8="Not Found","",IFERROR(VLOOKUP($C8,'Inventory Data'!$B$1:$I$9000,7,FALSE),"Not Found"))
A9: Enter Stock Number | E9: =IFERROR(VLOOKUP($C9,'Inventory Data'!$B$1:$I$9000,3,FALSE),"Not Found") -> Not Found | F9: =IF($E9="Not Found","",IFERROR(VLOOKUP($C9,'Inventory Data'!$B$1:$I$9000,4,FALSE),"Not Found")) | G9: =IF($E9="Not Found","",IFERROR(VLOOKUP($C9,'Inventory Data'!$B$1:$I$9000,5,FALSE),"Not Found")) | H9: =IF($E9="Not Found","",IFERROR(VLOOKUP($C9,'Inventory Data'!$B$1:$I$9000,6,FALSE),"Not Found")) | I9: =IF($E9="Not Found","",IFERROR(VLOOKUP($C9,'Inventory Data'!$B$1:$I$9000,7,FALSE),"Not Found"))
A10: Enter Stock Number | E10: =IFERROR(VLOOKUP($C10,'Inventory Data'!$B$1:$I$9000,3,FALSE),"Not Found") -> Not Found | F10: =IF($E10="Not Found","",IFERROR(VLOOKUP($C10,'Inventory Data'!$B$1:$I$9000,4,FALSE),"Not Found")) | G10: =IF($E10="Not Found","",IFERROR(VLOOKUP($C10,'Inventory Data'!$B$1:$I$9000,5,FALSE),"Not Found")) | H10: =IF($E10="Not Found","",IFERROR(VLOOKUP($C10,'Inventory Data'!$B$1:$I$9000,6,FALSE),"Not Found")) | I10: =IF($E10="Not Found","",IFERROR(VLOOKUP($C10,'Inventory Data'!$B$1:$I$9000,7,FALSE),"Not Found")) | J10: =IF($E10="Not Found","",IFERROR(VLOOKUP($C10,'Inventory Data'!$B$1:$I$9000,8,FALSE),"Not Found"))
A13: Enter Stock Number in Yellow Cells to get Unit Data
A14: Data Good through June 17

Sheet Sales Input Sheet
A2: Must Have a Value in Orange Cells
A3: Fill in all Cells with Possible Data
A6: Store
A8: Customer Number | C8: =+'Customer Input Screen'!I9
A9: Customer Name | C9: =+'Customer Input Screen'!I10
A11: Quote Number
A13: Quote Date
A15: Sales Person
A16: Second Sales Person
I17: Other Description from Table | K17: Other Description from Table | M17: Other Description from Table | O17: FREE FORM DESCRIPTION | U17: Group Code | W17: Type
A18: Stock Number | C18: Make | E18: Model | G18: Serial Number
C19: =+Calculations!B6 | E19: =+Calculations!B7 | G19: =+Calculations!B8 | U19: =Calculations!B618 | W19: =+Calculations!B656
C20: =+Calculations!B18 | E20: =+Calculations!B19 | G20: =+Calculations!B20 | U20: =Calculations!B619 | W20: =+Calculations!B657
C21: =+Calculations!B30 | E21: =+Calculations!B31 | G21: =+Calculations!B32 | U21: =Calculations!B620 | W21: =+Calculations!B658
C22: =+Calculations!B42 | E22: =+Calculations!B43 | G22: =+Calculations!B44 | U22: =Calculations!B621 | W22: =+Calculations!B659
C23: =+Calculations!B54 | E23: =+Calculations!B55 | G23: =+Calculations!B56 | U23: =Calculations!B622 | W23: =+Calculations!B660
C24: =+Calculations!B66 | E24: =+Calculations!B67 | G24: =+Calculations!B68 | U24: =Calculations!B623 | W24: =+Calculations!B661
C25: =+Calculations!B78 | E25: =+Calculations!B79 | G25: =+Calculations!B80 | U25: =Calculations!B624 | W25: =+Calculations!B662
C26: =+Calculations!B90 | E26: =+Calculations!B91 | G26: =+Calculations!B92 | U26: =Calculations!B625 | W26: =+Calculations!B663
C27: =+Calculations!B102 | E27: =+Calculations!B103 | G27: =+Calculations!B104 | U27: =Calculations!B626 | W27: =+Calculations!B664
C28: =+Calculations!B114 | E28: =+Calculations!B115 | G28: =+Calculations!B116 | U28: =Calculations!B627 | W28: =+Calculations!B665
A29: Not In Stock
C30: Make | E30: Model | G30: Serial Number | I30: Description | M30: Other Description
A36: Non Serialized items
A37: Quantity | C37: Make | E37: Model | I37: Part Number | K37: Description from Table | O37: Other Description Free Form
G38: No Serial Number
G39: No Serial Number
G40: No Serial Number
G41: No Serial Number
G42: No Serial Number
A43: Trade In
C44: Make | E44: Model | G44: Serial Number | I44: Lender | K44: Payoff Good Until | M44: Amount Owed | O44: Hours | Q44: Condition | S44: Description
A52: Quanitityof New Tires Sold | E52: Quantity of new tires sold
A53: Quantity of New Batteries Sold | E53: Quantity of new batteries Sold
A55: Additional Information for Invoice Detail
W90: =IF('Finance Manager Input Sheet'!C10="warranty","Store County",IF('Finance Manager Input Sheet'!C10="Extended Service Plan","Store County",""))

Sheet Costing Sheet
A1: Quote Number | C1: =+'Sales Input Sheet'!C11 -> 0
A2: Customer Name | C2: =+Calculations!B3
I3: Commission Split | K3: Tax Exempt | O3: Freight Charge | S3: Customer Accepted Terms before sent to Finance
E5: Sales Person Names | O5: Set Up Fee
E7: =+'Sales Input Sheet'!C15 -> 0 | K7: Sales Tax Exemption Reason 1 | O7: DMV Charges | S7: Customer Accepted Term in Months before Finance Referal | W7: Include Kubota Insurance On Quote | AA7: Yes if Kubota or Land Pride, Elect No as override
A9: Days Until Quote Expiration | E9: =+'Sales Input Sheet'!C16 -> 0 | I9: =+Calculations!B4 -> 1 | K9: SalesTax Exemption Reason 2 | O9: Title Fees | S9: Customer Accepted Interest Rate before Finance Referal | W9: Include Kubota Insurance on Invoice | AA9: Yes if selling Kubota Insurance on Invoice, If selected during Preinvoice
A11: Invoice Date | K11: SalesTax Exemption Reason 3 | O11: Tag Fees | S11: Customer Accepted Down Payment before Finance Referal | U11: =Q17+Q19 -> 0 | W11: Include Kubota Insurance on Refer to Finance | AA11: Kubota Insurance on Menu
A13: Invoice Number | K13: SalesTax Exemption Reason 4 | O13: UCC Fee | S13: Customer Accepted Payment | U13: =Calculations!B449 -> 0
A15: Quote Date | K15: SalesTax Exemption Reason 5 | O15: Doc Stamp Taxes | S15: {=IF(OR('Work a Quote'!F23:F25<>0,'Work a Quote'!D9<>0),"DATA STILL IN WORK A QUOTE, CONFIRM COSTING IS UPDATED AND CLEAR BEFORE PROCEEDING","")}
A17: Sale Type | K17: INCLUDE KUBOTA INSURANCE | O17: ADVANCE DEPOSIT
A19: Customer Primary End User | K19: Rate Table | O19: DOWN PAYMENT DUE AT SIGNING | S19: Purchase Order Number
A21: Stock Number | C21: MAKE | E21: MODEL | G21: Serial Number | I21: Dealer List Price | K21: Discount on Line Item | M21: Net Selling Price | O21: COST | Q21: Incentive Amount | S21: Margin | U21: Incentive Description | W21: Customer Rebate - Reduces Amount due from Customer | Y21: Rebate Description | AA21: MONTHLY KTC INSURANCE RATE | AC21: Suggested KTC Rate | AE21: Cost Adjustment | AG21: Cost Adjustment Description | AI21: We Owe Amount | AK21: We Owe Description | AM21: We Owe Free Form Description | AO21: Accounting Cost Adjustment | AQ21: Accounting Cost Adjustment Description | AS21: Second Incentive Description | AU21: Second Rebate Description | AW21: Second Accounting Cost Adjustment Description
A22: =+'Sales Input Sheet'!A19 -> 0 | C22: =+'Sales Input Sheet'!C19 | E22: =+'Sales Input Sheet'!E19 | G22: =Calculations!B8 | M22: =+Calculations!B526 -> 0 | O22: =Calculations!B11 -> 0 | S22: =+Calculations!B14 -> 0 | AC22: =IF(C22="land Pride",'Admin Input Sheet'!$C$3,IF(AND(C22="Kubota",OR(LEFT(E22,1)="b",LEFT(E22,1)="l",LEFT(E22,1)="f",LEFT(E22,1)="g",AND(LEFT(E22,1)="t",LEFT(E22,2)<>"te",LEFT(E22,3)<>"tlb"),LEFT(E22,1)="w",LEFT(E22,1)="z",LEFT(E22,3)="rtv")),'Admin Input Sheet'!$C$3,'Admin Input Sheet'!$C$4)) -> 0.002
A23: =+'Sales Input Sheet'!A20 -> 0 | C23: =+'Sales Input Sheet'!C20 | E23: =+'Sales Input Sheet'!E20 | G23: =Calculations!B20 | M23: =+Calculations!B527 -> 0 | O23: =Calculations!B23 -> 0 | S23: =+Calculations!B26 -> 0 | AC23: =IF(C23="land Pride",'Admin Input Sheet'!$C$3,IF(AND(C23="Kubota",OR(LEFT(E23,1)="b",LEFT(E23,1)="l",LEFT(E23,1)="f",LEFT(E23,1)="g",AND(LEFT(E23,1)="t",LEFT(E23,2)<>"te",LEFT(E23,3)<>"tlb"),LEFT(E23,1)="w",LEFT(E23,1)="z",LEFT(E23,3)="rtv")),'Admin Input Sheet'!$C$3,'Admin Input Sheet'!$C$4)) -> 0.002
A24: =+'Sales Input Sheet'!A21 -> 0 | C24: =+'Sales Input Sheet'!C21 | E24: =+'Sales Input Sheet'!E21 | G24: =Calculations!B32 | M24: =+Calculations!B528 -> 0 | O24: =Calculations!B35 -> 0 | S24: =+Calculations!B38 -> 0 | AC24: =IF(C24="land Pride",'Admin Input Sheet'!$C$3,IF(AND(C24="Kubota",OR(LEFT(E24,1)="b",LEFT(E24,1)="l",LEFT(E24,1)="f",LEFT(E24,1)="g",AND(LEFT(E24,1)="t",LEFT(E24,2)<>"te",LEFT(E24,3)<>"tlb"),LEFT(E24,1)="w",LEFT(E24,1)="z",LEFT(E24,3)="rtv")),'Admin Input Sheet'!$C$3,'Admin Input Sheet'!$C$4)) -> 0.002
A25: =+'Sales Input Sheet'!A22 -> 0 | C25: =+'Sales Input Sheet'!C22 | E25: =+'Sales Input Sheet'!E22 | G25: =Calculations!B44 | M25: =+Calculations!B529 -> 0 | O25: =Calculations!B47 -> 0 | S25: =+Calculations!B50 -> 0 | AC25: =IF(C25="land Pride",'Admin Input Sheet'!$C$3,IF(AND(C25="Kubota",OR(LEFT(E25,1)="b",LEFT(E25,1)="l",LEFT(E25,1)="f",LEFT(E25,1)="g",AND(LEFT(E25,1)="t",LEFT(E25,2)<>"te",LEFT(E25,3)<>"tlb"),LEFT(E25,1)="w",LEFT(E25,1)="z",LEFT(E25,3)="rtv")),'Admin Input Sheet'!$C$3,'Admin Input Sheet'!$C$4)) -> 0.002
A26: =+'Sales Input Sheet'!A23 -> 0 | C26: =+'Sales Input Sheet'!C23 | E26: =+'Sales Input Sheet'!E23 | G26: =Calculations!B56 | M26: =+Calculations!B530 -> 0 | O26: =Calculations!B59 -> 0 | S26: =+Calculations!B62 -> 0 | AC26: =IF(C26="land Pride",'Admin Input Sheet'!$C$3,IF(AND(C26="Kubota",OR(LEFT(E26,1)="b",LEFT(E26,1)="l",LEFT(E26,1)="f",LEFT(E26,1)="g",AND(LEFT(E26,1)="t",LEFT(E26,2)<>"te",LEFT(E26,3)<>"tlb"),LEFT(E26,1)="w",LEFT(E26,1)="z",LEFT(E26,3)="rtv")),'Admin Input Sheet'!$C$3,'Admin Input Sheet'!$C$4)) -> 0.002
A27: =+'Sales Input Sheet'!A24 -> 0 | C27: =+'Sales Input Sheet'!C24 | E27: =+'Sales Input Sheet'!E24 | G27: =Calculations!B68 | M27: =+Calculations!B531 -> 0 | O27: =Calculations!B71 -> 0 | S27: =+Calculations!B74 -> 0 | AC27: =IF(C27="land Pride",'Admin Input Sheet'!$C$3,IF(AND(C27="Kubota",OR(LEFT(E27,1)="b",LEFT(E27,1)="l",LEFT(E27,1)="f",LEFT(E27,1)="g",AND(LEFT(E27,1)="t",LEFT(E27,2)<>"te",LEFT(E27,3)<>"tlb"),LEFT(E27,1)="w",LEFT(E27,1)="z",LEFT(E27,3)="rtv")),'Admin Input Sheet'!$C$3,'Admin Input Sheet'!$C$4)) -> 0.002
A28: =+'Sales Input Sheet'!A25 -> 0 | C28: =+'Sales Input Sheet'!C25 | E28: =+'Sales Input Sheet'!E25 | G28: =Calculations!B80 | M28: =+Calculations!B532 -> 0 | O28: =Calculations!B83 -> 0 | S28: =+Calculations!B86 -> 0 | AC28: =IF(C28="land Pride",'Admin Input Sheet'!$C$3,IF(AND(C28="Kubota",OR(LEFT(E28,1)="b",LEFT(E28,1)="l",LEFT(E28,1)="f",LEFT(E28,1)="g",AND(LEFT(E28,1)="t",LEFT(E28,2)<>"te",LEFT(E28,3)<>"tlb"),LEFT(E28,1)="w",LEFT(E28,1)="z",LEFT(E28,3)="rtv")),'Admin Input Sheet'!$C$3,'Admin Input Sheet'!$C$4)) -> 0.002
A29: =+'Sales Input Sheet'!A26 -> 0 | C29: =+'Sales Input Sheet'!C26 | E29: =+'Sales Input Sheet'!E26 | G29: =Calculations!B92 | M29: =+Calculations!B533 -> 0 | O29: =Calculations!B95 -> 0 | S29: =+Calculations!B98 -> 0 | AC29: =IF(C29="land Pride",'Admin Input Sheet'!$C$3,IF(AND(C29="Kubota",OR(LEFT(E29,1)="b",LEFT(E29,1)="l",LEFT(E29,1)="f",LEFT(E29,1)="g",AND(LEFT(E29,1)="t",LEFT(E29,2)<>"te",LEFT(E29,3)<>"tlb"),LEFT(E29,1)="w",LEFT(E29,1)="z",LEFT(E29,3)="rtv")),'Admin Input Sheet'!$C$3,'Admin Input Sheet'!$C$4)) -> 0.002
A30: =+'Sales Input Sheet'!A27 -> 0 | C30: =+'Sales Input Sheet'!C27 | E30: =+'Sales Input Sheet'!E27 | G30: =Calculations!B104 | M30: =+Calculations!B534 -> 0 | O30: =Calculations!B107 -> 0 | S30: =+Calculations!B110 -> 0 | AC30: =IF(C30="land Pride",'Admin Input Sheet'!$C$3,IF(AND(C30="Kubota",OR(LEFT(E30,1)="b",LEFT(E30,1)="l",LEFT(E30,1)="f",LEFT(E30,1)="g",AND(LEFT(E30,1)="t",LEFT(E30,2)<>"te",LEFT(E30,3)<>"tlb"),LEFT(E30,1)="w",LEFT(E30,1)="z",LEFT(E30,3)="rtv")),'Admin Input Sheet'!$C$3,'Admin Input Sheet'!$C$4)) -> 0.002
A31: =+'Sales Input Sheet'!A28 -> 0 | C31: =+'Sales Input Sheet'!C28 | E31: =+'Sales Input Sheet'!E28 | G31: =Calculations!B116 | M31: =+Calculations!B535 -> 0 | O31: =Calculations!B119 -> 0 | S31: =+Calculations!B122 -> 0 | AC31: =IF(C31="land Pride",'Admin Input Sheet'!$C$3,IF(AND(C31="Kubota",OR(LEFT(E31,1)="b",LEFT(E31,1)="l",LEFT(E31,1)="f",LEFT(E31,1)="g",AND(LEFT(E31,1)="t",LEFT(E31,2)<>"te",LEFT(E31,3)<>"tlb"),LEFT(E31,1)="w",LEFT(E31,1)="z",LEFT(E31,3)="rtv")),'Admin Input Sheet'!$C$3,'Admin Input Sheet'!$C$4)) -> 0.002
A33: Write In Items | C33: MAKE | E33: MODEL | G33: Serial Number | I33: Dealer List Price | K33: Discount on Line Item | M33: Net Selling Price | O33: COST | Q33: Incentive Amount | S33: Margin | U33: Incentive Description | W33: Customer Rebate - Reduces Amount due from Customer | Y33: Rebate Description | AA33: MONTHLY KTC INSURANCE RATE | AE33: Accounting Cost Adjustment | AG33: Accounting Cost Adjustment Description | AS33: Second Incentive Description | AU33: Second Rebate Description | AW33: Second Accounting Cost Adjustment Description
C34: =+'Sales Input Sheet'!C31 -> 0 | E34: =+'Sales Input Sheet'!E31 -> 0 | G34: =+'Sales Input Sheet'!G31 -> 0 | M34: =+Calculations!B536 -> 0 | S34: =Calculations!B126 -> 0 | AC34: =IF(C34="land Pride",'Admin Input Sheet'!$C$3,IF(AND(C34="Kubota",OR(LEFT(E34,1)="b",LEFT(E34,1)="l",LEFT(E34,1)="f",LEFT(E34,1)="g",AND(LEFT(E34,1)="t",LEFT(E34,2)<>"te",LEFT(E34,3)<>"tlb"),LEFT(E34,1)="w",LEFT(E34,1)="z",LEFT(E34,3)="rtv")),'Admin Input Sheet'!$C$3,'Admin Input Sheet'!$C$4)) -> 0.002
C35: =+'Sales Input Sheet'!C32 -> 0 | E35: =+'Sales Input Sheet'!E32 -> 0 | G35: =+'Sales Input Sheet'!G32 -> 0 | M35: =+Calculations!B537 -> 0 | S35: =Calculations!B130 -> 0 | AC35: =IF(C35="land Pride",'Admin Input Sheet'!$C$3,IF(AND(C35="Kubota",OR(LEFT(E35,1)="b",LEFT(E35,1)="l",LEFT(E35,1)="f",LEFT(E35,1)="g",AND(LEFT(E35,1)="t",LEFT(E35,2)<>"te",LEFT(E35,3)<>"tlb"),LEFT(E35,1)="w",LEFT(E35,1)="z",LEFT(E35,3)="rtv")),'Admin Input Sheet'!$C$3,'Admin Input Sheet'!$C$4)) -> 0.002
C36: =+'Sales Input Sheet'!C33 -> 0 | E36: =+'Sales Input Sheet'!E33 -> 0 | G36: =+'Sales Input Sheet'!G33 -> 0 | M36: =+Calculations!B538 -> 0 | S36: =Calculations!B134 -> 0 | AC36: =IF(C36="land Pride",'Admin Input Sheet'!$C$3,IF(AND(C36="Kubota",OR(LEFT(E36,1)="b",LEFT(E36,1)="l",LEFT(E36,1)="f",LEFT(E36,1)="g",AND(LEFT(E36,1)="t",LEFT(E36,2)<>"te",LEFT(E36,3)<>"tlb"),LEFT(E36,1)="w",LEFT(E36,1)="z",LEFT(E36,3)="rtv")),'Admin Input Sheet'!$C$3,'Admin Input Sheet'!$C$4)) -> 0.002
C37: =+'Sales Input Sheet'!C34 -> 0 | E37: =+'Sales Input Sheet'!E34 -> 0 | G37: =+'Sales Input Sheet'!G34 -> 0 | M37: =+Calculations!B539 -> 0 | S37: =Calculations!B138 -> 0 | AC37: =IF(C37="land Pride",'Admin Input Sheet'!$C$3,IF(AND(C37="Kubota",OR(LEFT(E37,1)="b",LEFT(E37,1)="l",LEFT(E37,1)="f",LEFT(E37,1)="g",AND(LEFT(E37,1)="t",LEFT(E37,2)<>"te",LEFT(E37,3)<>"tlb"),LEFT(E37,1)="w",LEFT(E37,1)="z",LEFT(E37,3)="rtv")),'Admin Input Sheet'!$C$3,'Admin Input Sheet'!$C$4)) -> 0.002
C38: =+'Sales Input Sheet'!C35 -> 0 | E38: =+'Sales Input Sheet'!E35 -> 0 | G38: =+'Sales Input Sheet'!G35 -> 0 | M38: =+Calculations!B540 -> 0 | S38: =Calculations!B142 -> 0 | AC38: =IF(C38="land Pride",'Admin Input Sheet'!$C$3,IF(AND(C38="Kubota",OR(LEFT(E38,1)="b",LEFT(E38,1)="l",LEFT(E38,1)="f",LEFT(E38,1)="g",AND(LEFT(E38,1)="t",LEFT(E38,2)<>"te",LEFT(E38,3)<>"tlb"),LEFT(E38,1)="w",LEFT(E38,1)="z",LEFT(E38,3)="rtv")),'Admin Input Sheet'!$C$3,'Admin Input Sheet'!$C$4)) -> 0.002
A40: Non Serialied Items
A41: Quantity Sold | C41: MAKE | E41: MODEL | G41: Part Number | I41: Dealer List Price Per Unit | K41: Discount Line Item per unit | M41: Net Extended Selling Price | O41: COST per Item | S41: Extended Margin | AA41: MONTHLY KTC INSURANCE RATE
A42: =+'Sales Input Sheet'!A38 -> 0 | C42: =+'Sales Input Sheet'!C38 -> 0 | E42: =+'Sales Input Sheet'!E38 -> 0 | G42: =+'Sales Input Sheet'!I38 -> 0 | M42: =+Calculations!B541 -> 0 | S42: =Calculations!B146 -> 0 | AC42: =IF(C42="land Pride",'Admin Input Sheet'!$C$3,IF(AND(C42="Kubota",OR(LEFT(E42,1)="b",LEFT(E42,1)="l",LEFT(E42,1)="f",LEFT(E42,1)="g",AND(LEFT(E42,1)="t",LEFT(E42,2)<>"te",LEFT(E42,3)<>"tlb"),LEFT(E42,1)="w",LEFT(E42,1)="z",LEFT(E42,3)="rtv")),'Admin Input Sheet'!$C$3,'Admin Input Sheet'!$C$4)) -> 0.002
A43: =+'Sales Input Sheet'!A39 -> 0 | C43: =+'Sales Input Sheet'!C39 -> 0 | E43: =+'Sales Input Sheet'!E39 -> 0 | G43: =+'Sales Input Sheet'!I39 -> 0 | M43: =+Calculations!B542 -> 0 | S43: =Calculations!B154 -> 0 | AC43: =IF(C43="land Pride",'Admin Input Sheet'!$C$3,IF(AND(C43="Kubota",OR(LEFT(E43,1)="b",LEFT(E43,1)="l",LEFT(E43,1)="f",LEFT(E43,1)="g",AND(LEFT(E43,1)="t",LEFT(E43,2)<>"te",LEFT(E43,3)<>"tlb"),LEFT(E43,1)="w",LEFT(E43,1)="z",LEFT(E43,3)="rtv")),'Admin Input Sheet'!$C$3,'Admin Input Sheet'!$C$4)) -> 0.002
A44: =+'Sales Input Sheet'!A40 -> 0 | C44: =+'Sales Input Sheet'!C40 -> 0 | E44: =+'Sales Input Sheet'!E40 -> 0 | G44: =+'Sales Input Sheet'!I40 -> 0 | M44: =+Calculations!B543 -> 0 | S44: =Calculations!B162 -> 0 | AC44: =IF(C44="land Pride",'Admin Input Sheet'!$C$3,IF(AND(C44="Kubota",OR(LEFT(E44,1)="b",LEFT(E44,1)="l",LEFT(E44,1)="f",LEFT(E44,1)="g",AND(LEFT(E44,1)="t",LEFT(E44,2)<>"te",LEFT(E44,3)<>"tlb"),LEFT(E44,1)="w",LEFT(E44,1)="z",LEFT(E44,3)="rtv")),'Admin Input Sheet'!$C$3,'Admin Input Sheet'!$C$4)) -> 0.002
A45: =+'Sales Input Sheet'!A41 -> 0 | C45: =+'Sales Input Sheet'!C41 -> 0 | E45: =+'Sales Input Sheet'!E41 -> 0 | G45: =+'Sales Input Sheet'!I41 -> 0 | M45: =+Calculations!B544 -> 0 | S45: =Calculations!B170 -> 0 | AC45: =IF(C45="land Pride",'Admin Input Sheet'!$C$3,IF(AND(C45="Kubota",OR(LEFT(E45,1)="b",LEFT(E45,1)="l",LEFT(E45,1)="f",LEFT(E45,1)="g",AND(LEFT(E45,1)="t",LEFT(E45,2)<>"te",LEFT(E45,3)<>"tlb"),LEFT(E45,1)="w",LEFT(E45,1)="z",LEFT(E45,3)="rtv")),'Admin Input Sheet'!$C$3,'Admin Input Sheet'!$C$4)) -> 0.002
A46: =+'Sales Input Sheet'!A42 -> 0 | C46: =+'Sales Input Sheet'!C42 -> 0 | E46: =+'Sales Input Sheet'!E42 -> 0 | G46: =+'Sales Input Sheet'!I42 -> 0 | M46: =+Calculations!B545 -> 0 | S46: =Calculations!B178 -> 0 | AC46: =IF(C46="land Pride",'Admin Input Sheet'!$C$3,IF(AND(C46="Kubota",OR(LEFT(E46,1)="b",LEFT(E46,1)="l",LEFT(E46,1)="f",LEFT(E46,1)="g",AND(LEFT(E46,1)="t",LEFT(E46,2)<>"te",LEFT(E46,3)<>"tlb"),LEFT(E46,1)="w",LEFT(E46,1)="z",LEFT(E46,3)="rtv")),'Admin Input Sheet'!$C$3,'Admin Input Sheet'!$C$4)) -> 0.002
A47: Trade In
C48: Make | E48: Model | G48: Serial Number | I48: Trade Allowance | K48: Amount Owed | M48: =+'Sales Input Sheet'!Q44 -> Condition | O48: Trade ACV Value | Q48: =+'Sales Input Sheet'!O44 -> Hours | S48: Margin | U48: Disposition Plan | AA48: Reduce Taxable Amount by Trade Allowance
C49: =+'Sales Input Sheet'!C45 -> 0 | E49: =+'Sales Input Sheet'!E45 -> 0 | G49: =+'Sales Input Sheet'!G45 -> 0 | M49: =+'Sales Input Sheet'!Q45 -> 0 | Q49: =+'Sales Input Sheet'!O45 -> 0 | S49: =+Calculations!B185 -> 0
C50: =+'Sales Input Sheet'!C46 -> 0 | E50: =+'Sales Input Sheet'!E46 -> 0 | G50: =+'Sales Input Sheet'!G46 -> 0 | M50: =+'Sales Input Sheet'!Q46 -> 0 | Q50: =+'Sales Input Sheet'!O46 -> 0 | S50: =+Calculations!B186 -> 0
C51: =+'Sales Input Sheet'!C47 -> 0 | E51: =+'Sales Input Sheet'!E47 -> 0 | G51: =+'Sales Input Sheet'!G47 -> 0 | M51: =+'Sales Input Sheet'!Q47 -> 0 | Q51: =+'Sales Input Sheet'!O47 -> 0 | S51: =+Calculations!B666 -> 0
C52: =+'Sales Input Sheet'!C48 -> 0 | E52: =+'Sales Input Sheet'!E48 -> 0 | G52: =+'Sales Input Sheet'!G48 -> 0 | M52: =+'Sales Input Sheet'!Q48 -> 0 | Q52: =+'Sales Input Sheet'!O48 -> 0 | S52: =+Calculations!B669 -> 0
C53: =+'Sales Input Sheet'!C49 -> 0 | E53: =+'Sales Input Sheet'!E49 -> 0 | G53: =+'Sales Input Sheet'!G49 -> 0 | M53: =+'Sales Input Sheet'!Q49 -> 0 | Q53: =+'Sales Input Sheet'!O49 -> 0 | S53: =+Calculations!B672 -> 0
C54: =+'Sales Input Sheet'!C50 -> 0 | E54: =+'Sales Input Sheet'!E50 -> 0 | G54: =+'Sales Input Sheet'!G50 -> 0 | M54: =+'Sales Input Sheet'!Q50 -> 0 | Q54: =+'Sales Input Sheet'!O50 -> 0 | S54: =+Calculations!B675 -> 0
K56: Unit to Which We Owe Applies | O56: Cost to Fill We Owe | Q56: We Owe Desctiption | S56: Margin | U56: Free Form We Owe Description | Y56: If None, then Nothing Owed
I57: We Owe | S57: =-Calculations!B191 -> 0
I58: We Owe | S58: =-Calculations!B192 -> 0
I59: We Owe | S59: =-Calculations!B193 -> 0
I60: We Owe | S60: =-Calculations!B194 -> 0
I61: We Owe | S61: =-Calculations!B195 -> 0
Q63: Total Front Margin | S63: =Calculations!B201 -> 0
Q69: =IF(SUM('Work a Quote'!$J$2:$L$5)<>0,"WORK A QUOTE STILL CONTAINS ADJUSTMENTS, FIX BEFORE FINALIZING","")

Sheet Finance Manager Input Sheet
A2: Quote Number | C2: =+'Sales Input Sheet'!C11 -> 0 | E2: Finance Manager
C3: PRODUCT NAME | E3: Term and Expanded Description | G3: Seller of Product | I3: Selling Price | K3: Cost if Accepted | N3: Customer Accepted | P3: Margin | R3: Platinum Package | T3: Gold Package | V3: Silver Package | X3: Bronze Package | AA3: Platinum Plan | AB3: Platinum Selling Price without Tax | AC3: Platinum Price with Tax | AD3: Platinum Cost | AE3: Gold Plan | AF3: Gold Plan Price | AG3: Gold Price with Tax | AH3: GoldCost | AI3: Silver Plan | AJ3: SILVER PLAN PRICE | AK3: Silver Price with tax | AL3: Silver Cost | AM3: Bronze Plan | AN3: Bronze Plan Price | AO3: Bronze Price with tax | AP3: Bronze Cost | AQ3: Customer Accepted Protection Options | AR3: Customer Accepted Price | AS3: Accepted Price with tax | AT3: Accepted Cost | AU3: Customer Declined Protection Options | AV3: Customer Decline Price | AW3: Desc | AX3: Price with Tax | AY3: Cost | BA3: Customer Accepted | BB3: Customer Declined | BD3: Platinum | BF3: Gold | BH3: Silver | BJ3: Bronze
A4: Additional Product Sale | P4: =IF(N4="no",0,I4-K4) -> 0 | AA4: =IF(I4>0,IF($BD4<>"no",IF(C4<>0,UPPER(_xlfn.CONCAT(E4," ",C4)),""),""),"") | AB4: =IF($R4<>"no",IF(I4<>0,$I4,0),0) -> 0 | AC4: =IF($R4<>"no",IF($AX4<>0,$AX4,0),0) -> 0 | AD4: =IF($R4<>"no",IF($AY4<>0,$AY4,0),0) -> 0 | AE4: =IF(I4>0,IF($BF4<>"no",IF(C4<>0,UPPER(_xlfn.CONCAT(E4," ",C4)),""),""),"") | AF4: =IF($T4<>"no",IF(I4<>0,I4,0),0) -> 0 | AG4: =IF($T4<>"no",IF($AX4<>0,$AX4,0),0) -> 0 | AH4: =IF($T4<>"no",IF($AY4<>0,$AY4,0),0) -> 0 | AI4: =IF(I4>0,IF($BH4<>"no",IF(C4<>0,UPPER(_xlfn.CONCAT(E4," ",C4)),""),""),"") | AJ4: =IF($V4<>"no",IF($I4<>0,$I4,0),0) -> 0 | AK4: =IF($V4<>"no",IF($AX4<>0,$AX4,0),0) -> 0 | AL4: =IF($V4<>"no",IF($AY4<>0,$AY4,0),0) -> 0 | AM4: =IF(I4>0,IF($BJ4<>"no",IF(C4<>0,UPPER(_xlfn.CONCAT(E4," ",C4)),""),""),"") | AN4: =IF($X4<>"no",IF($I4<>0,$I4,0),0) -> 0 | AO4: =IF($X4<>"no",IF($AX4<>0,$AX4,0),0) -> 0 | AP4: =IF($X4<>"no",IF($AY4<>0,$AY4,0),0) -> 0 | AQ4: =IF(I4>0,IF($N4<>"no",IF(C4<>0,UPPER(_xlfn.CONCAT(E4," ",C4)),""),""),"") | AR4: =IF(N4<>"no",IF($I4<>0,$I4,0),0) -> 0 | AS4: =IF(N4<>"no",IF($AX4<>0,$AX4,0),0) -> 0 | AT4: =IF($N4<>"no",IF($AY4<>0,$AY4,0),0) -> 0 | AU4: =IF(I4>0,IF($N4="no",IF(C4<>0,UPPER(_xlfn.CONCAT(E4," ",C4)),""),""),"") | AW4: =_xlfn.CONCAT(C4) | AX4: =I4*(1+IF('Costing Sheet'!M3="Tax Exempt",0,IF(IFERROR(VLOOKUP(C4,'Admin Input Sheet'!C$9:I$18,3,FALSE),"Taxable")="Taxable",Calculations!B$404,0)+IF(IFERROR(VLOOKUP(C4,'Admin Input Sheet'!C$9:I$18,IF(Calculations!B402="FL",5,7),FALSE),"Store")="No County Tax",0,IF(IFERROR(VLOOKUP(C4,'Admin Input Sheet'!C$9:I$18,IF(Calculations!B402="FL",5,7),FALSE),"Store")="Customer",Calculations!B$410,Calculations!B$408)))) -> 0 | AY4: =K4 -> 0 | BA4: =IF(N4="No","Customer Declined",IF($I4>0,N4,"NO")) -> NO | BB4: =IF(AND(I4>0,N4="No"),"Customer Declined","No") -> No | BD4: =IF($I4>0,R4,"No") -> No | BF4: =IF($I4>0,T4,"No") -> No | BH4: =IF($I4>0,V4,"No") -> No | BJ4: =IF($I4>0,X4,"No") -> No
A5: Additional Product Sale | P5: =IF(N5="no",0,I5-K5) -> 0 | AA5: =IF(I5>0,IF($BD5<>"no",IF(C5<>0,UPPER(_xlfn.CONCAT(E5," ",C5)),""),""),"") | AB5: =IF($R5<>"no",IF(I5<>0,$I5,0),0) -> 0 | AC5: =IF($R5<>"no",IF($AX5<>0,$AX5,0),0) -> 0 | AD5: =IF($R5<>"no",IF($AY5<>0,$AY5,0),0) -> 0 | AE5: =IF(I5>0,IF($BF5<>"no",IF(C5<>0,UPPER(_xlfn.CONCAT(E5," ",C5)),""),""),"") | AF5: =IF($T5<>"no",IF(I5<>0,I5,0),0) -> 0 | AG5: =IF($T5<>"no",IF($AX5<>0,$AX5,0),0) -> 0 | AH5: =IF($T5<>"no",IF($AY5<>0,$AY5,0),0) -> 0 | AI5: =IF(I5>0,IF($BH5<>"no",IF(C5<>0,UPPER(_xlfn.CONCAT(E5," ",C5)),""),""),"") | AJ5: =IF($V5<>"no",IF($I5<>0,$I5,0),0) -> 0 | AK5: =IF($V5<>"no",IF($AX5<>0,$AX5,0),0) -> 0 | AL5: =IF($V5<>"no",IF($AY5<>0,$AY5,0),0) -> 0 | AM5: =IF(I5>0,IF($BJ5<>"no",IF(C5<>0,UPPER(_xlfn.CONCAT(E5," ",C5)),""),""),"") | AN5: =IF($X5<>"no",IF($I5<>0,$I5,0),0) -> 0 | AO5: =IF($X5<>"no",IF($AX5<>0,$AX5,0),0) -> 0 | AP5: =IF($X5<>"no",IF($AY5<>0,$AY5,0),0) -> 0 | AQ5: =IF(I5>0,IF($N5<>"no",IF(C5<>0,UPPER(_xlfn.CONCAT(E5," ",C5)),""),""),"") | AR5: =IF(N5<>"no",IF($I5<>0,$I5,0),0) -> 0 | AS5: =IF(N5<>"no",IF($AX5<>0,$AX5,0),0) -> 0 | AT5: =IF($N5<>"no",IF($AY5<>0,$AY5,0),0) -> 0 | AU5: =IF(I5>0,IF($N5="no",IF(C5<>0,UPPER(_xlfn.CONCAT(E5," ",C5)),""),""),"") | AW5: =_xlfn.CONCAT(C5) | AX5: =I5*(1+IF('Costing Sheet'!M4="Tax Exempt",0,IF(IFERROR(VLOOKUP(C5,'Admin Input Sheet'!C$9:I$18,3,FALSE),"Taxable")="Taxable",Calculations!B$404,0)+IF(IFERROR(VLOOKUP(C5,'Admin Input Sheet'!C$9:I$18,IF(Calculations!B403="FL",5,7),FALSE),"Store")="No County Tax",0,IF(IFERROR(VLOOKUP(C5,'Admin Input Sheet'!C$9:I$18,IF(Calculations!B403="FL",5,7),FALSE),"Store")="Customer",Calculations!B$410,Calculations!B$408)))) -> 0 | AY5: =K5 -> 0 | BA5: =IF(N5="No","Customer Declined",IF($I5>0,N5,"NO")) -> NO | BB5: =IF(AND(I5>0,N5="No"),"Customer Declined","No") -> No | BD5: =IF($I5>0,R5,"No") -> No | BF5: =IF($I5>0,T5,"No") -> No | BH5: =IF($I5>0,V5,"No") -> No | BJ5: =IF($I5>0,X5,"No") -> No
A6: Additional Product Sale | P6: =IF(N6="no",0,I6-K6) -> 0 | AA6: =IF(I6>0,IF($BD6<>"no",IF(C6<>0,UPPER(_xlfn.CONCAT(E6," ",C6)),""),""),"") | AB6: =IF($R6<>"no",IF(I6<>0,$I6,0),0) -> 0 | AC6: =IF($R6<>"no",IF($AX6<>0,$AX6,0),0) -> 0 | AD6: =IF($R6<>"no",IF($AY6<>0,$AY6,0),0) -> 0 | AE6: =IF(I6>0,IF($BF6<>"no",IF(C6<>0,UPPER(_xlfn.CONCAT(E6," ",C6)),""),""),"") | AF6: =IF($T6<>"no",IF(I6<>0,I6,0),0) -> 0 | AG6: =IF($T6<>"no",IF($AX6<>0,$AX6,0),0) -> 0 | AH6: =IF($T6<>"no",IF($AY6<>0,$AY6,0),0) -> 0 | AI6: =IF(I6>0,IF($BH6<>"no",IF(C6<>0,UPPER(_xlfn.CONCAT(E6," ",C6)),""),""),"") | AJ6: =IF($V6<>"no",IF($I6<>0,$I6,0),0) -> 0 | AK6: =IF($V6<>"no",IF($AX6<>0,$AX6,0),0) -> 0 | AL6: =IF($V6<>"no",IF($AY6<>0,$AY6,0),0) -> 0 | AM6: =IF(I6>0,IF($BJ6<>"no",IF(C6<>0,UPPER(_xlfn.CONCAT(E6," ",C6)),""),""),"") | AN6: =IF($X6<>"no",IF($I6<>0,$I6,0),0) -> 0 | AO6: =IF($X6<>"no",IF($AX6<>0,$AX6,0),0) -> 0 | AP6: =IF($X6<>"no",IF($AY6<>0,$AY6,0),0) -> 0 | AQ6: =IF(I6>0,IF($N6<>"no",IF(C6<>0,UPPER(_xlfn.CONCAT(E6," ",C6)),""),""),"") | AR6: =IF(N6<>"no",IF($I6<>0,$I6,0),0) -> 0 | AS6: =IF(N6<>"no",IF($AX6<>0,$AX6,0),0) -> 0 | AT6: =IF($N6<>"no",IF($AY6<>0,$AY6,0),0) -> 0 | AU6: =IF(I6>0,IF($N6="no",IF(C6<>0,UPPER(_xlfn.CONCAT(E6," ",C6)),""),""),"") | AW6: =_xlfn.CONCAT(C6) | AX6: =I6*(1+IF('Costing Sheet'!M5="Tax Exempt",0,IF(IFERROR(VLOOKUP(C6,'Admin Input Sheet'!C$9:I$18,3,FALSE),"Taxable")="Taxable",Calculations!B$404,0)+IF(IFERROR(VLOOKUP(C6,'Admin Input Sheet'!C$9:I$18,IF(Calculations!B404="FL",5,7),FALSE),"Store")="No County Tax",0,IF(IFERROR(VLOOKUP(C6,'Admin Input Sheet'!C$9:I$18,IF(Calculations!B404="FL",5,7),FALSE),"Store")="Customer",Calculations!B$410,Calculations!B$408)))) -> 0 | AY6: =K6 -> 0 | BA6: =IF(N6="No","Customer Declined",IF($I6>0,N6,"NO")) -> NO | BB6: =IF(AND(I6>0,N6="No"),"Customer Declined","No") -> No | BD6: =IF($I6>0,R6,"No") -> No | BF6: =IF($I6>0,T6,"No") -> No | BH6: =IF($I6>0,V6,"No") -> No | BJ6: =IF($I6>0,X6,"No") -> No
A7: Additional Product Sale | P7: =IF(N7="no",0,I7-K7) -> 0 | AA7: =IF(I7>0,IF($BD7<>"no",IF(C7<>0,UPPER(_xlfn.CONCAT(E7," ",C7)),""),""),"") | AB7: =IF($R7<>"no",IF(I7<>0,$I7,0),0) -> 0 | AC7: =IF($R7<>"no",IF($AX7<>0,$AX7,0),0) -> 0 | AD7: =IF($R7<>"no",IF($AY7<>0,$AY7,0),0) -> 0 | AE7: =IF(I7>0,IF($BF7<>"no",IF(C7<>0,UPPER(_xlfn.CONCAT(E7," ",C7)),""),""),"") | AF7: =IF($T7<>"no",IF(I7<>0,I7,0),0) -> 0 | AG7: =IF($T7<>"no",IF($AX7<>0,$AX7,0),0) -> 0 | AH7: =IF($T7<>"no",IF($AY7<>0,$AY7,0),0) -> 0 | AI7: =IF(I7>0,IF($BH7<>"no",IF(C7<>0,UPPER(_xlfn.CONCAT(E7," ",C7)),""),""),"") | AJ7: =IF($V7<>"no",IF($I7<>0,$I7,0),0) -> 0 | AK7: =IF($V7<>"no",IF($AX7<>0,$AX7,0),0) -> 0 | AL7: =IF($V7<>"no",IF($AY7<>0,$AY7,0),0) -> 0 | AM7: =IF(I7>0,IF($BJ7<>"no",IF(C7<>0,UPPER(_xlfn.CONCAT(E7," ",C7)),""),""),"") | AN7: =IF($X7<>"no",IF($I7<>0,$I7,0),0) -> 0 | AO7: =IF($X7<>"no",IF($AX7<>0,$AX7,0),0) -> 0 | AP7: =IF($X7<>"no",IF($AY7<>0,$AY7,0),0) -> 0 | AQ7: =IF(I7>0,IF($N7<>"no",IF(C7<>0,UPPER(_xlfn.CONCAT(E7," ",C7)),""),""),"") | AR7: =IF(N7<>"no",IF($I7<>0,$I7,0),0) -> 0 | AS7: =IF(N7<>"no",IF($AX7<>0,$AX7,0),0) -> 0 | AT7: =IF($N7<>"no",IF($AY7<>0,$AY7,0),0) -> 0 | AU7: =IF(I7>0,IF($N7="no",IF(C7<>0,UPPER(_xlfn.CONCAT(E7," ",C7)),""),""),"") | AW7: =_xlfn.CONCAT(C7) | AX7: =I7*(1+IF('Costing Sheet'!M6="Tax Exempt",0,IF(IFERROR(VLOOKUP(C7,'Admin Input Sheet'!C$9:I$18,3,FALSE),"Taxable")="Taxable",Calculations!B$404,0)+IF(IFERROR(VLOOKUP(C7,'Admin Input Sheet'!C$9:I$18,IF(Calculations!B405="FL",5,7),FALSE),"Store")="No County Tax",0,IF(IFERROR(VLOOKUP(C7,'Admin Input Sheet'!C$9:I$18,IF(Calculations!B405="FL",5,7),FALSE),"Store")="Customer",Calculations!B$410,Calculations!B$408)))) -> 0 | AY7: =K7 -> 0 | BA7: =IF(N7="No","Customer Declined",IF($I7>0,N7,"NO")) -> NO | BB7: =IF(AND(I7>0,N7="No"),"Customer Declined","No") -> No | BD7: =IF($I7>0,R7,"No") -> No | BF7: =IF($I7>0,T7,"No") -> No | BH7: =IF($I7>0,V7,"No") -> No | BJ7: =IF($I7>0,X7,"No") -> No
A8: Additional Product Sale | P8: =IF(N8="no",0,I8-K8) -> 0 | AA8: =IF(I8>0,IF($BD8<>"no",IF(C8<>0,UPPER(_xlfn.CONCAT(E8," ",C8)),""),""),"") | AB8: =IF($R8<>"no",IF(I8<>0,$I8,0),0) -> 0 | AC8: =IF($R8<>"no",IF($AX8<>0,$AX8,0),0) -> 0 | AD8: =IF($R8<>"no",IF($AY8<>0,$AY8,0),0) -> 0 | AE8: =IF(I8>0,IF($BF8<>"no",IF(C8<>0,UPPER(_xlfn.CONCAT(E8," ",C8)),""),""),"") | AF8: =IF($T8<>"no",IF(I8<>0,I8,0),0) -> 0 | AG8: =IF($T8<>"no",IF($AX8<>0,$AX8,0),0) -> 0 | AH8: =IF($T8<>"no",IF($AY8<>0,$AY8,0),0) -> 0 | AI8: =IF(I8>0,IF($BH8<>"no",IF(C8<>0,UPPER(_xlfn.CONCAT(E8," ",C8)),""),""),"") | AJ8: =IF($V8<>"no",IF($I8<>0,$I8,0),0) -> 0 | AK8: =IF($V8<>"no",IF($AX8<>0,$AX8,0),0) -> 0 | AL8: =IF($V8<>"no",IF($AY8<>0,$AY8,0),0) -> 0 | AM8: =IF(I8>0,IF($BJ8<>"no",IF(C8<>0,UPPER(_xlfn.CONCAT(E8," ",C8)),""),""),"") | AN8: =IF($X8<>"no",IF($I8<>0,$I8,0),0) -> 0 | AO8: =IF($X8<>"no",IF($AX8<>0,$AX8,0),0) -> 0 | AP8: =IF($X8<>"no",IF($AY8<>0,$AY8,0),0) -> 0 | AQ8: =IF(I8>0,IF($N8<>"no",IF(C8<>0,UPPER(_xlfn.CONCAT(E8," ",C8)),""),""),"") | AR8: =IF(N8<>"no",IF($I8<>0,$I8,0),0) -> 0 | AS8: =IF(N8<>"no",IF($AX8<>0,$AX8,0),0) -> 0 | AT8: =IF($N8<>"no",IF($AY8<>0,$AY8,0),0) -> 0 | AU8: =IF(I8>0,IF($N8="no",IF(C8<>0,UPPER(_xlfn.CONCAT(E8," ",C8)),""),""),"") | AW8: =_xlfn.CONCAT(C8) | AX8: =I8*(1+IF('Costing Sheet'!M7="Tax Exempt",0,IF(IFERROR(VLOOKUP(C8,'Admin Input Sheet'!C$9:I$18,3,FALSE),"Taxable")="Taxable",Calculations!B$404,0)+IF(IFERROR(VLOOKUP(C8,'Admin Input Sheet'!C$9:I$18,IF(Calculations!B406="FL",5,7),FALSE),"Store")="No County Tax",0,IF(IFERROR(VLOOKUP(C8,'Admin Input Sheet'!C$9:I$18,IF(Calculations!B406="FL",5,7),FALSE),"Store")="Customer",Calculations!B$410,Calculations!B$408)))) -> 0 | AY8: =K8 -> 0 | BA8: =IF(N8="No","Customer Declined",IF($I8>0,N8,"NO")) -> NO | BB8: =IF(AND(I8>0,N8="No"),"Customer Declined","No") -> No | BD8: =IF($I8>0,R8,"No") -> No | BF8: =IF($I8>0,T8,"No") -> No | BH8: =IF($I8>0,V8,"No") -> No | BJ8: =IF($I8>0,X8,"No") -> No
A9: Additional Product Sale | P9: =IF(N9="no",0,I9-K9) -> 0 | AA9: =IF(I9>0,IF($BD9<>"no",IF(C9<>0,UPPER(_xlfn.CONCAT(E9," ",C9)),""),""),"") | AB9: =IF($R9<>"no",IF(I9<>0,$I9,0),0) -> 0 | AC9: =IF($R9<>"no",IF($AX9<>0,$AX9,0),0) -> 0 | AD9: =IF($R9<>"no",IF($AY9<>0,$AY9,0),0) -> 0 | AE9: =IF(I9>0,IF($BF9<>"no",IF(C9<>0,UPPER(_xlfn.CONCAT(E9," ",C9)),""),""),"") | AF9: =IF($T9<>"no",IF(I9<>0,I9,0),0) -> 0 | AG9: =IF($T9<>"no",IF($AX9<>0,$AX9,0),0) -> 0 | AH9: =IF($T9<>"no",IF($AY9<>0,$AY9,0),0) -> 0 | AI9: =IF(I9>0,IF($BH9<>"no",IF(C9<>0,UPPER(_xlfn.CONCAT(E9," ",C9)),""),""),"") | AJ9: =IF($V9<>"no",IF($I9<>0,$I9,0),0) -> 0 | AK9: =IF($V9<>"no",IF($AX9<>0,$AX9,0),0) -> 0 | AL9: =IF($V9<>"no",IF($AY9<>0,$AY9,0),0) -> 0 | AM9: =IF(I9>0,IF($BJ9<>"no",IF(C9<>0,UPPER(_xlfn.CONCAT(E9," ",C9)),""),""),"") | AN9: =IF($X9<>"no",IF($I9<>0,$I9,0),0) -> 0 | AO9: =IF($X9<>"no",IF($AX9<>0,$AX9,0),0) -> 0 | AP9: =IF($X9<>"no",IF($AY9<>0,$AY9,0),0) -> 0 | AQ9: =IF(I9>0,IF($N9<>"no",IF(C9<>0,UPPER(_xlfn.CONCAT(E9," ",C9)),""),""),"") | AR9: =IF(N9<>"no",IF($I9<>0,$I9,0),0) -> 0 | AS9: =IF(N9<>"no",IF($AX9<>0,$AX9,0),0) -> 0 | AT9: =IF($N9<>"no",IF($AY9<>0,$AY9,0),0) -> 0 | AU9: =IF(I9>0,IF($N9="no",IF(C9<>0,UPPER(_xlfn.CONCAT(E9," ",C9)),""),""),"") | AW9: =_xlfn.CONCAT(C9) | AX9: =I9*(1+IF('Costing Sheet'!M8="Tax Exempt",0,IF(IFERROR(VLOOKUP(C9,'Admin Input Sheet'!C$9:I$18,3,FALSE),"Taxable")="Taxable",Calculations!B$404,0)+IF(IFERROR(VLOOKUP(C9,'Admin Input Sheet'!C$9:I$18,IF(Calculations!B407="FL",5,7),FALSE),"Store")="No County Tax",0,IF(IFERROR(VLOOKUP(C9,'Admin Input Sheet'!C$9:I$18,IF(Calculations!B407="FL",5,7),FALSE),"Store")="Customer",Calculations!B$410,Calculations!B$408)))) -> 0 | AY9: =K9 -> 0 | BA9: =IF(N9="No","Customer Declined",IF($I9>0,N9,"NO")) -> NO | BB9: =IF(AND(I9>0,N9="No"),"Customer Declined","No") -> No | BD9: =IF($I9>0,R9,"No") -> No | BF9: =IF($I9>0,T9,"No") -> No | BH9: =IF($I9>0,V9,"No") -> No | BJ9: =IF($I9>0,X9,"No") -> No
A10: Additional Product Sale | P10: =IF(N10="no",0,I10-K10) -> 0 | AA10: =IF(I10>0,IF($BD10<>"no",IF(C10<>0,UPPER(_xlfn.CONCAT(E10," ",C10)),""),""),"") | AB10: =IF($R10<>"no",IF(I10<>0,$I10,0),0) -> 0 | AC10: =IF($R10<>"no",IF($AX10<>0,$AX10,0),0) -> 0 | AD10: =IF($R10<>"no",IF($AY10<>0,$AY10,0),0) -> 0 | AE10: =IF(I10>0,IF($BF10<>"no",IF(C10<>0,UPPER(_xlfn.CONCAT(E10," ",C10)),""),""),"") | AF10: =IF($T10<>"no",IF(I10<>0,I10,0),0) -> 0 | AG10: =IF($T10<>"no",IF($AX10<>0,$AX10,0),0) -> 0 | AH10: =IF($T10<>"no",IF($AY10<>0,$AY10,0),0) -> 0 | AI10: =IF(I10>0,IF($BH10<>"no",IF(C10<>0,UPPER(_xlfn.CONCAT(E10," ",C10)),""),""),"") | AJ10: =IF($V10<>"no",IF($I10<>0,$I10,0),0) -> 0 | AK10: =IF($V10<>"no",IF($AX10<>0,$AX10,0),0) -> 0 | AL10: =IF($V10<>"no",IF($AY10<>0,$AY10,0),0) -> 0 | AM10: =IF(I10>0,IF($BJ10<>"no",IF(C10<>0,UPPER(_xlfn.CONCAT(E10," ",C10)),""),""),"") | AN10: =IF($X10<>"no",IF($I10<>0,$I10,0),0) -> 0 | AO10: =IF($X10<>"no",IF($AX10<>0,$AX10,0),0) -> 0 | AP10: =IF($X10<>"no",IF($AY10<>0,$AY10,0),0) -> 0 | AQ10: =IF(I10>0,IF($N10<>"no",IF(C10<>0,UPPER(_xlfn.CONCAT(E10," ",C10)),""),""),"") | AR10: =IF(N10<>"no",IF($I10<>0,$I10,0),0) -> 0 | AS10: =IF(N10<>"no",IF($AX10<>0,$AX10,0),0) -> 0 | AT10: =IF($N10<>"no",IF($AY10<>0,$AY10,0),0) -> 0 | AU10: =IF(I10>0,IF($N10="no",IF(C10<>0,UPPER(_xlfn.CONCAT(E10," ",C10)),""),""),"") | AW10: =_xlfn.CONCAT(C10) | AX10: =I10*(1+IF('Costing Sheet'!M9="Tax Exempt",0,IF(IFERROR(VLOOKUP(C10,'Admin Input Sheet'!C$9:I$18,3,FALSE),"Taxable")="Taxable",Calculations!B$404,0)+IF(IFERROR(VLOOKUP(C10,'Admin Input Sheet'!C$9:I$18,IF(Calculations!B408="FL",5,7),FALSE),"Store")="No County Tax",0,IF(IFERROR(VLOOKUP(C10,'Admin Input Sheet'!C$9:I$18,IF(Calculations!B408="FL",5,7),FALSE),"Store")="Customer",Calculations!B$410,Calculations!B$408)))) -> 0 | AY10: =K10 -> 0 | BA10: =IF(N10="No","Customer Declined",IF($I10>0,N10,"NO")) -> NO | BB10: =IF(AND(I10>0,N10="No"),"Customer Declined","No") -> No | BD10: =IF($I10>0,R10,"No") -> No | BF10: =IF($I10>0,T10,"No") -> No | BH10: =IF($I10>0,V10,"No") -> No | BJ10: =IF($I10>0,X10,"No") -> No
A11: Additional Product Sale | P11: =IF(N11="no",0,I11-K11) -> 0 | AA11: =IF(I11>0,IF($BD11<>"no",IF(C11<>0,UPPER(_xlfn.CONCAT(E11," ",C11)),""),""),"") | AB11: =IF($R11<>"no",IF(I11<>0,$I11,0),0) -> 0 | AC11: =IF($R11<>"no",IF($AX11<>0,$AX11,0),0) -> 0 | AD11: =IF($R11<>"no",IF($AY11<>0,$AY11,0),0) -> 0 | AE11: =IF(I11>0,IF($BF11<>"no",IF(C11<>0,UPPER(_xlfn.CONCAT(E11," ",C11)),""),""),"") | AF11: =IF($T11<>"no",IF(I11<>0,I11,0),0) -> 0 | AG11: =IF($T11<>"no",IF($AX11<>0,$AX11,0),0) -> 0 | AH11: =IF($T11<>"no",IF($AY11<>0,$AY11,0),0) -> 0 | AI11: =IF(I11>0,IF($BH11<>"no",IF(C11<>0,UPPER(_xlfn.CONCAT(E11," ",C11)),""),""),"") | AJ11: =IF($V11<>"no",IF($I11<>0,$I11,0),0) -> 0 | AK11: =IF($V11<>"no",IF($AX11<>0,$AX11,0),0) -> 0 | AL11: =IF($V11<>"no",IF($AY11<>0,$AY11,0),0) -> 0 | AM11: =IF(I11>0,IF($BJ11<>"no",IF(C11<>0,UPPER(_xlfn.CONCAT(E11," ",C11)),""),""),"") | AN11: =IF($X11<>"no",IF($I11<>0,$I11,0),0) -> 0 | AO11: =IF($X11<>"no",IF($AX11<>0,$AX11,0),0) -> 0 | AP11: =IF($X11<>"no",IF($AY11<>0,$AY11,0),0) -> 0 | AQ11: =IF(I11>0,IF($N11<>"no",IF(C11<>0,UPPER(_xlfn.CONCAT(E11," ",C11)),""),""),"") | AR11: =IF(N11<>"no",IF($I11<>0,$I11,0),0) -> 0 | AS11: =IF(N11<>"no",IF($AX11<>0,$AX11,0),0) -> 0 | AT11: =IF($N11<>"no",IF($AY11<>0,$AY11,0),0) -> 0 | AU11: =IF(I11>0,IF($N11="no",IF(C11<>0,UPPER(_xlfn.CONCAT(E11," ",C11)),""),""),"") | AW11: =_xlfn.CONCAT(C11) | AX11: =I11*(1+IF('Costing Sheet'!M10="Tax Exempt",0,IF(IFERROR(VLOOKUP(C11,'Admin Input Sheet'!C$9:I$18,3,FALSE),"Taxable")="Taxable",Calculations!B$404,0)+IF(IFERROR(VLOOKUP(C11,'Admin Input Sheet'!C$9:I$18,IF(Calculations!B409="FL",5,7),FALSE),"Store")="No County Tax",0,IF(IFERROR(VLOOKUP(C11,'Admin Input Sheet'!C$9:I$18,IF(Calculations!B409="FL",5,7),FALSE),"Store")="Customer",Calculations!B$410,Calculations!B$408)))) -> 0 | AY11: =K11 -> 0 | BA11: =IF(N11="No","Customer Declined",IF($I11>0,N11,"NO")) -> NO | BB11: =IF(AND(I11>0,N11="No"),"Customer Declined","No") -> No | BD11: =IF($I11>0,R11,"No") -> No | BF11: =IF($I11>0,T11,"No") -> No | BH11: =IF($I11>0,V11,"No") -> No | BJ11: =IF($I11>0,X11,"No") -> No
A12: Additional Product Sale | P12: =IF(N12="no",0,I12-K12) -> 0 | AA12: =IF(I12>0,IF($BD12<>"no",IF(C12<>0,UPPER(_xlfn.CONCAT(E12," ",C12)),""),""),"") | AB12: =IF($R12<>"no",IF(I12<>0,$I12,0),0) -> 0 | AC12: =IF($R12<>"no",IF($AX12<>0,$AX12,0),0) -> 0 | AD12: =IF($R12<>"no",IF($AY12<>0,$AY12,0),0) -> 0 | AE12: =IF(I12>0,IF($BF12<>"no",IF(C12<>0,UPPER(_xlfn.CONCAT(E12," ",C12)),""),""),"") | AF12: =IF($T12<>"no",IF(I12<>0,I12,0),0) -> 0 | AG12: =IF($T12<>"no",IF($AX12<>0,$AX12,0),0) -> 0 | AH12: =IF($T12<>"no",IF($AY12<>0,$AY12,0),0) -> 0 | AI12: =IF(I12>0,IF($BH12<>"no",IF(C12<>0,UPPER(_xlfn.CONCAT(E12," ",C12)),""),""),"") | AJ12: =IF($V12<>"no",IF($I12<>0,$I12,0),0) -> 0 | AK12: =IF($V12<>"no",IF($AX12<>0,$AX12,0),0) -> 0 | AL12: =IF($V12<>"no",IF($AY12<>0,$AY12,0),0) -> 0 | AM12: =IF(I12>0,IF($BJ12<>"no",IF(C12<>0,UPPER(_xlfn.CONCAT(E12," ",C12)),""),""),"") | AN12: =IF($X12<>"no",IF($I12<>0,$I12,0),0) -> 0 | AO12: =IF($X12<>"no",IF($AX12<>0,$AX12,0),0) -> 0 | AP12: =IF($X12<>"no",IF($AY12<>0,$AY12,0),0) -> 0 | AQ12: =IF(I12>0,IF($N12<>"no",IF(C12<>0,UPPER(_xlfn.CONCAT(E12," ",C12)),""),""),"") | AR12: =IF(N12<>"no",IF($I12<>0,$I12,0),0) -> 0 | AS12: =IF(N12<>"no",IF($AX12<>0,$AX12,0),0) -> 0 | AT12: =IF($N12<>"no",IF($AY12<>0,$AY12,0),0) -> 0 | AU12: =IF(I12>0,IF($N12="no",IF(C12<>0,UPPER(_xlfn.CONCAT(E12," ",C12)),""),""),"") | AW12: =_xlfn.CONCAT(C12) | AX12: =I12*(1+IF('Costing Sheet'!M11="Tax Exempt",0,IF(IFERROR(VLOOKUP(C12,'Admin Input Sheet'!C$9:I$18,3,FALSE),"Taxable")="Taxable",Calculations!B$404,0)+IF(IFERROR(VLOOKUP(C12,'Admin Input Sheet'!C$9:I$18,IF(Calculations!B410="FL",5,7),FALSE),"Store")="No County Tax",0,IF(IFERROR(VLOOKUP(C12,'Admin Input Sheet'!C$9:I$18,IF(Calculations!B410="FL",5,7),FALSE),"Store")="Customer",Calculations!B$410,Calculations!B$408)))) -> 0 | AY12: =K12 -> 0 | BA12: =IF(N12="No","Customer Declined",IF($I12>0,N12,"NO")) -> NO | BB12: =IF(AND(I12>0,N12="No"),"Customer Declined","No") -> No | BD12: =IF($I12>0,R12,"No") -> No | BF12: =IF($I12>0,T12,"No") -> No | BH12: =IF($I12>0,V12,"No") -> No | BJ12: =IF($I12>0,X12,"No") -> No
A13: Additional Product Sale | P13: =IF(N13="no",0,I13-K13) -> 0 | AA13: =IF(I13>0,IF($BD13<>"no",IF(C13<>0,UPPER(_xlfn.CONCAT(E13," ",C13)),""),""),"") | AB13: =IF($R13<>"no",IF(I13<>0,$I13,0),0) -> 0 | AC13: =IF($R13<>"no",IF($AX13<>0,$AX13,0),0) -> 0 | AD13: =IF($R13<>"no",IF($AY13<>0,$AY13,0),0) -> 0 | AE13: =IF(I13>0,IF($BF13<>"no",IF(C13<>0,UPPER(_xlfn.CONCAT(E13," ",C13)),""),""),"") | AF13: =IF($T13<>"no",IF(I13<>0,I13,0),0) -> 0 | AG13: =IF($T13<>"no",IF($AX13<>0,$AX13,0),0) -> 0 | AH13: =IF($T13<>"no",IF($AY13<>0,$AY13,0),0) -> 0 | AI13: =IF(I13>0,IF($BH13<>"no",IF(C13<>0,UPPER(_xlfn.CONCAT(E13," ",C13)),""),""),"") | AJ13: =IF($V13<>"no",IF($I13<>0,$I13,0),0) -> 0 | AK13: =IF($V13<>"no",IF($AX13<>0,$AX13,0),0) -> 0 | AL13: =IF($V13<>"no",IF($AY13<>0,$AY13,0),0) -> 0 | AM13: =IF(I13>0,IF($BJ13<>"no",IF(C13<>0,UPPER(_xlfn.CONCAT(E13," ",C13)),""),""),"") | AN13: =IF($X13<>"no",IF($I13<>0,$I13,0),0) -> 0 | AO13: =IF($X13<>"no",IF($AX13<>0,$AX13,0),0) -> 0 | AP13: =IF($X13<>"no",IF($AY13<>0,$AY13,0),0) -> 0 | AQ13: =IF(I13>0,IF($N13<>"no",IF(C13<>0,UPPER(_xlfn.CONCAT(E13," ",C13)),""),""),"") | AR13: =IF(N13<>"no",IF($I13<>0,$I13,0),0) -> 0 | AS13: =IF(N13<>"no",IF($AX13<>0,$AX13,0),0) -> 0 | AT13: =IF($N13<>"no",IF($AY13<>0,$AY13,0),0) -> 0 | AU13: =IF(I13>0,IF($N13="no",IF(C13<>0,UPPER(_xlfn.CONCAT(E13," ",C13)),""),""),"") | AW13: =_xlfn.CONCAT(C13) | AX13: =I13*(1+IF('Costing Sheet'!M12="Tax Exempt",0,IF(IFERROR(VLOOKUP(C13,'Admin Input Sheet'!C$9:I$18,3,FALSE),"Taxable")="Taxable",Calculations!B$404,0)+IF(IFERROR(VLOOKUP(C13,'Admin Input Sheet'!C$9:I$18,IF(Calculations!B411="FL",5,7),FALSE),"Store")="No County Tax",0,IF(IFERROR(VLOOKUP(C13,'Admin Input Sheet'!C$9:I$18,IF(Calculations!B411="FL",5,7),FALSE),"Store")="Customer",Calculations!B$410,Calculations!B$408)))) -> 0 | AY13: =K13 -> 0 | BA13: =IF(N13="No","Customer Declined",IF($I13>0,N13,"NO")) -> NO | BB13: =IF(AND(I13>0,N13="No"),"Customer Declined","No") -> No | BD13: =IF($I13>0,R13,"No") -> No | BF13: =IF($I13>0,T13,"No") -> No | BH13: =IF($I13>0,V13,"No") -> No | BJ13: =IF($I13>0,X13,"No") -> No
P14: PLAN PRICE | R14: =AB14 -> 0 | T14: =AF14 -> 0 | V14: =AJ14 -> 0 | X14: =AN14 -> 0 | AA14: totals | AB14: =SUM(AB4:AB13) -> 0 | AC14: =SUM(AC4:AC13) -> 0 | AD14: =SUM(AD4:AD13) -> 0 | AE14: totals | AF14: =SUM(AF4:AF13) -> 0 | AG14: =SUM(AG4:AG13) -> 0 | AH14: =SUM(AH4:AH13) -> 0 | AI14: totals | AJ14: =SUM(AJ4:AJ13) -> 0 | AK14: =SUM(AK4:AK13) -> 0 | AL14: =SUM(AL4:AL13) -> 0 | AM14: totals | AN14: =SUM(AN4:AN13) -> 0 | AO14: =SUM(AO4:AO13) -> 0 | AP14: =SUM(AP4:AP13) -> 0 | AQ14: totala | AR14: =SUM(AR4:AR13) -> 0 | AS14: =SUM(AS4:AS13) -> 0 | AT14: =SUM(AT4:AT13) -> 0 | AX14: =I14*(1+IF('Costing Sheet'!M13="Tax Exempt",0,IF(IFERROR(VLOOKUP(C14,'Admin Input Sheet'!C$9:I$18,3,FALSE),"Taxable")="Taxable",Calculations!B$404,0)+IF(IFERROR(VLOOKUP(C14,'Admin Input Sheet'!C$9:I$18,IF(Calculations!B412="FL",5,7),FALSE),"Store")="No County Tax",0,IF(IFERROR(VLOOKUP(C14,'Admin Input Sheet'!C$9:I$18,IF(Calculations!B412="FL",5,7),FALSE),"Store")="Customer",Calculations!B$410,Calculations!B$408)))) -> 0
A15: Include Kubota Insurance on Final Invocie and Payments | G15: Kubota Insurance Amount overide
A16: Agreed and Approved Finance Term
A17: Agreed and Approved Finance Rate
A18: Days to First Payment | I18: Name of Non Listed Finance Source
A19: Funding Lender | N19: DELAYED PAYMENT DATE
A20: Buy Rate | N20: Finance Spread | P20: =+Calculations!B609 -> 0 | BA20: {=IFERROR(INDEX('Finance Manager Input Sheet'!$AU$4:$AU$13, SMALL(IF('Finance Manager Input Sheet'!$BA$4:$BA$13="Customer Declined", ROW('Finance Manager Input Sheet'!$AU$4:$AU$13)-ROW('Finance Manager Input Sheet'!$AU$4)+1), ROW(C6))), "")} | BB20: {=IFERROR(INDEX('Finance Manager Input Sheet'!$AU$4:$AU$13, SMALL(IF('Finance Manager Input Sheet'!$BA$4:$BA$13="Customer Declined", ROW('Finance Manager Input Sheet'!$AU$4:$AU$13)-ROW('Finance Manager Input Sheet'!$AU$4)+1), ROW(D6))), "")}
A21: Rate Participation Percentage | BA21: {=IFERROR(INDEX('Finance Manager Input Sheet'!$AU$4:$AU$13, SMALL(IF('Finance Manager Input Sheet'!$BA$4:$BA$13="Customer Declined", ROW('Finance Manager Input Sheet'!$AU$4:$AU$13)-ROW('Finance Manager Input Sheet'!$AU$4)+1), ROW(C7))), "")} | BB21: {=IFERROR(INDEX('Finance Manager Input Sheet'!$AU$4:$AU$13, SMALL(IF('Finance Manager Input Sheet'!$BA$4:$BA$13="Customer Declined", ROW('Finance Manager Input Sheet'!$AU$4:$AU$13)-ROW('Finance Manager Input Sheet'!$AU$4)+1), ROW(D7))), "")}
A22: FLAT FEE DUE FROM LENDER | N22: Flat Fee From Lender | P22: =+C22 -> 0
A23: Cash in Lieu if not listed on incentives | E23: From What Party | I23: APPLICABLE TO WHICH UNIT | P23: =+C23 -> 0
A24: Cash in Lieu if not listed on incentives | E24: From What Party | I24: APPLICABLE TO WHICH UNIT | P24: =+C24 -> 0
A25: Cash in Lieu if not listed on incentives | E25: From What Party | I25: APPLICABLE TO WHICH UNIT | P25: =+C25 -> 0
A26: Rate Buydown cost
N27: Back End Margin | P27: =SUM(P4:P25) -> 0
A28: LOAN NUMBER

Sheet Admin Input Sheet
A3: Monthly KTC RATE 1 | C3: 0.0013
A4: Monthly KTC Rate 2 | C4: 0.002
A5: Monthly KTC Rate 3 | C5: 0
A6: Zero Cost Rate | C6: 0
C8: Name | E8: Taxable | G8: Florida County Tax Level | I8: Georgia County Tax Level
A9: Product 1
A10: Product 2
A11: Product 3
A12: Product 4
A13: Product 5
A14: Product 6
A15: Product 7
A16: Product 8
A17: Product 9
A18: Product 10
C20: Amount | E20: Cutoff | G20: Aggregate or Individual
A21: Lowest cutoff Dealer fee | C21: 0 | E21: 3999 | G21: Individual
A22: Second lowest cutoff dlr fee | C22: 299 | E22: 9999 | G22: Aggregate
A23: third lowest cutoff dealer fee | C23: 649 | E23: 39999 | G23: Aggregate
A24: fourth lowest cutoff dealer fee | C24: 849 | E24: 79999 | G24: Aggregate
A25: fifth lowest cutof dealer fee | C25: 849 | E25: 99999 | G25: Aggregate
A26: highest level of dealer fee | C26: 1149 | G26: Aggregate
E27: State Tax Level | G27: County Tax Level
A28: Florida Battery Fee per unit | C28: 1.5 | E28: Customer | G28: No County Tax
A29: Georgia Battery Fee per unit | C29: 0 | E29: No State Tax | G29: No County Tax
A30: Florida Tire Tax per unit | C30: 1 | E30: Customer | G30: No County Tax
A31: Georgia Tire Tax per Unit | C31: 0 | E31: No State Tax | G31: No County Tax
A33: Title of Document Fee | C33: Dealer Fee
C34: State Taxable | E34: Florida County Tax Level | G34: Georgia County Tax Level
A35: Freight Charge | C35: Taxable | E35: Customer | G35: Customer
A36: Prep Charge | C36: Taxable | E36: Customer | G36: Customer
A37: DMV Charges | C37: Non Taxable | E37: No County Tax | G37: No County Tax
A38: Title Fees | C38: Non Taxable | E38: No County Tax | G38: No County Tax
A39: Tag Fees | C39: Non Taxable | E39: No County Tax | G39: No County Tax
A41: Florida State Sales Tax Rate | C41: 0.06
A42: Georgia State Sales Tax Rate | C42: 0.04
A43: Florida Per Item Sales Tax Cap | C43: 5000
A44: Georgia Per Item Sales tax Cap | C44: 1000000

Sheet Rates for Quote
A2: Rates For Matrix
C3: Regular Equipment Rate | D3: Mower And UTV Rate | E3: Prime Rate | F3: Overide Rate
A4: Term 1
A6: Term 2
A8: Term 3
A10: Down Payment 1
A11: Down Payment 2
A12: Down Payment 3

Sheet Quote
B2: CAIRO, GA | CHIEFLAND,FL. | DELAND, FL. | K2: CRYSTAL | Q2: =+Calculations!$B$568
B4: HASTINGS, FL | HOMOSASSA, FL | JACKSONVILLE, FL | LECANTO, FL | Q4: =+Calculations!$B$569
Q5: =Calculations!B570
B6: LEESBURG, FL. | LIVE OAK, FL. | MADISON, FL | K6: TRACTOR & EQUIPMENT
B8: MIAMI, FL. | PALATKA, FL. | PANAMA CITY, FL | OCALA, FL
B10: SPRING HILL, FL. | STARKE, FL. | TALLAHASSEE, FL | K10: =+Calculations!B572 -> CRYSTALTRACTOR.COM | Q10: =Calculations!B571
B11: CUSTOMER:
C12: =IF('Customer Input Screen'!I10<>"",UPPER('Customer Input Screen'!I10),"") | L12: CUSTOMER CELL | O12: =+'Customer Input Screen'!I22 | Q12: QUOTE NUMBER | S12: =+'Sales Input Sheet'!C11 -> 0
C13: =IF(Calculations!B3<>"",UPPER(Calculations!B3),"") | L13: CUSTOMER WORK | O13: =+'Customer Input Screen'!I23 | Q13: QUOTE DATE | S13: =+'Costing Sheet'!C15 -> 0
C15: =IF('Customer Input Screen'!I14<>"",UPPER('Customer Input Screen'!I14),"") | L15: CUSTOMER HOME | O15: =+'Customer Input Screen'!I24 | Q15: SALES PERSON | S15: =IF('Sales Input Sheet'!C15<>"",UPPER('Sales Input Sheet'!C15),"")
C16: =IF('Customer Input Screen'!I15<>"",UPPER('Customer Input Screen'!I15),"") | L16: =+Calculations!$B$602 | Q16: =UPPER('Costing Sheet'!C17) | S16: =UPPER('Costing Sheet'!E17)
C17: =+Calculations!$B$601 | L17: PURCHASE ORDER NO. | O17: =UPPER('Costing Sheet'!U19)
B19: Customer hereby orders the following described machinery and equipment from Crystal Tractor, LLC, Crystal Equipment, LLC or Crystal Motorsports, LLC. Upon acceptance by Seller and Customer, this order becomes a agreement to endeavor to conclude the purchase and sale of goods upon the terms and conditions set forth herein and on the reverse of this order.
Q21: DEALER SUGGESTED PRICE | S21: DISCOUNT | U21: NET SELLING PRICE
C22: STOCK NUMBER | I22: MAKE | L22: MODEL | O22: SERIAL NUMBER
C23: =Calculations!B451 | I23: =Calculations!B6 | L23: =Calculations!B7 | O23: =Calculations!B8 | Q23: =+'Costing Sheet'!I$22 -> 0 | S23: =-'Costing Sheet'!K$22 -> 0 | U23: =+Calculations!B$526 -> 0
J24: =Calculations!B9
J25: =+Calculations!B12
C27: =Calculations!B452 | I27: =Calculations!B18 | L27: =Calculations!B19 | O27: =Calculations!B20 | Q27: =+'Costing Sheet'!I$23 -> 0 | S27: =-'Costing Sheet'!K$23 -> 0 | U27: =+Calculations!B$527 -> 0
J28: =Calculations!B21
J29: =+Calculations!B24
C31: =Calculations!B453 | I31: =Calculations!B30 | L31: =Calculations!B31 | O31: =Calculations!B32 | Q31: =+'Costing Sheet'!I$24 -> 0 | S31: =-'Costing Sheet'!K$24 -> 0 | U31: =+Calculations!B$528 -> 0
J32: =Calculations!B33
J33: =+Calculations!B36
C35: =Calculations!B454 | I35: =Calculations!B42 | L35: =Calculations!B43 | O35: =Calculations!B44 | Q35: =+'Costing Sheet'!I$25 -> 0 | S35: =-'Costing Sheet'!K$25 -> 0 | U35: =+Calculations!B$529 -> 0
J36: =Calculations!B45
J37: =+Calculations!B48
C39: =Calculations!B455 | I39: =Calculations!B54 | L39: =Calculations!B55 | O39: =Calculations!B56 | Q39: =+'Costing Sheet'!I$26 -> 0 | S39: =-'Costing Sheet'!K$26 -> 0 | U39: =+Calculations!B$530 -> 0
J40: =Calculations!B57
J41: =+Calculations!B60
C43: =Calculations!B456 | I43: =Calculations!B66 | L43: =Calculations!B67 | O43: =Calculations!B68 | Q43: =+'Costing Sheet'!I$27 -> 0 | S43: =-'Costing Sheet'!K$27 -> 0 | U43: =+Calculations!B$531 -> 0
J44: =Calculations!B69
J45: =+Calculations!B72
C47: =Calculations!B457 | I47: =Calculations!B78 | L47: =Calculations!B79 | O47: =Calculations!B80 | Q47: =+'Costing Sheet'!I$28 -> 0 | S47: =-'Costing Sheet'!K$28 -> 0 | U47: =+Calculations!B$532 -> 0
J48: =Calculations!B81
J49: =+Calculations!B84
C51: =Calculations!B458 | I51: =Calculations!B90 | L51: =Calculations!B91 | O51: =Calculations!B92 | Q51: =+'Costing Sheet'!I$29 -> 0 | S51: =-'Costing Sheet'!K$29 -> 0 | U51: =+Calculations!B$533 -> 0
J52: =Calculations!B93
J53: =+Calculations!B96
C55: =Calculations!B459 | I55: =Calculations!B102 | L55: =Calculations!B103 | O55: =Calculations!B104 | Q55: =+'Costing Sheet'!I$30 -> 0 | S55: =-'Costing Sheet'!K$30 -> 0 | U55: =+Calculations!B$534 -> 0
J56: =Calculations!B105
J57: =+Calculations!B108
C59: =Calculations!B460 | I59: =Calculations!B114 | L59: =Calculations!B115 | O59: =Calculations!B116 | Q59: =+'Costing Sheet'!I$31 -> 0 | S59: =-'Costing Sheet'!K$31 -> 0 | U59: =+Calculations!B$535 -> 0
J60: =Calculations!B117
J61: =+Calculations!B120
C62: =UPPER('Sales Input Sheet'!E55)
B66: TRADE IN | I66: MAKE | L66: MODEL | O66: SERIAL NUMBER | Q66: DESCRIPTION | S66: ALLOWANCE | U66: PAYOFF
I67: =+Calculations!B504 | L67: =+Calculations!B506 | O67: =+Calculations!B502 | Q67: =Calculations!B514 | S67: =Calculations!B498 -> 0 | U67: =Calculations!B500 -> 0
I68: =+Calculations!B505 | L68: =+Calculations!B507 | O68: =+Calculations!B503 | Q68: =Calculations!B515 | S68: =Calculations!B499 -> 0 | U68: =Calculations!B501 -> 0
I69: =+Calculations!B694 | L69: =+Calculations!B698 | O69: =+Calculations!B690 | Q69: =+Calculations!B678 | S69: =+Calculations!B682 -> 0 | U69: =+Calculations!B686 -> 0
I70: =+Calculations!B695 | L70: =+Calculations!B699 | O70: =+Calculations!B691 | Q70: =+Calculations!B679 | S70: =+Calculations!B683 -> 0 | U70: =+Calculations!B687 -> 0
I71: =+Calculations!B696 | L71: =+Calculations!B700 | O71: =+Calculations!B692 | Q71: =+Calculations!B680 | S71: =+Calculations!B684 -> 0 | U71: =+Calculations!B688 -> 0
I72: =+Calculations!B697 | L72: =+Calculations!B701 | O72: =+Calculations!B693 | Q72: =+Calculations!B681 | S72: =+Calculations!B685 -> 0 | U72: =+Calculations!B689 -> 0
B75: Down Payment | H75: ='Rates for Quote'!B$4 -> 0 | N75: ='Rates for Quote'!B$6 -> 0 | R75: ='Rates for Quote'!B$8 -> 0
B77: =+Calculations!B$429 -> 0 | H77: =+Calculations!B$440 -> 0 | N77: =+Calculations!B$441 -> 0 | R77: =+Calculations!B$442 -> 0
B79: =+Calculations!B$430 -> 0 | H79: =+Calculations!B$443 -> 0 | N79: =+Calculations!B$444 -> 0 | R79: =+Calculations!B$445 -> 0
B81: =+Calculations!B$431 -> 0 | H81: =+Calculations!B$446 -> 0 | N81: =+Calculations!B$447 -> 0 | R81: =+Calculations!B$448 -> 0
B83: =UPPER(Calculations!B$415) | H83: =IF(B83="","",+Calculations!B$418) | N83: =IF(B83="","",+Calculations!B$419) | R83: =IF(B83="","",+Calculations!B$420)
B84: =_xlfn.CONCAT(Calculations!B$371,Calculations!B$376,Calculations!B$381) -> The payments presented herein are based upon interest rates available to a variety of customers based upon credit quality, down payment, collateral and other factors. The actual interest rate charged will be disclosed in the finance contract and may be higher or lower then the rates used in this illustration. For presentation purposes, month term payments are presented at an interest rate of 0.000% , month term payments are presented at an interest rate of 0.000%, month term payments are presented with an interest rate of 0.000%.
J87: =+Q2
J88: =+Q4
J89: =+Q5 | Q89: =+Q15 -> SALES PERSON | S89: =+S15
J90: =+Q10
C92: =+C12 | Q92: QUOTE NUMBER | S92: =+'Sales Input Sheet'!C11 -> 0
C93: =+C13 | Q93: QUOTE DATE | S93: =+'Costing Sheet'!C15 -> 0
C95: =+'Costing Sheet'!C19 -> 0 | F95: =+'Costing Sheet'!E19 -> 0 | O95: =+UPPER('Costing Sheet'!C17) | Q95: =UPPER('Costing Sheet'!E17)
B96: TRANSACTION SUMMARY
B97: DEALER PRICE OF ALL EQUIPMENT | L97: =+Calculations!B$310 -> 0 | N97: SUB TOTAL | U97: =+Calculations!B$319 -> 0
B98: =IF(L98=0,"","LINE ITEM DISCOUNT") | L98: =-Calculations!B$311 -> 0 | N98: TIRE FEE | U98: =+Calculations!B$386 -> 0
B99: SELLING PRICE, NET | L99: =+Calculations!B$312 -> 0 | N99: BATTERY FEE | U99: =+Calculations!B$385 -> 0
B100: TRADE VALUE | L100: =-Calculations!B$315 -> 0 | N100: DMV, TAX & TITLE FEES | U100: =+Calculations!B$439 -> 0
B101: TRADE PAYOFF | L101: =+Calculations!B$316 -> 0 | N101: DOC STAMP TAX | U101: =+'Costing Sheet'!Q15 -> 0
B102: DOCUMENT FEE (1) | L102: =+Calculations!B$302 -> 0 | N102: UCC FEE | U102: =+'Costing Sheet'!Q13 -> 0
N103: =+Calculations!$B$403 -> SALES TAX | U103: =+Calculations!$B$405 -> 0
B104: FREIGHT | L104: =+'Costing Sheet'!Q$3 -> 0 | N104: =+Calculations!$B$399 | U104: =+Calculations!$B$412 -> 0
B105: SET UP FEE (1) | L105: =+'Costing Sheet'!Q$5 -> 0 | N105: =+Calculations!$B$406 -> COUNTY SALES TAX OUT OF STATE OR NO COUNTY WAS SPECIFIED FOR CUSTOMER | U105: =+Calculations!$B$413 -> 0
B106: =+Calculations!B640 | L106: =+Calculations!B232 -> 0 | N106: =+Calculations!$B$414 | U106: =+Calculations!$B$407 -> 0
B107: =+Calculations!B641 | L107: =+Calculations!B233 -> 0 | N107: =Calculations!B651 | U107: =-Calculations!B$318 -> 0
B108: =+Calculations!B642 | L108: =+Calculations!B234 -> 0 | O108: =Calculations!$B$653
B109: =+Calculations!B643 | L109: =+Calculations!B235 -> 0
B110: =+Calculations!B644 | L110: =+Calculations!B236 -> 0
B111: =+Calculations!B645 | L111: =+Calculations!B237 -> 0
B112: =+Calculations!B646 | L112: =+Calculations!B238 -> 0
B113: =+Calculations!B647 | L113: =+Calculations!B239 -> 0
B114: =+Calculations!B648 | L114: =+Calculations!B240 -> 0
B115: =+Calculations!B649 | L115: =+Calculations!B241 -> 0
B118: SUB TOTAL | L118: =+Calculations!B$319 -> 0 | N118: =UPPER(_xlfn.CONCAT("TOTAL DUE FROM CUSTOMER",Calculations!$B$650)) -> TOTAL DUE FROM CUSTOMER | U118: =+Calculations!B$435 -> 0
B120: =Calculations!B$616 -> #DIV/0! | H120: =IF(B120="","",Calculations!B$617) -> #DIV/0!
B121: Final Transaction Terms may vary based upon financing terms approved by lenders, products selected by the customer and finalization of pricing by the Company
B122: (1) Document Fee and Set Up Fee: These charges represents cost and profit to the seller/dealer for items such as assembling, inspecting, cleaning and adjusting new and used units and preparing documents related to the sale.

Sheet Additional Items
I2: =+Calculations!$B$568
I4: =+Calculations!$B$569
I5: =Calculations!B570
I8: =Calculations!B571
Q9: QUOTE NUMBER | S9: =+'Sales Input Sheet'!C11 -> 0
Q10: INVOICE NUMBER | S10: =+'Costing Sheet'!$C$13 -> 0
B11: CUSTOMER: | Q11: INVOICE DATE | S11: ='Costing Sheet'!$C$11 -> 0
C13: =IF('Customer Input Screen'!I10<>"",UPPER('Customer Input Screen'!I10),"") | Q13: Sales Person | S13: =IF('Sales Input Sheet'!C15<>"",UPPER('Sales Input Sheet'!C15),"")
C14: =IF(Calculations!B3<>"",UPPER(Calculations!B3),"") | Q14: Customer Cell | R14: =+'Customer Input Screen'!I22
C15: =IF('Customer Input Screen'!I14<>"",UPPER('Customer Input Screen'!I14),"") | Q15: Customer Work | R15: =+'Customer Input Screen'!I23
Q16: DEALER SUGGESTED PRICE | S16: DISCOUNT | U16: NET SELLING PRICE
C17: STOCK NUMBER | F17: MAKE | I17: MODEL | L17: SERIAL NUMBER
F18: =+Calculations!B461 -> 0 | I18: =Calculations!B466 | L18: =Calculations!B471 | Q18: =+'Costing Sheet'!I$34 -> 0 | S18: =-'Costing Sheet'!K$34 -> 0 | U18: =+Calculations!B$536 -> 0
J20: =UPPER(Calculations!B125)
F22: =+Calculations!B462 -> 0 | I22: =Calculations!B467 | L22: =Calculations!B472 | Q22: =+'Costing Sheet'!I$35 -> 0 | S22: =-'Costing Sheet'!K$35 -> 0 | U22: =+Calculations!B$537 -> 0
J24: =UPPER(Calculations!B129)
F26: =+Calculations!B463 -> 0 | I26: =Calculations!B468 | L26: =Calculations!B473 | Q26: =+'Costing Sheet'!I$36 -> 0 | S26: =-'Costing Sheet'!K$36 -> 0 | U26: =+Calculations!B$538 -> 0
J28: =UPPER(Calculations!B133)
F30: =+Calculations!B464 -> 0 | I30: =Calculations!B469 | L30: =Calculations!B474 | Q30: =+'Costing Sheet'!I$37 -> 0 | S30: =-'Costing Sheet'!K$37 -> 0 | U30: =+Calculations!B$539 -> 0
J32: =UPPER(Calculations!B137)
F34: =+Calculations!B465 -> 0 | I34: =Calculations!B470 | L34: =Calculations!B475 | Q34: =+'Costing Sheet'!I$38 -> 0 | S34: =-'Costing Sheet'!K$38 -> 0 | U34: =+Calculations!B$540 -> 0
J36: =UPPER(Calculations!B141)
C38: QUANTITY | F38: MAKE | I38: MODEL | L38: PART NUMBER | Q38: PER UNIT PRICE | S38: PER UNIT DISCOUNT | U38: EXTENDED VALUE
C40: =+Calculations!B476 | F40: =+Calculations!B491 | I40: =+Calculations!B481 | L40: =+Calculations!B486 | Q40: =+'Costing Sheet'!I$42 -> 0 | S40: =-'Costing Sheet'!K$42 -> 0 | U40: =+Calculations!B$541 -> 0
J41: =Calculations!B145
C43: =+Calculations!B477 | F43: =+Calculations!B492 | I43: =+Calculations!B482 | L43: =+Calculations!B487 | Q43: =+'Costing Sheet'!I$43 -> 0 | S43: =-'Costing Sheet'!K$43 -> 0 | U43: =+Calculations!B$542 -> 0
J44: =Calculations!B153
C46: =+Calculations!B478 | F46: =+Calculations!B493 | I46: =+Calculations!B483 | L46: =+Calculations!B488 | Q46: =+'Costing Sheet'!I$44 -> 0 | S46: =-'Costing Sheet'!K$44 -> 0 | U46: =+Calculations!B$543 -> 0
J47: =Calculations!B161
C49: =+Calculations!B479 | F49: =+Calculations!B494 | I49: =+Calculations!B484 | L49: =+Calculations!B489 | Q49: =+'Costing Sheet'!I$45 -> 0 | S49: =-'Costing Sheet'!K$45 -> 0 | U49: =+Calculations!B$544 -> 0
J50: =Calculations!B169
C52: =+Calculations!B480 | F52: =+Calculations!B495 | I52: =+Calculations!B485 | L52: =+Calculations!B490 | Q52: =+'Costing Sheet'!I$46 -> 0 | S52: =-'Costing Sheet'!K$46 -> 0 | U52: =+Calculations!B$545 -> 0
J53: =Calculations!B177

Sheet Work a Quote
D1: PRIOR PENCIL | F1: Revised Loan Terms to achieve Desired Payment
B2: APR | F2: =IF(D9="",0,IF(D11="Rate",Calculations!B606,D2)) -> 0
B3: Month Term | F3: =IF(D9="",0,IF(D11="Term",Calculations!B607,D3)) -> 0
B4: Down Payment | F4: =IF(D9="",0,IF(D11="down payment",Calculations!B608,D4)) -> 0
B5: Payment at Prior Pencil | D5: =IF(AND($D$2<>"",$D$3<>""),-PMT($D$2/12,$D$3,(Calculations!D427+Calculations!B435)-$D$4),0) -> 0
B9: Desired Payment
B11: Where to roll payment
F15: New Terms
B16: APR
B17: Month Term
B18: Down Payment
D22: Original Matrix | F22: Revised Amount | H22: Change In Profit
B23: Original Net Equipment Price | D23: =+Quote!L99 -> 0 | H23: =IF(F23=0,0,F23-D23) -> 0
B24: Original Trade ALLOWANCE | D24: =+Quote!L100 -> 0 | H24: =IF(F24=0,0,-F24+D24) -> 0
B25: INCLUDE ADDITONAL EQUIPMENT AT NO COST TO CUSTOMER | D25: 0 | H25: =IF(F25=0,0,-F25) -> 0
B26: Incentives | D26: =Calculations!B324 -> 0 | F26: 0 | H26: =IF(F26=0,0,F26-D26) -> 0
B28: Include Kubota Insurance in Revised Quote | D28: ='Costing Sheet'!M17 -> 0
B30: Payment at Prior Pencil | D30: =D5 -> 0 | F30: New Payment | H30: =IF(AND(F16<>"",F17<>""),-PMT(F16/12,F17,(-F18+Calculations!D435+Calculations!D428)),0) -> 0
B33: Front End Profit | D33: =+Recap!P97 -> 0 | F33: Revised Front End Profit | H33: =D33+SUM(H23:H26) -> 0

Sheet Agreed Terms to Finance
B2: CAIRO, GA | CHIEFLAND,FL. | DELAND, FL. | K2: CRYSTAL | Q2: =+Calculations!$B$568
B4: HASTINGS, FL | HOMOSASSA, FL | JACKSONVILLE, FL | LECANTO, FL | Q4: =+Calculations!$B$569
Q5: =Calculations!B570
B6: LEESBURG, FL. | LIVE OAK, FL. | MADISON, FL | K6: TRACTOR & EQUIPMENT
B8: MIAMI, FL. | PALATKA, FL. | PANAMA CITY, FL | OCALA, FL
B10: SPRING HILL, FL. | STARKE, FL. | TALLAHASSEE, FL | K10: =+Calculations!B572 -> CRYSTALTRACTOR.COM | Q10: =Calculations!B571
B11: CUSTOMER: | Q11: QUOTE NUMBER | S11: =+'Sales Input Sheet'!C11 -> 0
C12: =IF('Customer Input Screen'!I10<>"",UPPER('Customer Input Screen'!I10),"") | L12: CUSTOMER CELL | O12: =+'Customer Input Screen'!I22 | Q12: INVOICE NUMBER | S12: =+'Costing Sheet'!$C$13 -> 0
C13: =IF(Calculations!B3<>"",UPPER(Calculations!B3),"") | L13: CUSTOMER WORK | O13: =+'Customer Input Screen'!I23 | Q13: QUOTE DATE | S13: =+'Sales Input Sheet'!C13 -> 0
C15: =IF('Customer Input Screen'!I14<>"",UPPER('Customer Input Screen'!I14),"") | L15: CUSTOMER HOME | O15: =+'Customer Input Screen'!I24 | Q15: SALES PERSON | S15: =IF('Sales Input Sheet'!C15<>"",UPPER('Sales Input Sheet'!C15),"")
C16: =IF('Customer Input Screen'!I15<>"",UPPER('Customer Input Screen'!I15),"") | L16: =+Calculations!$B$602
C17: =+Calculations!$B$601 | L17: PURCHASE ORDER NO. | O17: =UPPER('Costing Sheet'!U19)
B19: Customer hereby orders the following described machinery and equipment from Crystal Tractor, LLC, Crystal Equipment, LLC or Crystal Motorsports, LLC. Upon acceptance by Seller and Customer, this order becomes a agreement to endeavor to conclude the purchase and sale of goods upon the terms and conditions set forth herein and on the reverse of this order.
Q21: DEALER SUGGESTED PRICE | S21: DISCOUNT | U21: NET SELLING PRICE
C22: STOCK NUMBER | I22: MAKE | L22: MODEL | O22: SERIAL NUMBER
C23: =Calculations!B451 | I23: =Calculations!B6 | L23: =Calculations!B7 | O23: =Calculations!B8 | Q23: =+'Costing Sheet'!I$22 -> 0 | S23: =-'Costing Sheet'!K$22 -> 0 | U23: =+Calculations!B$526 -> 0
J24: =Calculations!B9
J25: =+Calculations!B12
C27: =Calculations!B452 | I27: =Calculations!B18 | L27: =Calculations!B19 | O27: =Calculations!B20 | Q27: =+'Costing Sheet'!I$23 -> 0 | S27: =-'Costing Sheet'!K$23 -> 0 | U27: =+Calculations!B$527 -> 0
J28: =Calculations!B21
J29: =+Calculations!B24
C31: =Calculations!B453 | I31: =Calculations!B30 | L31: =Calculations!B31 | O31: =Calculations!B32 | Q31: =+'Costing Sheet'!I$24 -> 0 | S31: =-'Costing Sheet'!K$24 -> 0 | U31: =+Calculations!B$528 -> 0
J32: =Calculations!B33
J33: =+Calculations!B36
C35: =Calculations!B454 | I35: =Calculations!B42 | L35: =Calculations!B43 | O35: =Calculations!B44 | Q35: =+'Costing Sheet'!I$25 -> 0 | S35: =-'Costing Sheet'!K$25 -> 0 | U35: =+Calculations!B$529 -> 0
J36: =Calculations!B45
J37: =+Calculations!B48
C39: =Calculations!B455 | I39: =Calculations!B54 | L39: =Calculations!B55 | O39: =Calculations!B56 | Q39: =+'Costing Sheet'!I$26 -> 0 | S39: =-'Costing Sheet'!K$26 -> 0 | U39: =+Calculations!B$530 -> 0
J40: =Calculations!B57
J41: =+Calculations!B60
C43: =Calculations!B456 | I43: =Calculations!B66 | L43: =Calculations!B67 | O43: =Calculations!B68 | Q43: =+'Costing Sheet'!I$27 -> 0 | S43: =-'Costing Sheet'!K$27 -> 0 | U43: =+Calculations!B$531 -> 0
J44: =Calculations!B69
J45: =+Calculations!B72
C47: =Calculations!B457 | I47: =Calculations!B78 | L47: =Calculations!B79 | O47: =Calculations!B80 | Q47: =+'Costing Sheet'!I$28 -> 0 | S47: =-'Costing Sheet'!K$28 -> 0 | U47: =+Calculations!B$532 -> 0
J48: =Calculations!B81
J49: =+Calculations!B84
C51: =Calculations!B458 | I51: =Calculations!B90 | L51: =Calculations!B91 | O51: =Calculations!B92 | Q51: =+'Costing Sheet'!I$29 -> 0 | S51: =-'Costing Sheet'!K$29 -> 0 | U51: =+Calculations!B$533 -> 0
J52: =Calculations!B93
J53: =+Calculations!B96
C55: =Calculations!B459 | I55: =Calculations!B102 | L55: =Calculations!B103 | O55: =Calculations!B104 | Q55: =+'Costing Sheet'!I$30 -> 0 | S55: =-'Costing Sheet'!K$30 -> 0 | U55: =+Calculations!B$534 -> 0
J56: =Calculations!B105
J57: =+Calculations!B108
C59: =Calculations!B460 | I59: =Calculations!B114 | L59: =Calculations!B115 | O59: =Calculations!B116 | Q59: =+'Costing Sheet'!I$31 -> 0 | S59: =-'Costing Sheet'!K$31 -> 0 | U59: =+Calculations!B$535 -> 0
J60: =Calculations!B117
J61: =+Calculations!B120
C62: =UPPER('Sales Input Sheet'!E55)
B66: TRADE IN | I66: MAKE | L66: MODEL | O66: SERIAL NUMBER | Q66: DESCRIPTION | S66: TRADE ALLOWANCE | U66: TRADE PAYOFF
I67: =+Calculations!B504 | L67: =+Calculations!B506 | O67: =+Calculations!B502 | Q67: =Calculations!B514 | S67: =Calculations!B498 -> 0 | U67: =Calculations!B500 -> 0
I68: =+Calculations!B505 | L68: =+Calculations!B507 | O68: =+Calculations!B503 | Q68: =Calculations!B515 | S68: =Calculations!B499 -> 0 | U68: =Calculations!B501 -> 0
I69: =+Calculations!B694 | L69: =+Calculations!B698 | O69: =+Calculations!B690 | Q69: =+Calculations!B678 | S69: =+Calculations!B682 -> 0 | U69: =+Calculations!B686 -> 0
I70: =+Calculations!B695 | L70: =+Calculations!B699 | O70: =+Calculations!B691 | Q70: =+Calculations!B679 | S70: =+Calculations!B683 -> 0 | U70: =+Calculations!B687 -> 0
I71: =+Calculations!B696 | L71: =+Calculations!B700 | O71: =+Calculations!B692 | Q71: =+Calculations!B680 | S71: =+Calculations!B684 -> 0 | U71: =+Calculations!B688 -> 0
I72: =+Calculations!B697 | L72: =+Calculations!B701 | O72: =+Calculations!B693 | Q72: =+Calculations!B681 | S72: =+Calculations!B685 -> 0 | U72: =+Calculations!B689 -> 0
B74: Payment Summary
B75: DOWN PAYMENT | H75: TERM | N75: RATE | R75: PAYMENT
B76: ='Costing Sheet'!$U$11 -> 0 | H76: ='Costing Sheet'!$U$7 -> 0 | N76: ='Costing Sheet'!$U$9 -> 0 | R76: =+Calculations!$B$449 -> 0
B77: =+Calculations!B$416 | H77: =IF(B77="","",+Calculations!B$425)
B78: =_xlfn.CONCAT(Calculations!B384) -> For presentation purposes and submitting for approval of financing, payments are based upon a month term at an annual interest rate of 0.000%. Actual term and rates may vary based upon financing available based upon customers credit and other factors.
J80: =+Q2
J81: =+Q4
J82: =+Q5 | Q82: =+Q15 -> SALES PERSON | S82: =+S15
J83: =+Q10
C85: =+C12 | Q85: INVOICE NUMBER | S85: =+'Costing Sheet'!$C$13 -> 0
C86: =+C13 | Q86: INVOICE DATE | S86: ='Costing Sheet'!$C$11 -> 0
C87: =+'Costing Sheet'!C19 -> 0 | F87: =+'Costing Sheet'!E19 -> 0 | O87: =UPPER('Costing Sheet'!C17) | Q87: =UPPER('Costing Sheet'!E17)
B88: TRANSACTION SUMMARY
B89: DEALER PRICE OF ALL EQUIPMENT | L89: =+Calculations!B$310 -> 0 | N89: SUB TOTAL | U89: =+Calculations!B$319 -> 0
B90: =IF(L90=0,"","LINE ITEM DISCOUNT") | L90: =-Calculations!B$311 -> 0 | N90: TIRE FEE | U90: =+Calculations!B$386 -> 0
B91: SELLING PRICE, NET | L91: =+Calculations!B$312 -> 0 | N91: BATTERY FEE | U91: =+Calculations!B$385 -> 0
B92: TRADE VALUE | L92: =-Calculations!B$315 -> 0 | N92: DMV, TAX & TITLE FEES | U92: =+Calculations!B$439 -> 0
B93: TRADE PAYOFF | L93: =+Calculations!B$316 -> 0 | N93: DOC STAMP TAX | U93: =+'Costing Sheet'!Q15 -> 0
B94: DOCUMENT FEE (1) | L94: =+Calculations!B$302 -> 0 | N94: UCC FEE | U94: =+'Costing Sheet'!Q13 -> 0
N95: =+Calculations!$B$403 -> SALES TAX | U95: =+Calculations!$B$405 -> 0
B96: FREIGHT | L96: =+'Costing Sheet'!Q$3 -> 0 | N96: =+Calculations!$B$399 | U96: =+Calculations!$B$412 -> 0
B97: SET UP FEE (1) | L97: =+'Costing Sheet'!Q$5 -> 0 | N97: =+Calculations!$B$406 -> COUNTY SALES TAX OUT OF STATE OR NO COUNTY WAS SPECIFIED FOR CUSTOMER | U97: =+Calculations!$B$413 -> 0
B98: =+Calculations!B640 | L98: =+Calculations!B232 -> 0 | N98: =+Calculations!$B$414 | U98: =+Calculations!$B$407 -> 0
B99: =+Calculations!B641 | L99: =+Calculations!B233 -> 0 | N99: =Calculations!B651 | U99: =-Calculations!B$318 -> 0
B100: =+Calculations!B642 | L100: =+Calculations!B234 -> 0 | O100: =Calculations!$B$653
B101: =+Calculations!B643 | L101: =+Calculations!B235 -> 0
B102: =+Calculations!B644 | L102: =+Calculations!B236 -> 0
B103: =+Calculations!B645 | L103: =+Calculations!B237 -> 0
B104: =+Calculations!B646 | L104: =+Calculations!B238 -> 0
B105: =+Calculations!B647 | L105: =+Calculations!B239 -> 0
B106: =+Calculations!B648 | L106: =+Calculations!B240 -> 0
B107: =+Calculations!B649 | L107: =+Calculations!B241 -> 0
B109: SUB TOTAL | L109: =+Calculations!B$319 -> 0 | N109: =UPPER(_xlfn.CONCAT("TOTAL DUE FROM CUSTOMER",Calculations!$B$650)) -> TOTAL DUE FROM CUSTOMER | U109: =+Calculations!B$435 -> 0
B111: =Calculations!B$616 -> #DIV/0! | H111: =IF(B111="","",Calculations!B$617) -> #DIV/0!

Sheet Pre-Invoice
B2: CAIRO, GA | CHIEFLAND,FL. | DELAND, FL. | K2: CRYSTAL | Q2: =+Calculations!$B$568
B4: HASTINGS, FL | HOMOSASSA, FL | JACKSONVILLE, FL | LECANTO, FL | Q4: =+Calculations!$B$569
Q5: =Calculations!B570
B6: LEESBURG, FL. | LIVE OAK, FL. | MADISON, FL | K6: TRACTOR & EQUIPMENT
B8: MIAMI, FL. | PALATKA, FL. | PANAMA CITY, FL | OCALA, FL
B10: SPRING HILL, FL. | STARKE, FL. | TALLAHASSEE, FL | K10: =+Calculations!B572 -> CRYSTALTRACTOR.COM | Q10: =Calculations!B571
B11: CUSTOMER: | Q11: QUOTE NUMBER | S11: ='Sales Input Sheet'!C11 -> 0
C12: =IF('Customer Input Screen'!I10<>"",UPPER('Customer Input Screen'!I10),"") | L12: CUSTOMER CELL | O12: =+'Customer Input Screen'!I22 | Q12: INVOICE NUMBER | S12: =+'Costing Sheet'!$C$13 -> 0
C13: =IF(Calculations!B3<>"",UPPER(Calculations!B3),"") | L13: CUSTOMER WORK | O13: =+'Customer Input Screen'!I23 | Q13: INVOICE DATE | S13: ='Costing Sheet'!$C$11 -> 0
C15: =IF('Customer Input Screen'!I14<>"",UPPER('Customer Input Screen'!I14),"") | L15: CUSTOMER HOME | O15: =+'Customer Input Screen'!I24 | Q15: SALES PERSON | S15: =IF('Sales Input Sheet'!C15<>"",UPPER('Sales Input Sheet'!C15),"")
C16: =IF('Customer Input Screen'!I15<>"",UPPER('Customer Input Screen'!I15),"") | L16: =+Calculations!$B$602
C17: =+Calculations!$B$601 | L17: PURCHASE ORDER NO. | O17: =UPPER('Costing Sheet'!U19)
B20: PRELIMINARY INVOICE
Q22: DEALER SUGGESTED PRICE | S22: DISCOUNT | U22: NET SELLING PRICE
C23: STOCK NUMBER | I23: MAKE | L23: MODEL | O23: SERIAL NUMBER
C24: =Calculations!B451 | I24: =Calculations!B6 | L24: =Calculations!B7 | O24: =Calculations!B8 | Q24: =+'Costing Sheet'!I$22 -> 0 | S24: =-'Costing Sheet'!K$22 -> 0 | U24: =+Calculations!B$526 -> 0
J25: =Calculations!B9
J26: =+Calculations!B12
C28: =Calculations!B452 | I28: =Calculations!B18 | L28: =Calculations!B19 | O28: =Calculations!B20 | Q28: =+'Costing Sheet'!I$23 -> 0 | S28: =-'Costing Sheet'!K$23 -> 0 | U28: =+Calculations!B$527 -> 0
J29: =Calculations!B21
J30: =+Calculations!B24
C32: =Calculations!B453 | I32: =Calculations!B30 | L32: =Calculations!B31 | O32: =Calculations!B32 | Q32: =+'Costing Sheet'!I$24 -> 0 | S32: =-'Costing Sheet'!K$24 -> 0 | U32: =+Calculations!B$528 -> 0
J33: =Calculations!B33
J34: =+Calculations!B36
C36: =Calculations!B454 | I36: =Calculations!B42 | L36: =Calculations!B43 | O36: =Calculations!B44 | Q36: =+'Costing Sheet'!I$25 -> 0 | S36: =-'Costing Sheet'!K$25 -> 0 | U36: =+Calculations!B$529 -> 0
J37: =Calculations!B45
J38: =+Calculations!B48
C40: =Calculations!B455 | I40: =Calculations!B54 | L40: =Calculations!B55 | O40: =Calculations!B56 | Q40: =+'Costing Sheet'!I$26 -> 0 | S40: =-'Costing Sheet'!K$26 -> 0 | U40: =+Calculations!B$530 -> 0
J41: =Calculations!B57
J42: =+Calculations!B60
C44: =Calculations!B456 | I44: =Calculations!B66 | L44: =Calculations!B67 | O44: =Calculations!B68 | Q44: =+'Costing Sheet'!I$27 -> 0 | S44: =-'Costing Sheet'!K$27 -> 0 | U44: =+Calculations!B$531 -> 0
J45: =Calculations!B69
J46: =+Calculations!B72
C48: =Calculations!B457 | I48: =Calculations!B78 | L48: =Calculations!B79 | O48: =Calculations!B80 | Q48: =+'Costing Sheet'!I$28 -> 0 | S48: =-'Costing Sheet'!K$28 -> 0 | U48: =+Calculations!B$532 -> 0
J49: =Calculations!B81
J50: =+Calculations!B84
C52: =Calculations!B458 | I52: =Calculations!B90 | L52: =Calculations!B91 | O52: =Calculations!B92 | Q52: =+'Costing Sheet'!I$29 -> 0 | S52: =-'Costing Sheet'!K$29 -> 0 | U52: =+Calculations!B$533 -> 0
J53: =Calculations!B93
J54: =+Calculations!B96
C56: =Calculations!B459 | I56: =Calculations!B102 | L56: =Calculations!B103 | O56: =Calculations!B104 | Q56: =+'Costing Sheet'!I$30 -> 0 | S56: =-'Costing Sheet'!K$30 -> 0 | U56: =+Calculations!B$534 -> 0
J57: =Calculations!B105
J58: =+Calculations!B108
C60: =Calculations!B460 | I60: =Calculations!B114 | L60: =Calculations!B115 | O60: =Calculations!B116 | Q60: =+'Costing Sheet'!I$31 -> 0 | S60: =-'Costing Sheet'!K$31 -> 0 | U60: =+Calculations!B$535 -> 0
J61: =Calculations!B117
J62: =+Calculations!B120
C63: =UPPER('Sales Input Sheet'!E55)
B67: TRADE IN | I67: MAKE | L67: MODEL | O67: SERIAL NUMBER | Q67: DESCRIPTION | S67: TRADE ALLOWANCE | U67: TRADE PAYOFF
I68: =+Calculations!B504 | L68: =+Calculations!B506 | O68: =+Calculations!B502 | Q68: =Calculations!B514 | S68: =Calculations!B498 -> 0 | U68: =Calculations!B500 -> 0
I69: =+Calculations!B694 | L69: =+Calculations!B698 | O69: =+Calculations!B690 | Q69: =+Calculations!B678 | S69: =+Calculations!B682 -> 0 | U69: =+Calculations!B686 -> 0
I70: =+Calculations!B695 | L70: =+Calculations!B699 | O70: =+Calculations!B691 | Q70: =+Calculations!B679 | S70: =+Calculations!B683 -> 0 | U70: =+Calculations!B687 -> 0
I71: =+Calculations!B696 | L71: =+Calculations!B700 | O71: =+Calculations!B692 | Q71: =+Calculations!B680 | S71: =+Calculations!B684 -> 0 | U71: =+Calculations!B688 -> 0
I72: =+Calculations!B697 | L72: =+Calculations!B701 | O72: =+Calculations!B693 | Q72: =+Calculations!B681 | S72: =+Calculations!B685 -> 0 | U72: =+Calculations!B689 -> 0
I73: =+Calculations!B505 | L73: =+Calculations!B507 | O73: =+Calculations!B503 | Q73: =Calculations!B515 | S73: =Calculations!B499 -> 0 | U73: =Calculations!B501 -> 0
J76: =+Q2
J77: =+Q4
J78: =+Q5 | Q78: =+Q15 -> SALES PERSON | S78: =+S15
J79: =+Q10
Q80: =+UPPER('Costing Sheet'!$C$17)
C81: =+C12 | Q81: INVOICE NUMBER | S81: =+'Costing Sheet'!$C$13 -> 0
C82: =+C13 | Q82: INVOICE DATE | S82: ='Costing Sheet'!$C$11 -> 0
C83: =+'Costing Sheet'!C19 -> 0 | F83: =+'Costing Sheet'!E19 -> 0 | O83: =UPPER('Costing Sheet'!C17) | Q83: =UPPER('Costing Sheet'!E17)
B84: PRELIMINARY INVOICE SUMMARY
B86: DEALER PRICE OF ALL EQUIPMENT | F86: =+Calculations!B310 -> 0 | I86: PURCHASES BEFORE ADDITIONAL FEES, TAXES AND REBATES | L86: =+Calculations!B320 -> 0 | O86: PURCHASES WITH FEES BEFORE TAX AND REBATES | Q86: =Calculations!B437 -> 0 | S86: NET PURCHASE PRICE DUE FROM CUSTOMER | U86: =+Calculations!B436 -> 0
B87: =IF(F87=0,"","DISCOUNT") | F87: =-Calculations!B311 -> 0 | I87: DOCUMENT FEE (1) | L87: =+Calculations!B302 -> 0 | O87: DOC Stamp Tax | Q87: =+'Costing Sheet'!Q15 -> 0
B88: =_xlfn.CONCAT("SELLING PRICE",IF(B87="",""," NET")) -> SELLING PRICE | F88: =+Calculations!B312 -> 0 | O88: UCC Fee | Q88: =+'Costing Sheet'!Q13 -> 0 | S88: LESS:
B89: TRADE ALLOWANCE | F89: =-Calculations!B315 -> 0 | I89: FREIGHT | L89: =+'Costing Sheet'!Q3 -> 0 | O89: =+Calculations!B403 -> SALES TAX | Q89: =+Calculations!B405 -> 0 | S89: ADVANCED DEPOSIT | U89: =-'Costing Sheet'!Q17 -> 0
B90: TRADE PAYOFF | F90: =+Calculations!B316 -> 0 | I90: SET UP FEE (1) | L90: =+'Costing Sheet'!Q5 -> 0 | O90: =+Calculations!B399 | Q90: =+Calculations!B412 -> 0
B91: =+Calculations!B640 | F91: =+Calculations!B232 -> 0 | I91: TIRE FEE | L91: =+Calculations!B386 -> 0 | O91: =+Calculations!B406 -> COUNTY SALES TAX OUT OF STATE OR NO COUNTY WAS SPECIFIED FOR CUSTOMER | Q91: =+Calculations!B413 -> 0
B92: =+Calculations!B641 | F92: =+Calculations!B233 -> 0
B93: =+Calculations!B642 | F93: =+Calculations!B234 -> 0
B94: =+Calculations!B643 | F94: =+Calculations!B235 -> 0 | S94: ADDITIONAL DOWN PAYMENT | U94: =-'Costing Sheet'!Q19 -> 0
B95: =+Calculations!B644 | F95: =+Calculations!B236 -> 0
B96: =+Calculations!B645 | F96: =+Calculations!B237 -> 0 | I96: BATTERY FEE | L96: =+Calculations!B385 -> 0 | O96: =+Calculations!B414 | Q96: =+Calculations!B407 -> 0
B97: =+Calculations!B646 | F97: =+Calculations!B238 -> 0
B98: =+Calculations!B647 | F98: =+Calculations!B239 -> 0
B99: =+Calculations!B648 | F99: =+Calculations!B240 -> 0
B100: =+Calculations!B649 | F100: =+Calculations!B241 -> 0 | O100: =Calculations!$B$653
B101: =+Calculations!B417 | F101: =+Calculations!B421 -> 0 | I101: DMV & TITLE FEES | L101: =+Calculations!B439 -> 0 | O101: =Calculations!B651 | Q101: =-Calculations!B318 -> 0
B102: PURCHASES BEFORE ADDITIONAL FEES, TAXES AND REBATES | F102: =+Calculations!B320 -> 0 | I102: PURCHASES WITH FEES BEFORE TAX AND REBATES | L102: =+Calculations!B437 -> 0 | O102: NET PURCHASE PRICE DUE FROM CUSTOMER | Q102: =+Calculations!B436 -> 0 | S102: NET CASH BALANCE DUE | U102: =+Calculations!B438 -> 0
B103: (1) Document Fee and Set Up Fee: These charges represents cost and profit to the seller/dealer for items such as assembling, inspecting, cleaning and adjusting new and used units and preparing documents related to the sale.
B104: AS-IS and WITH ALL FAULTS. The only warranties applying to the equioment sold herein are those provided in a separate writing or offered by the manufacturer or, if applicable, by the manufacturer of the non-factory installed equipment. The Dealer expressly disclaims all warranties, either express or implied, including any implied warranty of merchantability and implied warranty of fitness for a particular purpose and the Dealer neither assumes nor authorizes any other person to assume for it any liability in connection with the sale of this equipment. Buyer shall not be entitled to recover from the Dealer any consequential damages, damages to property, damages for loss of use, loss of time, loss of profit, or income, or any other incidental damages.
B105: Upon Execution, you agree to receive conversational messages sent via SMS/text message. This agreement isn't a condition of any purchase. Terms, Privacy Policy, and opt out process can be found at www.crystaltractor.com/read-our-policy-statement-xprivacy. Charges may apply. You may reply "Stop" at any time to opt-out.
B107: This Document reflects the anticipated terms fo the sale of the listed equipmnent to the customer as identified above. While the Cusotmer is agreeing to purchase the indicated items, no Sale of the Equipment occurs unitl a final invoice is issued and excuted by both the seller/dealer and customer and no sale occurs until payment is receoievd by dealer/seller.
B109: Accepted:
B112: Customer

Sheet Invoice
B2: CAIRO, GA | CHIEFLAND,FL. | DELAND, FL. | K2: CRYSTAL | Q2: =+Calculations!$B$568
B4: HASTINGS, FL | HOMOSASSA, FL | JACKSONVILLE, FL | LECANTO, FL | Q4: =+Calculations!$B$569
Q5: =Calculations!B570
B6: LEESBURG, FL. | LIVE OAK, FL. | MADISON, FL | K6: TRACTOR & EQUIPMENT
B7: MIAMI, FL. | PALATKA, FL. | PANAMA CITY, FL | OCALA, FL
B10: SPRING HILL, FL. | STARKE, FL. | TALLAHASSEE, FL | K10: =+Calculations!B572 -> CRYSTALTRACTOR.COM | Q10: =Calculations!B571
B11: CUSTOMER: | Q11: QUOTE NUMBER | S11: ='Sales Input Sheet'!C11 -> 0
C12: =IF('Customer Input Screen'!I10<>"",UPPER('Customer Input Screen'!I10),"") | L12: CUSTOMER CELL | O12: =+'Customer Input Screen'!I22 | Q12: INVOICE NUMBER | S12: =+'Costing Sheet'!$C$13 -> 0
C13: =IF(Calculations!B3<>"",UPPER(Calculations!B3),"") | L13: CUSTOMER WORK | O13: =+'Customer Input Screen'!I23 | Q13: INVOICE DATE | S13: ='Costing Sheet'!$C$11 -> 0
C15: =IF('Customer Input Screen'!I14<>"",UPPER('Customer Input Screen'!I14),"") | L15: CUSTOMER HOME | O15: =+'Customer Input Screen'!I24 | Q15: SALES PERSON | S15: =IF('Sales Input Sheet'!C15<>"",UPPER('Sales Input Sheet'!C15),"")
C16: =IF('Customer Input Screen'!I15<>"",UPPER('Customer Input Screen'!I15),"") | L16: =+Calculations!$B$602
C17: =+Calculations!$B$601 | L17: PURCHASE ORDER NO. | O17: =UPPER('Costing Sheet'!U19)
B20: INVOICE
Q22: DEALER SUGGESTED PRICE | S22: DISCOUNT | U22: NET SELLING PRICE
C23: STOCK NUMBER | I23: MAKE | L23: MODEL | O23: SERIAL NUMBER
C24: =Calculations!B451 | I24: =Calculations!B6 | L24: =Calculations!B7 | O24: =Calculations!B8 | Q24: =+'Costing Sheet'!I$22 -> 0 | S24: =-'Costing Sheet'!K$22 -> 0 | U24: =+Calculations!B$526 -> 0
J25: =Calculations!B9
J26: =+Calculations!B12
C28: =Calculations!B452 | I28: =Calculations!B18 | L28: =Calculations!B19 | O28: =Calculations!B20 | Q28: =+'Costing Sheet'!I$23 -> 0 | S28: =-'Costing Sheet'!K$23 -> 0 | U28: =+Calculations!B$527 -> 0
J29: =Calculations!B21
J30: =+Calculations!B24
C32: =Calculations!B453 | I32: =Calculations!B30 | L32: =Calculations!B31 | O32: =Calculations!B32 | Q32: =+'Costing Sheet'!I$24 -> 0 | S32: =-'Costing Sheet'!K$24 -> 0 | U32: =+Calculations!B$528 -> 0
J33: =Calculations!B33
J34: =+Calculations!B36
C36: =Calculations!B454 | I36: =Calculations!B42 | L36: =Calculations!B43 | O36: =Calculations!B44 | Q36: =+'Costing Sheet'!I$25 -> 0 | S36: =-'Costing Sheet'!K$25 -> 0 | U36: =+Calculations!B$529 -> 0
J37: =Calculations!B45
J38: =+Calculations!B48
C40: =Calculations!B455 | I40: =Calculations!B54 | L40: =Calculations!B55 | O40: =Calculations!B56 | Q40: =+'Costing Sheet'!I$26 -> 0 | S40: =-'Costing Sheet'!K$26 -> 0 | U40: =+Calculations!B$530 -> 0
J41: =Calculations!B57
J42: =+Calculations!B60
C44: =Calculations!B456 | I44: =Calculations!B66 | L44: =Calculations!B67 | O44: =Calculations!B68 | Q44: =+'Costing Sheet'!I$27 -> 0 | S44: =-'Costing Sheet'!K$27 -> 0 | U44: =+Calculations!B$531 -> 0
J45: =Calculations!B69
J46: =+Calculations!B72
C48: =Calculations!B457 | I48: =Calculations!B78 | L48: =Calculations!B79 | O48: =Calculations!B80 | Q48: =+'Costing Sheet'!I$28 -> 0 | S48: =-'Costing Sheet'!K$28 -> 0 | U48: =+Calculations!B$532 -> 0
J49: =Calculations!B81
J50: =+Calculations!B84
C52: =Calculations!B458 | I52: =Calculations!B90 | L52: =Calculations!B91 | O52: =Calculations!B92 | Q52: =+'Costing Sheet'!I$29 -> 0 | S52: =-'Costing Sheet'!K$29 -> 0 | U52: =+Calculations!B$533 -> 0
J53: =Calculations!B93
J54: =+Calculations!B96
C56: =Calculations!B459 | I56: =Calculations!B102 | L56: =Calculations!B103 | O56: =Calculations!B104 | Q56: =+'Costing Sheet'!I$30 -> 0 | S56: =-'Costing Sheet'!K$30 -> 0 | U56: =+Calculations!B$534 -> 0
J57: =Calculations!B105
J58: =+Calculations!B108
C60: =Calculations!B460 | I60: =Calculations!B114 | L60: =Calculations!B115 | O60: =Calculations!B116 | Q60: =+'Costing Sheet'!I$31 -> 0 | S60: =-'Costing Sheet'!K$31 -> 0 | U60: =+Calculations!B$535 -> 0
J61: =Calculations!B117
J62: =+Calculations!B120
C63: =UPPER('Sales Input Sheet'!E55)
B67: TRADE IN | I67: MAKE | L67: MODEL | O67: SERIAL NUMBER | Q67: DESCRIPTION | S67: TRADE ALLOWANCE | U67: TRADE PAYOFF
I68: =+Calculations!B504 | L68: =+Calculations!B506 | O68: =+Calculations!B502 | Q68: =Calculations!B514 | S68: =Calculations!B498 -> 0 | U68: =Calculations!B500 -> 0
I69: =+Calculations!B694 | L69: =+Calculations!B698 | O69: =+Calculations!B690 | Q69: =+Calculations!B678 | S69: =+Calculations!B682 -> 0 | U69: =+Calculations!B686 -> 0
I70: =+Calculations!B695 | L70: =+Calculations!B699 | O70: =+Calculations!B691 | Q70: =+Calculations!B679 | S70: =+Calculations!B683 -> 0 | U70: =+Calculations!B687 -> 0
I71: =+Calculations!B696 | L71: =+Calculations!B700 | O71: =+Calculations!B692 | Q71: =+Calculations!B680 | S71: =+Calculations!B684 -> 0 | U71: =+Calculations!B688 -> 0
I72: =+Calculations!B697 | L72: =+Calculations!B701 | O72: =+Calculations!B693 | Q72: =+Calculations!B681 | S72: =+Calculations!B685 -> 0 | U72: =+Calculations!B689 -> 0
I73: =+Calculations!B505 | L73: =+Calculations!B507 | O73: =+Calculations!B503 | Q73: =Calculations!B515 | S73: =Calculations!B499 -> 0 | U73: =Calculations!B501 -> 0
J76: =+Q2
J77: =+Q4
J78: =+Q5 | Q78: =+Q15 -> SALES PERSON | S78: =+S15
J79: =+Q10
Q80: =+UPPER('Costing Sheet'!$C$17)
C81: =+C12 | Q81: INVOICE NUMBER | S81: =+'Costing Sheet'!$C$13 -> 0
C82: =+C13 | Q82: INVOICE DATE | S82: ='Costing Sheet'!$C$11 -> 0
C83: =+'Costing Sheet'!C19 -> 0 | F83: =+'Costing Sheet'!E19 -> 0 | O83: =UPPER('Costing Sheet'!C17) | Q83: =UPPER('Costing Sheet'!E17)
B84: INVOICE SUMMARY
B86: DEALER PRICE OF ALL EQUIPMENT | F86: =+Calculations!B310 -> 0 | I86: PURCHASES BEFORE ADDITIONAL FEES, TAXES AND REBATES | L86: =+Calculations!B320 -> 0 | O86: PURCHASES WITH FEES BEFORE TAX AND REBATES | Q86: =Calculations!B437 -> 0 | S86: NET PURCHASE PRICE DUE FROM CUSTOMER | U86: =+Calculations!B436 -> 0
B87: =IF(F87=0,"","DISCOUNT") | F87: =-Calculations!B311 -> 0 | I87: DOCUMENT FEE (1) | L87: =+Calculations!B302 -> 0 | O87: DOC Stamp Tax | Q87: =+'Costing Sheet'!Q15 -> 0
B88: =_xlfn.CONCAT("SELLING PRICE",IF(B87="",""," NET")) -> SELLING PRICE | F88: =+Calculations!B312 -> 0 | O88: UCC Fee | Q88: =+'Costing Sheet'!Q13 -> 0 | S88: LESS:
B89: TRADE ALLOWANCE | F89: =-Calculations!B315 -> 0 | I89: FREIGHT | L89: =+'Costing Sheet'!Q3 -> 0 | O89: =+Calculations!B403 -> SALES TAX | Q89: =+Calculations!B405 -> 0 | S89: ADVANCED DEPOSIT | U89: =-'Costing Sheet'!Q17 -> 0
B90: TRADE PAYOFF | F90: =+Calculations!B316 -> 0 | I90: SET UP FEE (1) | L90: =+'Costing Sheet'!Q5 -> 0 | O90: =+Calculations!B399 | Q90: =+Calculations!B412 -> 0
B91: =+Calculations!B640 | F91: =+Calculations!B232 -> 0 | I91: TIRE FEE | L91: =+Calculations!B386 -> 0 | O91: =+Calculations!B406 -> COUNTY SALES TAX OUT OF STATE OR NO COUNTY WAS SPECIFIED FOR CUSTOMER | Q91: =+Calculations!B413 -> 0
B92: =+Calculations!B641 | F92: =+Calculations!B233 -> 0
B93: =+Calculations!B642 | F93: =+Calculations!B234 -> 0
B94: =+Calculations!B643 | F94: =+Calculations!B235 -> 0 | S94: ADDITIONAL DOWN PAYMENT | U94: =-'Costing Sheet'!Q19 -> 0
B95: =+Calculations!B644 | F95: =+Calculations!B236 -> 0
B96: =+Calculations!B645 | F96: =+Calculations!B237 -> 0 | I96: BATTERY FEE | L96: =+Calculations!B385 -> 0 | O96: =+Calculations!B414 | Q96: =+Calculations!B407 -> 0
B97: =+Calculations!B646 | F97: =+Calculations!B238 -> 0
B98: =+Calculations!B647 | F98: =+Calculations!B239 -> 0
B99: =+Calculations!B648 | F99: =+Calculations!B240 -> 0
B100: =+Calculations!B649 | F100: =+Calculations!B241 -> 0 | O100: =Calculations!$B$653
B101: =+Calculations!B417 | F101: =+Calculations!B421 -> 0 | I101: DMV & TITLE FEES | L101: =+Calculations!B439 -> 0 | O101: =Calculations!B651 | Q101: =-Calculations!B318 -> 0
B102: PURCHASES BEFORE ADDITIONAL FEES, TAXES AND REBATES | F102: =+Calculations!B320 -> 0 | I102: PURCHASES WITH FEES BEFORE TAX AND REBATES | L102: =+Calculations!B437 -> 0 | O102: NET PURCHASE PRICE DUE FROM CUSTOMER | Q102: =+Calculations!B436 -> 0 | S102: NET CASH BALANCE DUE | U102: =+Calculations!B438 -> 0
B103: (1) Document Fee and Set Up Fee: These charges represents cost and profit to the seller/dealer for items such as assembling, inspecting, cleaning and adjusting new and used units and preparing documents related to the sale.
B104: AS-IS and WITH ALL FAULTS. The only warranties applying to the equioment sold herein are those provided in a separate writing or offered by the manufacturer or, if applicable, by the manufacturer of the non-factory installed equipment. The Dealer expressly disclaims all warranties, either express or implied, including any implied warranty of merchantability and implied warranty of fitness for a particular purpose and the Dealer neither assumes nor authorizes any other person to assume for it any liability in connection with the sale of this equipment. Buyer shall not be entitled to recover from the Dealer any consequential damages, damages to property, damages for loss of use, loss of time, loss of profit, or income, or any other incidental damages.
B105: You agree to receive conversational messages sent via SMS/text message. This agreement isn't a condition of any purchase. Terms, Privacy Policy, and opt out process can be found at www.crystaltractor.com/read-our-policy-statement-xprivacy. Charges may apply. You may reply "Stop" at any time to opt-out.
B107: Accepted:
B108: ='Customer Input Screen'!C32 -> [Customer Signature] | Q108: ='Customer Input Screen'!C33 -> [Company Signature]
B110: Customer | Q110: Company

Sheet KUB INV
B2: CAIRO, GA | CHIEFLAND,FL. | DELAND, FL. | K2: CRYSTAL | Q2: =+Calculations!$B$568
B4: HASTINGS, FL | HOMOSASSA, FL | JACKSONVILLE, FL | LECANTO, FL | Q4: =+Calculations!$B$569
Q5: =Calculations!B570
B6: LEESBURG, FL. | LIVE OAK, FL. | MADISON, FL | K6: TRACTOR & EQUIPMENT
B7: MIAMI, FL. | PALATKA, FL. | PANAMA CITY, FL | OCALA, FL
B10: SPRING HILL, FL. | STARKE, FL. | TALLAHASSEE, FL | K10: =+Calculations!B572 -> CRYSTALTRACTOR.COM | Q10: =Calculations!B571
B11: CUSTOMER: | Q11: QUOTE NUMBER | S11: ='Sales Input Sheet'!C11 -> 0
C12: =IF('Customer Input Screen'!I10<>"",UPPER('Customer Input Screen'!I10),"") | L12: CUSTOMER CELL | O12: =+'Customer Input Screen'!I22 | Q12: INVOICE NUMBER | S12: =+'Costing Sheet'!$C$13 -> 0
C13: =IF(Calculations!B3<>"",UPPER(Calculations!B3),"") | L13: CUSTOMER WORK | O13: =+'Customer Input Screen'!I23 | Q13: INVOICE DATE | S13: ='Costing Sheet'!$C$11 -> 0
C15: =IF('Customer Input Screen'!I14<>"",UPPER('Customer Input Screen'!I14),"") | L15: CUSTOMER HOME | O15: =+'Customer Input Screen'!I24 | Q15: SALES PERSON | S15: =IF('Sales Input Sheet'!C15<>"",UPPER('Sales Input Sheet'!C15),"")
C16: =IF('Customer Input Screen'!I15<>"",UPPER('Customer Input Screen'!I15),"") | L16: =+Calculations!$B$602
C17: =+Calculations!$B$601 | L17: PURCHASE ORDER NO. | O17: =UPPER('Costing Sheet'!U19)
B20: INVOICE
Q22: DEALER SUGGESTED PRICE | S22: DISCOUNT | U22: NET SELLING PRICE
C23: STOCK NUMBER | I23: MAKE | L23: MODEL | O23: SERIAL NUMBER
C24: =Calculations!B451 | I24: =Calculations!B6 | L24: =Calculations!B7 | O24: =Calculations!B8 | Q24: =+'Costing Sheet'!I$22+SUM(Invoice!F91:F100)-SUM(F91:F100) -> 0 | S24: =-'Costing Sheet'!K$22 -> 0 | U24: =+Calculations!B$526+SUM(Invoice!F91:F100)-SUM(F91:F100) -> 0
J25: =Calculations!B9
J26: =+Calculations!B12
C28: =Calculations!B452 | I28: =Calculations!B18 | L28: =Calculations!B19 | O28: =Calculations!B20 | Q28: =+'Costing Sheet'!I$23 -> 0 | S28: =-'Costing Sheet'!K$23 -> 0 | U28: =+Calculations!B$527 -> 0
J29: =Calculations!B21
J30: =+Calculations!B24
C32: =Calculations!B453 | I32: =Calculations!B30 | L32: =Calculations!B31 | O32: =Calculations!B32 | Q32: =+'Costing Sheet'!I$24 -> 0 | S32: =-'Costing Sheet'!K$24 -> 0 | U32: =+Calculations!B$528 -> 0
J33: =Calculations!B33
J34: =+Calculations!B36
C36: =Calculations!B454 | I36: =Calculations!B42 | L36: =Calculations!B43 | O36: =Calculations!B44 | Q36: =+'Costing Sheet'!I$25 -> 0 | S36: =-'Costing Sheet'!K$25 -> 0 | U36: =+Calculations!B$529 -> 0
J37: =Calculations!B45
J38: =+Calculations!B48
C40: =Calculations!B455 | I40: =Calculations!B54 | L40: =Calculations!B55 | O40: =Calculations!B56 | Q40: =+'Costing Sheet'!I$26 -> 0 | S40: =-'Costing Sheet'!K$26 -> 0 | U40: =+Calculations!B$530 -> 0
J41: =Calculations!B57
J42: =+Calculations!B60
C44: =Calculations!B456 | I44: =Calculations!B66 | L44: =Calculations!B67 | O44: =Calculations!B68 | Q44: =+'Costing Sheet'!I$27 -> 0 | S44: =-'Costing Sheet'!K$27 -> 0 | U44: =+Calculations!B$531 -> 0
J45: =Calculations!B69
J46: =+Calculations!B72
C48: =Calculations!B457 | I48: =Calculations!B78 | L48: =Calculations!B79 | O48: =Calculations!B80 | Q48: =+'Costing Sheet'!I$28 -> 0 | S48: =-'Costing Sheet'!K$28 -> 0 | U48: =+Calculations!B$532 -> 0
J49: =Calculations!B81
J50: =+Calculations!B84
C52: =Calculations!B458 | I52: =Calculations!B90 | L52: =Calculations!B91 | O52: =Calculations!B92 | Q52: =+'Costing Sheet'!I$29 -> 0 | S52: =-'Costing Sheet'!K$29 -> 0 | U52: =+Calculations!B$533 -> 0
J53: =Calculations!B93
J54: =+Calculations!B96
C56: =Calculations!B459 | I56: =Calculations!B102 | L56: =Calculations!B103 | O56: =Calculations!B104 | Q56: =+'Costing Sheet'!I$30 -> 0 | S56: =-'Costing Sheet'!K$30 -> 0 | U56: =+Calculations!B$534 -> 0
J57: =Calculations!B105
J58: =+Calculations!B108
C60: =Calculations!B460 | I60: =Calculations!B114 | L60: =Calculations!B115 | O60: =Calculations!B116 | Q60: =+'Costing Sheet'!I$31 -> 0 | S60: =-'Costing Sheet'!K$31 -> 0 | U60: =+Calculations!B$535 -> 0
J61: =Calculations!B117
J62: =+Calculations!B120
C63: =UPPER('Sales Input Sheet'!E55)
B67: TRADE IN | I67: MAKE | L67: MODEL | O67: SERIAL NUMBER | Q67: DESCRIPTION | S67: TRADE ALLOWANCE | U67: TRADE PAYOFF
I68: =+Calculations!B504 | L68: =+Calculations!B506 | O68: =+Calculations!B502 | Q68: =Calculations!B514 | S68: =Calculations!B498 -> 0 | U68: =Calculations!B500 -> 0
I69: =+Calculations!B694 | L69: =+Calculations!B698 | O69: =+Calculations!B690 | Q69: =+Calculations!B678 | S69: =+Calculations!B682 -> 0 | U69: =+Calculations!B686 -> 0
I70: =+Calculations!B695 | L70: =+Calculations!B699 | O70: =+Calculations!B691 | Q70: =+Calculations!B679 | S70: =+Calculations!B683 -> 0 | U70: =+Calculations!B687 -> 0
I71: =+Calculations!B696 | L71: =+Calculations!B700 | O71: =+Calculations!B692 | Q71: =+Calculations!B680 | S71: =+Calculations!B684 -> 0 | U71: =+Calculations!B688 -> 0
I72: =+Calculations!B697 | L72: =+Calculations!B701 | O72: =+Calculations!B693 | Q72: =+Calculations!B681 | S72: =+Calculations!B685 -> 0 | U72: =+Calculations!B689 -> 0
I73: =+Calculations!B505 | L73: =+Calculations!B507 | O73: =+Calculations!B503 | Q73: =Calculations!B515 | S73: =Calculations!B499 -> 0 | U73: =Calculations!B501 -> 0
J76: =+Q2
J77: =+Q4
J78: =+Q5 | Q78: =+Q15 -> SALES PERSON | S78: =+S15
J79: =+Q10
Q80: =+UPPER('Costing Sheet'!$C$17)
C81: =+C12 | Q81: INVOICE NUMBER | S81: =+'Costing Sheet'!$C$13 -> 0
C82: =+C13 | Q82: INVOICE DATE | S82: ='Costing Sheet'!$C$11 -> 0
C83: =+'Costing Sheet'!C19 -> 0 | F83: =+'Costing Sheet'!E19 -> 0 | O83: =UPPER('Costing Sheet'!C17) | Q83: =UPPER('Costing Sheet'!E17)
B84: INVOICE SUMMARY
B86: DEALER PRICE OF ALL EQUIPMENT | F86: =+Calculations!B310+SUM(Invoice!F91:F100)-SUM(F91:F100) -> 0 | I86: PURCHASES BEFORE ADDITIONAL FEES, TAXES AND REBATES | L86: =+Calculations!B320 -> 0 | O86: PURCHASES WITH FEES BEFORE TAX AND REBATES | Q86: =Calculations!B437 -> 0 | S86: NET PURCHASE PRICE DUE FROM CUSTOMER | U86: =+Calculations!B436 -> 0
B87: =IF(F87=0,"","DISCOUNT") | F87: =-Calculations!B311 -> 0 | I87: DOCUMENT FEE (1) | L87: =+Calculations!B302 -> 0 | O87: DOC Stamp Tax | Q87: =+'Costing Sheet'!Q15 -> 0
B88: =_xlfn.CONCAT("SELLING PRICE",IF(B87="",""," NET")) -> SELLING PRICE | F88: =+Calculations!B312+SUM(Invoice!F91:F100)-SUM(F91:F100) -> 0 | O88: UCC Fee | Q88: =+'Costing Sheet'!Q13 -> 0 | S88: LESS:
B89: TRADE ALLOWANCE | F89: =-Calculations!B315 -> 0 | I89: FREIGHT | L89: =+'Costing Sheet'!Q3 -> 0 | O89: =+Calculations!B403 -> SALES TAX | Q89: =+Calculations!B405 -> 0 | S89: ADVANCED DEPOSIT | U89: =-'Costing Sheet'!Q17 -> 0
B90: TRADE PAYOFF | F90: =+Calculations!B316 -> 0 | I90: SET UP FEE (1) | L90: =+'Costing Sheet'!Q5 -> 0 | O90: =+Calculations!B399 | Q90: =+Calculations!B412 -> 0
B91: =IF(ISNUMBER(SEARCH("Kubota",Calculations!B640)),Calculations!B640,"") | F91: =IF(B91="","",+Calculations!B232) | I91: TIRE FEE | L91: =+Calculations!B386 -> 0 | O91: =+Calculations!B406 -> COUNTY SALES TAX OUT OF STATE OR NO COUNTY WAS SPECIFIED FOR CUSTOMER | Q91: =+Calculations!B413 -> 0
B92: =IF(ISNUMBER(SEARCH("Kubota",Calculations!B641)),Calculations!B641,"") | F92: =IF(B92="","",+Calculations!B233)
B93: =IF(ISNUMBER(SEARCH("Kubota",Calculations!B642)),Calculations!B642,"") | F93: =IF(B93="","",+Calculations!B234)
B94: =IF(ISNUMBER(SEARCH("Kubota",Calculations!B643)),Calculations!B643,"") | F94: =IF(B94="","",+Calculations!B235) | S94: ADDITIONAL DOWN PAYMENT | U94: =-'Costing Sheet'!Q19 -> 0
B95: =IF(ISNUMBER(SEARCH("Kubota",Calculations!B644)),Calculations!B644,"") | F95: =IF(B95="","",+Calculations!B236)
B96: =IF(ISNUMBER(SEARCH("Kubota",Calculations!B645)),Calculations!B645,"") | F96: =IF(B96="","",+Calculations!B237) | I96: BATTERY FEE | L96: =+Calculations!B385 -> 0 | O96: =+Calculations!B414 | Q96: =+Calculations!B407 -> 0
B97: =IF(ISNUMBER(SEARCH("Kubota",Calculations!B646)),Calculations!B646,"") | F97: =IF(B97="","",+Calculations!B238)
B98: =IF(ISNUMBER(SEARCH("Kubota",Calculations!B647)),Calculations!B647,"") | F98: =IF(B98="","",+Calculations!B239)
B99: =IF(ISNUMBER(SEARCH("Kubota",Calculations!B648)),Calculations!B648,"") | F99: =IF(B99="","",+Calculations!B240)
B100: =IF(ISNUMBER(SEARCH("Kubota",Calculations!B649)),Calculations!B649,"") | F100: =IF(B100="","",+Calculations!B241) | O100: =Calculations!$B$653
B101: =+Calculations!B417 | F101: =+Calculations!B421 -> 0 | I101: DMV & TITLE FEES | L101: =+Calculations!B439 -> 0 | O101: =Calculations!B651 | Q101: =-Calculations!B318 -> 0
B102: PURCHASES BEFORE ADDITIONAL FEES, TAXES AND REBATES | F102: =+Calculations!B320 -> 0 | I102: PURCHASES WITH FEES BEFORE TAX AND REBATES | L102: =+Calculations!B437 -> 0 | O102: NET PURCHASE PRICE DUE FROM CUSTOMER | Q102: =+Calculations!B436 -> 0 | S102: NET CASH BALANCE DUE | U102: =+Calculations!B438 -> 0
B103: (1) Document Fee and Set Up Fee: These charges represents cost and profit to the seller/dealer for items such as assembling, inspecting, cleaning and adjusting new and used units and preparing documents related to the sale.
B104: AS-IS and WITH ALL FAULTS. The only warranties applying to the equioment sold herein are those provided in a separate writing or offered by the manufacturer or, if applicable, by the manufacturer of the non-factory installed equipment. The Dealer expressly disclaims all warranties, either express or implied, including any implied warranty of merchantability and implied warranty of fitness for a particular purpose and the Dealer neither assumes nor authorizes any other person to assume for it any liability in connection with the sale of this equipment. Buyer shall not be entitled to recover from the Dealer any consequential damages, damages to property, damages for loss of use, loss of time, loss of profit, or income, or any other incidental damages.
B105: You agree to receive conversational messages sent via SMS/text message. This agreement isn't a condition of any purchase. Terms, Privacy Policy, and opt out process can be found at www.crystaltractor.com/read-our-policy-statement-xprivacy. Charges may apply. You may reply "Stop" at any time to opt-out.
B107: Accepted:
B108: ='Customer Input Screen'!C32 -> [Customer Signature] | Q108: ='Customer Input Screen'!C33 -> [Company Signature]
B110: Customer | Q110: Company

Sheet Tax Exemption Form
B1: CAIRO, GA | CHIEFLAND,FL. | DELAND, FL. | K1: CRYSTAL | R1: =+Calculations!B568
B3: HASTINGS, FL | HOMOSASSA, FL | JACKSONVILLE, FL | LECANTO, FL | R3: =+Calculations!B569
B5: LEESBURG, FL. | LIVE OAK, FL. | MADISON, FL | R5: =+Calculations!B570
B8: MIAMI, FL. | PALATKA, FL. | PANAMA CITY, FL | OCALA, FL | K8: TRACTOR & EQUIPMENT | R8: =+Calculations!B571
B9: SPRING HILL, FL. | STARKE, FL. | TALLAHASSEE, FL | K9: =+Calculations!B572 -> CRYSTALTRACTOR.COM
C11: Invoice Number | E11: =+'Costing Sheet'!C13 -> 0
C12: Invoice Date | E12: ='Costing Sheet'!C11 -> 0 | N12: Invoice Number | R12: =+'Costing Sheet'!C13 -> 0
N13: Sales Person | R13: =IF('Sales Input Sheet'!C15<>"",UPPER('Sales Input Sheet'!C15),"")
C14: =IF('Customer Input Screen'!I10<>"",UPPER('Customer Input Screen'!I10),"")
C15: =IF(Calculations!B3<>"",UPPER(Calculations!B3),"")
C16: =IF('Customer Input Screen'!I14<>"",UPPER('Customer Input Screen'!I14),"")
C17: =IF('Customer Input Screen'!I15<>"",UPPER('Customer Input Screen'!I15),"")
C18: =+Calculations!$B$601
B20: TAX EXEMPTION CERTIFICATION
B23: =Calculations!B561 -> THIS IS TO CERTIFY THAT THE ITEMS IDENTIFIED BELOW, PURCHASED ON OR AFTER JANUARY 0, 1900 FROM ARE PURCHASED, LEASED, LICENSED, OR RENTED FOR THE FOLLOWING PURPOSE. THIS IS NOT INTENDED TO BE AN EXHAUSTIVE LIST:
C25: =IF(OR('Costing Sheet'!M$3="",'Costing Sheet'!M$3="no"),"",IFERROR(VLOOKUP('Costing Sheet'!M7,'Tax Exemption Cert table'!A$2:B$15,2,FALSE),""))
C27: =IF(OR('Costing Sheet'!M$3="",'Costing Sheet'!M$3="no"),"",IFERROR(VLOOKUP('Costing Sheet'!M9,'Tax Exemption Cert table'!A$2:B$15,2,FALSE),""))
C29: =IF(OR('Costing Sheet'!M$3="",'Costing Sheet'!M$3="no"),"",IFERROR(VLOOKUP('Costing Sheet'!M11,'Tax Exemption Cert table'!A$2:B$15,2,FALSE),""))
C31: =IF(OR('Costing Sheet'!M$3="",'Costing Sheet'!M$3="no"),"",IFERROR(VLOOKUP('Costing Sheet'!M13,'Tax Exemption Cert table'!A$2:B$15,2,FALSE),""))
C33: =IF(OR('Costing Sheet'!M$3="",'Costing Sheet'!M$3="no"),"",IFERROR(VLOOKUP('Costing Sheet'!M15,'Tax Exemption Cert table'!A$2:B$15,2,FALSE),""))
B35: Sales and Use Tax Certificate No. | H35: =+'Customer Input Screen'!I25
B37: I understand that if I use the item for any purpose other than the one I stated, I must pay tax on the purchase or lease price of the taxable item directly to the Department of Revenue. I understand that if I fraudulently issue this certificate to evade the payment of sales tax I will be liable for payment of the sales tax plus a penalty of 200% of the tax and may be subject to conviction of a third degree felony. Under penalties of perjury, I declare that I have read the foregoing document and that the facts stated in it are true.
B39: {='Finance Declination'!Q40:S40} -> [Customer Signature] | C39: 0 | D39: 0
B41: Customer

Sheet We Owe
B1: CAIRO, GA | CHIEFLAND,FL. | DELAND, FL. | K1: CRYSTAL | R1: =+Calculations!B568
B3: HASTINGS, FL | HOMOSASSA, FL | JACKSONVILLE, FL | LECANTO, FL | R3: =+Calculations!B569
B5: LEESBURG, FL. | LIVE OAK, FL. | MADISON, FL | R5: =+Calculations!B570
B7: MIAMI, FL. | PALATKA, FL. | PANAMA CITY, FL | OCALA, FL | K7: TRACTOR & EQUIPMENT | R7: =+Calculations!B571
B9: SPRING HILL, FL. | STARKE, FL. | TALLAHASSEE, FL | K9: =+Calculations!B572 -> CRYSTALTRACTOR.COM | R9: =+Calculations!B572 -> CRYSTALTRACTOR.COM
C13: Invoice Date | E13: ='Costing Sheet'!C11 -> 0 | N13: Invoice Number | R13: =+'Costing Sheet'!C13 -> 0
N14: Sales Person | R14: =IF('Sales Input Sheet'!C15<>"",UPPER('Sales Input Sheet'!C15),"")
C15: =IF('Customer Input Screen'!I10<>"",UPPER('Customer Input Screen'!I10),"")
C16: =IF(Calculations!B3<>"",UPPER(Calculations!B3),"")
C17: =IF('Customer Input Screen'!I14<>"",UPPER('Customer Input Screen'!I14),"")
C18: =IF('Customer Input Screen'!I15<>"",UPPER('Customer Input Screen'!I15),"")
C19: =+Calculations!$B$601
B21: WE OWE
B24: =Calculations!B567 -> CUSTOMER ACKNOWLEDGES THAT THEY HAVE / IT HAS RECEIVED ALL ITEMS TO BE DELIVERED BY UNDER INVOICE NUMBER - EXCEPT FOR THOSE ITEMS LISTED BELOW:
C26: =Calculations!B628 -> NOTHING OWED
E27: =IF(OR($C26=" ",$C26="NOTHING OWED"),"",UPPER(_xlfn.CONCAT("Apply to Stock Number ",'Costing Sheet'!A22))) | K27: =IF(OR($C26=" ",$C26="NOTHING OWED"),"",UPPER(_xlfn.CONCAT('Costing Sheet'!C22))) | N27: =IF(OR($C26=" ",$C26="NOTHING OWED"),"",UPPER(_xlfn.CONCAT('Costing Sheet'!E22)))
C28: =Calculations!B629
E29: =IF(OR($C28=" ",$C28="NOTHING OWED",$C28=""),"",UPPER(_xlfn.CONCAT("Apply to Stock Number ",'Costing Sheet'!A23))) | K29: =IF(OR($C28=" ",$C28="NOTHING OWED"),"",UPPER(_xlfn.CONCAT('Costing Sheet'!C23))) | N29: =IF(OR($C28=" ",$C28="NOTHING OWED"),"",UPPER(_xlfn.CONCAT('Costing Sheet'!E23)))
C30: =Calculations!B630
E31: =IF(OR($C30=" ",$C30="NOTHING OWED",$C30=""),"",UPPER(_xlfn.CONCAT("Apply to Stock Number ",'Costing Sheet'!A24))) | K31: =IF(OR($C30=" ",$C30="NOTHING OWED"),"",UPPER(_xlfn.CONCAT('Costing Sheet'!C24))) | N31: =IF(OR($C30=" ",$C30="NOTHING OWED"),"",UPPER(_xlfn.CONCAT('Costing Sheet'!E24)))
C32: =Calculations!B631
E33: =IF(OR($C32=" ",$C32="NOTHING OWED",$C32=""),"",UPPER(_xlfn.CONCAT("Apply to Stock Number ",'Costing Sheet'!A25))) | K33: =IF(OR($C32=" ",$C32="NOTHING OWED"),"",UPPER(_xlfn.CONCAT('Costing Sheet'!C25))) | N33: =IF(OR($C32=" ",$C32="NOTHING OWED"),"",UPPER(_xlfn.CONCAT('Costing Sheet'!E25)))
C34: =Calculations!B632
E35: =IF(OR($C34=" ",$C34="NOTHING OWED",$C34=""),"",UPPER(_xlfn.CONCAT("Apply to Stock Number ",'Costing Sheet'!A26))) | K35: =IF(OR($C34=" ",$C34="NOTHING OWED"),"",UPPER(_xlfn.CONCAT('Costing Sheet'!C26))) | N35: =IF(OR($C34=" ",$C34="NOTHING OWED"),"",UPPER(_xlfn.CONCAT('Costing Sheet'!E26)))
C36: =Calculations!B633
E37: =IF(OR($C36=" ",$C36="NOTHING OWED",$C36=""),"",UPPER(_xlfn.CONCAT("Apply to Stock Number ",'Costing Sheet'!A27))) | K37: =IF(OR($C36=" ",$C36="NOTHING OWED"),"",UPPER(_xlfn.CONCAT('Costing Sheet'!C27))) | N37: =IF(OR($C36=" ",$C36="NOTHING OWED"),"",UPPER(_xlfn.CONCAT('Costing Sheet'!E27)))
C38: =Calculations!B634
E39: =IF(OR($C38=" ",$C38="NOTHING OWED",$C38=""),"",UPPER(_xlfn.CONCAT("Apply to Stock Number ",'Costing Sheet'!A28))) | K39: =IF(OR($C38=" ",$C38="NOTHING OWED"),"",UPPER(_xlfn.CONCAT('Costing Sheet'!C28))) | N39: =IF(OR($C38=" ",$C38="NOTHING OWED"),"",UPPER(_xlfn.CONCAT('Costing Sheet'!E28)))
C40: =Calculations!B635
E41: =IF(OR($C40=" ",$C40="NOTHING OWED",$C40=""),"",UPPER(_xlfn.CONCAT("Apply to Stock Number ",'Costing Sheet'!A29))) | K41: =IF(OR($C40=" ",$C40="NOTHING OWED"),"",UPPER(_xlfn.CONCAT('Costing Sheet'!C29))) | N41: =IF(OR($C40=" ",$C40="NOTHING OWED"),"",UPPER(_xlfn.CONCAT('Costing Sheet'!E29)))
C42: =Calculations!B636
E43: =IF(OR($C42=" ",$C42="NOTHING OWED",$C42=""),"",UPPER(_xlfn.CONCAT("Apply to Stock Number ",'Costing Sheet'!A30))) | K43: =IF(OR($C42=" ",$C42="NOTHING OWED"),"",UPPER(_xlfn.CONCAT('Costing Sheet'!C30))) | N43: =IF(OR($C42=" ",$C42="NOTHING OWED"),"",UPPER(_xlfn.CONCAT('Costing Sheet'!E30)))
C44: =Calculations!B637
E45: =IF(OR($C44=" ",$C44="NOTHING OWED",$C44=""),"",UPPER(_xlfn.CONCAT("Apply to Stock Number ",'Costing Sheet'!A31))) | K45: =IF(OR($C44=" ",$C44="NOTHING OWED"),"",UPPER(_xlfn.CONCAT('Costing Sheet'!C31))) | N45: =IF(OR($C44=" ",$C44="NOTHING OWED"),"",UPPER(_xlfn.CONCAT('Costing Sheet'!E31)))
C46: =+Calculations!B196
E47: =IF(C46<>" ",IF('Costing Sheet'!K57="Apply to Whole Invoice",UPPER('Costing Sheet'!K57),UPPER(_xlfn.CONCAT("Apply to Stock Number ",'Costing Sheet'!K57))),"")
C48: =+Calculations!B197
E49: =IF(C48<>" ",IF('Costing Sheet'!K58="Apply to Whole Invoice",UPPER('Costing Sheet'!K58),UPPER(_xlfn.CONCAT("Apply to Stock Number ",'Costing Sheet'!K58))),"")
C50: =+Calculations!B198
E51: =IF(C50<>" ",IF('Costing Sheet'!K59="Apply to Whole Invoice",UPPER('Costing Sheet'!K59),UPPER(_xlfn.CONCAT("Apply to Stock Number ",'Costing Sheet'!K59))),"")
C52: =+Calculations!B199
E53: =IF(C52<>" ",IF('Costing Sheet'!K60="Apply to Whole Invoice",UPPER('Costing Sheet'!K60),UPPER(_xlfn.CONCAT("Apply to Stock Number ",'Costing Sheet'!K60))),"")
C54: =+Calculations!B200
E55: =IF(C54<>" ",IF('Costing Sheet'!K61="Apply to Whole Invoice",UPPER('Costing Sheet'!K61),UPPER(_xlfn.CONCAT("Apply to Stock Number ",'Costing Sheet'!K61))),"")
B59: ='Customer Input Screen'!C32 -> [Customer Signature]
B61: Customer

Sheet Finance Menu
B1: CAIRO, GA | CHIEFLAND,FL. | DELAND, FL. | K1: CRYSTAL | Q1: =+Calculations!$B$568
B3: HASTINGS, FL | HOMOSASSA, FL | JACKSONVILLE, FL | LECANTO, FL | Q3: =+Calculations!$B$569
B5: LEESBURG, FL. | LIVE OAK, FL. | MADISON, FL | K5: TRACTOR & EQUIPMENT | Q5: =Calculations!B570
B7: MIAMI, FL. | PALATKA, FL. | PANAMA CITY, FL | OCALA, FL
B9: SPRING HILL, FL. | STARKE, FL. | TALLAHASSEE, FL | K9: =+Calculations!B572 -> CRYSTALTRACTOR.COM | Q9: =Calculations!B571
C12: Quote Number | D12: =+'Sales Input Sheet'!$C$11 -> 0 | R12: Sales Person | U12: =IF('Sales Input Sheet'!C15<>"",UPPER('Sales Input Sheet'!C15),"")
C13: =+Calculations!$B$597
C14: =+Calculations!B598
B16: EQUIPMENT PROTECTION OPTIONS
B18: TRANSACTION SUMMARY
B19: SELLING PRICE, NET OF DISCOUNTS | L19: =+Calculations!B312 -> 0
B20: Net Trade Value | L20: =-Calculations!B315+Calculations!B316 -> 0 | P20: Sales Tax | W20: =+Calculations!$F$405+Calculations!$F$412+Calculations!$F$413+Calculations!$F$407 -> 0
B21: Dealer Based Fees for Documents, Freight and Set Up | L21: =+Calculations!B302+'Costing Sheet'!Q3+'Costing Sheet'!Q5 -> 0 | P21: MANUFACTURER REBATE | W21: =-Calculations!B318 -> 0
B22: Governmental Fees | L22: =+Calculations!B386+Calculations!B385+Calculations!B439+'Costing Sheet'!Q13+'Costing Sheet'!Q15 -> 0 | P22: TOTAL DUE FROM CUSTOMER, plus Kubota Insurance, if purchased as shown below | W22: =+Calculations!F435 -> 0
B23: Down Payment | G23: TERM | O23: Rate | S23: BASE PAYMENT BASED UPON TERMS HEREIN LISTED
B24: ='Costing Sheet'!U11 -> 0 | G24: ='Finance Manager Input Sheet'!C16 -> 0 | O24: ='Finance Manager Input Sheet'!C17 -> 0 | S24: =Calculations!B596 -> 0
B25: =Calculations!B416 | E25: =IF(B25="","",Calculations!B724)
C27: Platinum Plan | F27: =AD27 -> Gold Plan | O27: =AF27 -> Silver Plan | U27: =AH27 -> Bronze Plan | AB27: Platinum Plan | AD27: Gold Plan | AF27: Silver Plan | AH27: Bronze Plan
C28: =AB28 | F28: =AD28 | O28: =AF28 | U28: =AH28 | AB28: {=IFERROR(INDEX('Finance Manager Input Sheet'!$AA$4:$AA$13, SMALL(IF('Finance Manager Input Sheet'!$BD$4:$BD$13="Platinum", ROW('Finance Manager Input Sheet'!$AA$4:$AA$13)-ROW('Finance Manager Input Sheet'!$AA$4)+1), ROW(A1))), "")} | AD28: {=IFERROR(INDEX('Finance Manager Input Sheet'!$AE$4:$AE$13, SMALL(IF('Finance Manager Input Sheet'!$BF$4:$BF$13="Gold", ROW('Finance Manager Input Sheet'!$AE$4:$AE$13)-ROW('Finance Manager Input Sheet'!$AE$4)+1), ROW(A1))), "")} | AF28: {=IFERROR(INDEX('Finance Manager Input Sheet'!$AI$4:$AI$13, SMALL(IF('Finance Manager Input Sheet'!$BH$4:$BH$13="Silver", ROW('Finance Manager Input Sheet'!$AI$4:$AI$13)-ROW('Finance Manager Input Sheet'!$AI$4)+1), ROW(A1))), "")} | AH28: {=IFERROR(INDEX('Finance Manager Input Sheet'!$AM$4:$AM$13, SMALL(IF('Finance Manager Input Sheet'!$BJ$4:$BJ$13="Bronze", ROW('Finance Manager Input Sheet'!$AM$4:$AM$13)-ROW('Finance Manager Input Sheet'!$AM$4)+1), ROW(A1))), "")}
C29: =AB29 | F29: =AD29 | O29: =AF29 | U29: =AH29 | AB29: {=IFERROR(INDEX('Finance Manager Input Sheet'!$AA$4:$AA$13, SMALL(IF('Finance Manager Input Sheet'!$BD$4:$BD$13="Platinum", ROW('Finance Manager Input Sheet'!$AA$4:$AA$13)-ROW('Finance Manager Input Sheet'!$AA$4)+1), ROW(A2))), "")} | AD29: {=IFERROR(INDEX('Finance Manager Input Sheet'!$AE$4:$AE$13, SMALL(IF('Finance Manager Input Sheet'!$BF$4:$BF$13="Gold", ROW('Finance Manager Input Sheet'!$AE$4:$AE$13)-ROW('Finance Manager Input Sheet'!$AE$4)+1), ROW(A2))), "")} | AF29: {=IFERROR(INDEX('Finance Manager Input Sheet'!$AI$4:$AI$13, SMALL(IF('Finance Manager Input Sheet'!$BH$4:$BH$13="Silver", ROW('Finance Manager Input Sheet'!$AI$4:$AI$13)-ROW('Finance Manager Input Sheet'!$AI$4)+1), ROW(A2))), "")} | AH29: {=IFERROR(INDEX('Finance Manager Input Sheet'!$AM$4:$AM$13, SMALL(IF('Finance Manager Input Sheet'!$BJ$4:$BJ$13="Bronze", ROW('Finance Manager Input Sheet'!$AM$4:$AM$13)-ROW('Finance Manager Input Sheet'!$AM$4)+1), ROW(A2))), "")}
C30: =AB30 | F30: =AD30 | O30: =AF30 | U30: =AH30 | AB30: {=IFERROR(INDEX('Finance Manager Input Sheet'!$AA$4:$AA$13, SMALL(IF('Finance Manager Input Sheet'!$BD$4:$BD$13="Platinum", ROW('Finance Manager Input Sheet'!$AA$4:$AA$13)-ROW('Finance Manager Input Sheet'!$AA$4)+1), ROW(A3))), "")} | AD30: {=IFERROR(INDEX('Finance Manager Input Sheet'!$AE$4:$AE$13, SMALL(IF('Finance Manager Input Sheet'!$BF$4:$BF$13="Gold", ROW('Finance Manager Input Sheet'!$AE$4:$AE$13)-ROW('Finance Manager Input Sheet'!$AE$4)+1), ROW(A3))), "")} | AF30: {=IFERROR(INDEX('Finance Manager Input Sheet'!$AI$4:$AI$13, SMALL(IF('Finance Manager Input Sheet'!$BH$4:$BH$13="Silver", ROW('Finance Manager Input Sheet'!$AI$4:$AI$13)-ROW('Finance Manager Input Sheet'!$AI$4)+1), ROW(A3))), "")} | AH30: {=IFERROR(INDEX('Finance Manager Input Sheet'!$AM$4:$AM$13, SMALL(IF('Finance Manager Input Sheet'!$BJ$4:$BJ$13="Bronze", ROW('Finance Manager Input Sheet'!$AM$4:$AM$13)-ROW('Finance Manager Input Sheet'!$AM$4)+1), ROW(A3))), "")}
C31: =AB31 | F31: =AD31 | O31: =AF31 | U31: =AH31 | AB31: {=IFERROR(INDEX('Finance Manager Input Sheet'!$AA$4:$AA$13, SMALL(IF('Finance Manager Input Sheet'!$BD$4:$BD$13="Platinum", ROW('Finance Manager Input Sheet'!$AA$4:$AA$13)-ROW('Finance Manager Input Sheet'!$AA$4)+1), ROW(A4))), "")} | AD31: {=IFERROR(INDEX('Finance Manager Input Sheet'!$AE$4:$AE$13, SMALL(IF('Finance Manager Input Sheet'!$BF$4:$BF$13="Gold", ROW('Finance Manager Input Sheet'!$AE$4:$AE$13)-ROW('Finance Manager Input Sheet'!$AE$4)+1), ROW(A4))), "")} | AF31: {=IFERROR(INDEX('Finance Manager Input Sheet'!$AI$4:$AI$13, SMALL(IF('Finance Manager Input Sheet'!$BH$4:$BH$13="Silver", ROW('Finance Manager Input Sheet'!$AI$4:$AI$13)-ROW('Finance Manager Input Sheet'!$AI$4)+1), ROW(A4))), "")} | AH31: {=IFERROR(INDEX('Finance Manager Input Sheet'!$AM$4:$AM$13, SMALL(IF('Finance Manager Input Sheet'!$BJ$4:$BJ$13="Bronze", ROW('Finance Manager Input Sheet'!$AM$4:$AM$13)-ROW('Finance Manager Input Sheet'!$AM$4)+1), ROW(A4))), "")}
C32: =AB32 | F32: =AD32 | O32: =AF32 | U32: =AH32 | AB32: {=IFERROR(INDEX('Finance Manager Input Sheet'!$AA$4:$AA$13, SMALL(IF('Finance Manager Input Sheet'!$BD$4:$BD$13="Platinum", ROW('Finance Manager Input Sheet'!$AA$4:$AA$13)-ROW('Finance Manager Input Sheet'!$AA$4)+1), ROW(A5))), "")} | AD32: {=IFERROR(INDEX('Finance Manager Input Sheet'!$AE$4:$AE$13, SMALL(IF('Finance Manager Input Sheet'!$BF$4:$BF$13="Gold", ROW('Finance Manager Input Sheet'!$AE$4:$AE$13)-ROW('Finance Manager Input Sheet'!$AE$4)+1), ROW(A5))), "")} | AF32: {=IFERROR(INDEX('Finance Manager Input Sheet'!$AI$4:$AI$13, SMALL(IF('Finance Manager Input Sheet'!$BH$4:$BH$13="Silver", ROW('Finance Manager Input Sheet'!$AI$4:$AI$13)-ROW('Finance Manager Input Sheet'!$AI$4)+1), ROW(A5))), "")} | AH32: {=IFERROR(INDEX('Finance Manager Input Sheet'!$AM$4:$AM$13, SMALL(IF('Finance Manager Input Sheet'!$BJ$4:$BJ$13="Bronze", ROW('Finance Manager Input Sheet'!$AM$4:$AM$13)-ROW('Finance Manager Input Sheet'!$AM$4)+1), ROW(A5))), "")}
C33: =AB33 | F33: =AD33 | O33: =AF33 | U33: =AH33 | AB33: {=IFERROR(INDEX('Finance Manager Input Sheet'!$AA$4:$AA$13, SMALL(IF('Finance Manager Input Sheet'!$BD$4:$BD$13="Platinum", ROW('Finance Manager Input Sheet'!$AA$4:$AA$13)-ROW('Finance Manager Input Sheet'!$AA$4)+1), ROW(A6))), "")} | AD33: {=IFERROR(INDEX('Finance Manager Input Sheet'!$AE$4:$AE$13, SMALL(IF('Finance Manager Input Sheet'!$BF$4:$BF$13="Gold", ROW('Finance Manager Input Sheet'!$AE$4:$AE$13)-ROW('Finance Manager Input Sheet'!$AE$4)+1), ROW(A6))), "")} | AF33: {=IFERROR(INDEX('Finance Manager Input Sheet'!$AI$4:$AI$13, SMALL(IF('Finance Manager Input Sheet'!$BH$4:$BH$13="Silver", ROW('Finance Manager Input Sheet'!$AI$4:$AI$13)-ROW('Finance Manager Input Sheet'!$AI$4)+1), ROW(A6))), "")} | AH33: {=IFERROR(INDEX('Finance Manager Input Sheet'!$AM$4:$AM$13, SMALL(IF('Finance Manager Input Sheet'!$BJ$4:$BJ$13="Bronze", ROW('Finance Manager Input Sheet'!$AM$4:$AM$13)-ROW('Finance Manager Input Sheet'!$AM$4)+1), ROW(A6))), "")}
C34: =AB34 | F34: =AD34 | O34: =AF34 | U34: =AH34 | AB34: {=IFERROR(INDEX('Finance Manager Input Sheet'!$AA$4:$AA$13, SMALL(IF('Finance Manager Input Sheet'!$BD$4:$BD$13="Platinum", ROW('Finance Manager Input Sheet'!$AA$4:$AA$13)-ROW('Finance Manager Input Sheet'!$AA$4)+1), ROW(A7))), "")} | AD34: {=IFERROR(INDEX('Finance Manager Input Sheet'!$AE$4:$AE$13, SMALL(IF('Finance Manager Input Sheet'!$BF$4:$BF$13="Gold", ROW('Finance Manager Input Sheet'!$AE$4:$AE$13)-ROW('Finance Manager Input Sheet'!$AE$4)+1), ROW(A7))), "")} | AF34: {=IFERROR(INDEX('Finance Manager Input Sheet'!$AI$4:$AI$13, SMALL(IF('Finance Manager Input Sheet'!$BH$4:$BH$13="Silver", ROW('Finance Manager Input Sheet'!$AI$4:$AI$13)-ROW('Finance Manager Input Sheet'!$AI$4)+1), ROW(A7))), "")} | AH34: {=IFERROR(INDEX('Finance Manager Input Sheet'!$AM$4:$AM$13, SMALL(IF('Finance Manager Input Sheet'!$BJ$4:$BJ$13="Bronze", ROW('Finance Manager Input Sheet'!$AM$4:$AM$13)-ROW('Finance Manager Input Sheet'!$AM$4)+1), ROW(A7))), "")}
C35: =AB35 | F35: =AD35 | O35: =AF35 | U35: =AH35 | AB35: {=IFERROR(INDEX('Finance Manager Input Sheet'!$AA$4:$AA$13, SMALL(IF('Finance Manager Input Sheet'!$BD$4:$BD$13="Platinum", ROW('Finance Manager Input Sheet'!$AA$4:$AA$13)-ROW('Finance Manager Input Sheet'!$AA$4)+1), ROW(A8))), "")} | AD35: {=IFERROR(INDEX('Finance Manager Input Sheet'!$AE$4:$AE$13, SMALL(IF('Finance Manager Input Sheet'!$BF$4:$BF$13="Gold", ROW('Finance Manager Input Sheet'!$AE$4:$AE$13)-ROW('Finance Manager Input Sheet'!$AE$4)+1), ROW(A8))), "")} | AF35: {=IFERROR(INDEX('Finance Manager Input Sheet'!$AI$4:$AI$13, SMALL(IF('Finance Manager Input Sheet'!$BH$4:$BH$13="Silver", ROW('Finance Manager Input Sheet'!$AI$4:$AI$13)-ROW('Finance Manager Input Sheet'!$AI$4)+1), ROW(A8))), "")} | AH35: {=IFERROR(INDEX('Finance Manager Input Sheet'!$AM$4:$AM$13, SMALL(IF('Finance Manager Input Sheet'!$BJ$4:$BJ$13="Bronze", ROW('Finance Manager Input Sheet'!$AM$4:$AM$13)-ROW('Finance Manager Input Sheet'!$AM$4)+1), ROW(A8))), "")}
C36: =AB36 | F36: =AD36 | O36: =AF36 | U36: =AH36 | AB36: {=IFERROR(INDEX('Finance Manager Input Sheet'!$AA$4:$AA$13, SMALL(IF('Finance Manager Input Sheet'!$BD$4:$BD$13="Platinum", ROW('Finance Manager Input Sheet'!$AA$4:$AA$13)-ROW('Finance Manager Input Sheet'!$AA$4)+1), ROW(A9))), "")} | AD36: {=IFERROR(INDEX('Finance Manager Input Sheet'!$AE$4:$AE$13, SMALL(IF('Finance Manager Input Sheet'!$BF$4:$BF$13="Gold", ROW('Finance Manager Input Sheet'!$AE$4:$AE$13)-ROW('Finance Manager Input Sheet'!$AE$4)+1), ROW(A9))), "")} | AF36: {=IFERROR(INDEX('Finance Manager Input Sheet'!$AI$4:$AI$13, SMALL(IF('Finance Manager Input Sheet'!$BH$4:$BH$13="Silver", ROW('Finance Manager Input Sheet'!$AI$4:$AI$13)-ROW('Finance Manager Input Sheet'!$AI$4)+1), ROW(A9))), "")} | AH36: {=IFERROR(INDEX('Finance Manager Input Sheet'!$AM$4:$AM$13, SMALL(IF('Finance Manager Input Sheet'!$BJ$4:$BJ$13="Bronze", ROW('Finance Manager Input Sheet'!$AM$4:$AM$13)-ROW('Finance Manager Input Sheet'!$AM$4)+1), ROW(A9))), "")}
C37: =AB37 | F37: =AD37 | O37: =AF37 | U37: =AH37 | AB37: {=IFERROR(INDEX('Finance Manager Input Sheet'!$AA$4:$AA$13, SMALL(IF('Finance Manager Input Sheet'!$BD$4:$BD$13="Platinum", ROW('Finance Manager Input Sheet'!$AA$4:$AA$13)-ROW('Finance Manager Input Sheet'!$AA$4)+1), ROW(A10))), "")} | AD37: {=IFERROR(INDEX('Finance Manager Input Sheet'!$AE$4:$AE$13, SMALL(IF('Finance Manager Input Sheet'!$BF$4:$BF$13="Gold", ROW('Finance Manager Input Sheet'!$AE$4:$AE$13)-ROW('Finance Manager Input Sheet'!$AE$4)+1), ROW(A10))), "")} | AF37: {=IFERROR(INDEX('Finance Manager Input Sheet'!$AI$4:$AI$13, SMALL(IF('Finance Manager Input Sheet'!$BH$4:$BH$13="Silver", ROW('Finance Manager Input Sheet'!$AI$4:$AI$13)-ROW('Finance Manager Input Sheet'!$AI$4)+1), ROW(A10))), "")} | AH37: {=IFERROR(INDEX('Finance Manager Input Sheet'!$AM$4:$AM$13, SMALL(IF('Finance Manager Input Sheet'!$BJ$4:$BJ$13="Bronze", ROW('Finance Manager Input Sheet'!$AM$4:$AM$13)-ROW('Finance Manager Input Sheet'!$AM$4)+1), ROW(A10))), "")}
C38: =AB38 | F38: =AD38 | O38: =AF38 | U38: =AH38 | AB38: {=IFERROR(INDEX('Finance Manager Input Sheet'!$AA$4:$AA$13, SMALL(IF('Finance Manager Input Sheet'!$BD$4:$BD$13="Platinum", ROW('Finance Manager Input Sheet'!$AA$4:$AA$13)-ROW('Finance Manager Input Sheet'!$AA$4)+1), ROW(A11))), "")} | AD38: {=IFERROR(INDEX('Finance Manager Input Sheet'!$AE$4:$AE$13, SMALL(IF('Finance Manager Input Sheet'!$BF$4:$BF$13="Gold", ROW('Finance Manager Input Sheet'!$AE$4:$AE$13)-ROW('Finance Manager Input Sheet'!$AE$4)+1), ROW(A11))), "")} | AF38: {=IFERROR(INDEX('Finance Manager Input Sheet'!$AI$4:$AI$13, SMALL(IF('Finance Manager Input Sheet'!$BH$4:$BH$13="Silver", ROW('Finance Manager Input Sheet'!$AI$4:$AI$13)-ROW('Finance Manager Input Sheet'!$AI$4)+1), ROW(A11))), "")} | AH38: {=IFERROR(INDEX('Finance Manager Input Sheet'!$AM$4:$AM$13, SMALL(IF('Finance Manager Input Sheet'!$BJ$4:$BJ$13="Bronze", ROW('Finance Manager Input Sheet'!$AM$4:$AM$13)-ROW('Finance Manager Input Sheet'!$AM$4)+1), ROW(A11))), "")}
C39: =AB39 | F39: =AD39 | O39: =AF39 | U39: =AH39 | AB39: {=IFERROR(INDEX('Finance Manager Input Sheet'!$AA$4:$AA$13, SMALL(IF('Finance Manager Input Sheet'!$BD$4:$BD$13="Platinum", ROW('Finance Manager Input Sheet'!$AA$4:$AA$13)-ROW('Finance Manager Input Sheet'!$AA$4)+1), ROW(A12))), "")} | AD39: {=IFERROR(INDEX('Finance Manager Input Sheet'!$AE$4:$AE$13, SMALL(IF('Finance Manager Input Sheet'!$BF$4:$BF$13="Gold", ROW('Finance Manager Input Sheet'!$AE$4:$AE$13)-ROW('Finance Manager Input Sheet'!$AE$4)+1), ROW(A12))), "")} | AF39: {=IFERROR(INDEX('Finance Manager Input Sheet'!$AI$4:$AI$13, SMALL(IF('Finance Manager Input Sheet'!$BH$4:$BH$13="Silver", ROW('Finance Manager Input Sheet'!$AI$4:$AI$13)-ROW('Finance Manager Input Sheet'!$AI$4)+1), ROW(A12))), "")} | AH39: {=IFERROR(INDEX('Finance Manager Input Sheet'!$AM$4:$AM$13, SMALL(IF('Finance Manager Input Sheet'!$BJ$4:$BJ$13="Bronze", ROW('Finance Manager Input Sheet'!$AM$4:$AM$13)-ROW('Finance Manager Input Sheet'!$AM$4)+1), ROW(A12))), "")}
C45: =UPPER(_xlfn.CONCAT(TEXT(Calculations!$B$610+Calculations!$B$596,"$#,#00.00"),IF($G$24<=1,""," PER MONTH"))) -> #NUM! | F45: =UPPER(_xlfn.CONCAT(TEXT(Calculations!$B$611+Calculations!$B$596,"$#,#00.00"),IF(G24<=1,""," PER MONTH"))) -> #NUM! | O45: =UPPER(_xlfn.CONCAT(TEXT(Calculations!$B$612+Calculations!$B$596,"$#,#00.00"),IF(G24<=1,""," PER MONTH"))) -> #NUM! | U45: =UPPER(_xlfn.CONCAT(TEXT(Calculations!$B$613+Calculations!$B$596,"$#,#00.00"),IF(G24<=1,""," PER MONTH"))) -> #NUM!
C46: =UPPER(_xlfn.CONCAT("ADDITIONAL PAYMENT FOR ",'Finance Manager Input Sheet'!$R$3," IS APPROXIMATELY ",TEXT(Calculations!$B$610,"$#,#00.00"),IF($G$24<=1,""," PER MONTH"))) -> #NUM! | F46: =UPPER(_xlfn.CONCAT("ADDITIONAL PAYMENT FOR ",'Finance Manager Input Sheet'!$T$3," IS APPROXIMATELY ",TEXT(Calculations!$B$611,"$#,#00.00"),IF($G$24<=1,""," PER MONTH"))) -> #NUM! | O46: =UPPER(_xlfn.CONCAT("ADDITIONAL PAYMENT FOR ",'Finance Manager Input Sheet'!$V$3," IS APPROXIMATELY ",TEXT(Calculations!$B$612,"$#,#00.00"),IF($G$24<=1,""," PER MONTH"))) -> #NUM! | U46: =UPPER(_xlfn.CONCAT("ADDITIONAL PAYMENT FOR ",'Finance Manager Input Sheet'!$X$3," IS APPROXIMATELY ",TEXT(Calculations!$B$613,"$#,#00.00"),IF($G$24<=1,""," PER MONTH"))) -> #NUM!
C47: Price | D47: =+'Finance Manager Input Sheet'!AB14 -> 0 | F47: Price | K47: =+'Finance Manager Input Sheet'!AF14 -> 0 | O47: Price | Q47: =+'Finance Manager Input Sheet'!AJ14 -> 0 | U47: Price | W47: =+'Finance Manager Input Sheet'!AN14 -> 0
C48: Tax | D48: =+D49-D47 -> 0 | F48: Tax | K48: =+K49-K47 -> 0 | O48: Tax | Q48: =+Q49-Q47 -> 0 | U48: Tax | W48: =+W49-W47 -> 0
C49: Total Package Price | D49: =+'Finance Manager Input Sheet'!AC14 -> 0 | F49: Total Package Price | K49: =+'Finance Manager Input Sheet'!AG14 -> 0 | O49: Total Package Price | Q49: =+'Finance Manager Input Sheet'!AK14 -> 0 | U49: Total Package Price | W49: =+'Finance Manager Input Sheet'!AO14 -> 0
C50: Accept | D50: Decline | F50: Accept | K50: Decline | O50: Accept | Q50: Decline | U50: Accept | W50: Decline
B53: We make available to all of our customers optional products and plans that provide additional protection in connection with the purchase and/or financing of your equipment. Each of these optional products is described in detail in separate contracts and all forms and contracts are available for your review prior to purchase. You are not required to buy any of the products in order to obtain financing. The "Accepted Protection" column means that you have purchased these protection options. (If you accepted a protection package, each individual product is itemized.) The "Declined Protection" column means that you have chosen not to purchase any of the declined products or packages, and you will not be eligible for the benefits associated with the declined products/packages. If you accept, you may choose to pay cash for the plan or it can be financed through your Promissory Note/Security Agreement (PNSA), lease or retail installment contract with the approval of the financial institution. The dealership is compensated for providing financial products and services. I understand that this Menu tool is not a legal contract and that these payments are estimates. Complete terms and conditions of each optional products is detailed in the agreements itself.
B57: =Calculations!B614 -> For presentation purposes and submitting for approval of financing, payments are based upon a month term at an annual interest rate of 0.00%. Actual term and rates may vary based upon financing available based upon customers credit and other factors.
B63: Accepted:
B66: ='Customer Input Screen'!C32 -> [Customer Signature]
B67: Customer | T67: Prepared by | U67: ='Finance Manager Input Sheet'!G2 -> 0
T68: %(Invoice Date)%

Sheet Finance Declination
B1: CAIRO, GA | CHIEFLAND,FL. | DELAND, FL. | L1: CRYSTAL | R1: =+Calculations!$B$568
B3: HASTINGS, FL | HOMOSASSA, FL | JACKSONVILLE, FL | LECANTO, FL | R3: =+Calculations!$B$569
B5: LEESBURG, FL. | LIVE OAK, FL. | MADISON, FL | L5: TRACTOR & EQUIPMENT | R5: =Calculations!B570
B7: MIAMI, FL. | PALATKA, FL. | PANAMA CITY, FL | OCALA, FL
B9: SPRING HILL, FL. | STARKE, FL. | TALLAHASSEE, FL | L9: =+Calculations!B572 -> CRYSTALTRACTOR.COM | R9: =Calculations!B571
C11: Quote Number | D11: =+'Sales Input Sheet'!$C$11 -> 0 | S11: Sales Person | V11: =IF('Sales Input Sheet'!C15<>"",UPPER('Sales Input Sheet'!C15),"")
C12: =+Calculations!$B$597
C13: =+Calculations!B598
B15: EQUIPMENT PROTECTION OPTIONS
B17: TRANSACTION SUMMARY
B18: SELLING PRICE, NET OF DISCOUNTS | M18: =+Calculations!B312 -> 0 | Q18: Accepted Products | X18: =+Calculations!B321 -> 0
B19: Net Trade Value | M19: =-Calculations!B315+Calculations!B316 -> 0 | Q19: Sales Tax | X19: =+Calculations!$B$405+Calculations!$B$412+Calculations!$B$413+Calculations!$B$407 -> 0
B20: Dealer Based Fees for Documents, Freight and Prep | M20: =+Calculations!B302+'Costing Sheet'!Q3+'Costing Sheet'!Q5 -> 0 | Q20: MANUFACTURER REBATE | X20: =-Calculations!B318 -> 0
B21: Governmental Fees | M21: =+Calculations!B386+Calculations!B385+Calculations!B439+'Costing Sheet'!Q13+'Costing Sheet'!Q15 -> 0 | Q21: TOTAL DUE FROM CUSTOMER, plus Kubota Insurance, if applicable, as shown below | X21: =+Calculations!B435 -> 0
B22: Down Payment | G22: TERM | P22: Rate | T22: BASE PAYMENT BASED UPON TERMS HEREIN LISTED
B23: ='Costing Sheet'!U11 -> 0 | G23: ='Finance Manager Input Sheet'!C16 -> 0 | P23: ='Finance Manager Input Sheet'!C17 -> 0 | T23: =Calculations!B450 -> 0
C24: =Calculations!B723
C26: =AA26 -> Customer Accepted Protection Options | Q26: =AC26 -> Customer Declined Protection Options | AA26: Customer Accepted Protection Options | AC26: Customer Declined Protection Options
C27: =AA27 | Q27: =AC27 | AA27: {=IFERROR(INDEX('Finance Manager Input Sheet'!$AQ$4:$AQ$13, SMALL(IF('Finance Manager Input Sheet'!$BA$4:$BA$13="Customer Accepted", ROW('Finance Manager Input Sheet'!$AQ$4:$AQ$13)-ROW('Finance Manager Input Sheet'!$AQ$4)+1), ROW(A1))), "")} | AC27: {=IFERROR(INDEX('Finance Manager Input Sheet'!$AU$4:$AU$13, SMALL(IF('Finance Manager Input Sheet'!$BB$4:$BB$13="Customer Declined", ROW('Finance Manager Input Sheet'!$AU$4:$AU$13)-ROW('Finance Manager Input Sheet'!$AU$4)+1), ROW(C1))), "")}
C28: =AA28 | Q28: =AC28 | AA28: {=IFERROR(INDEX('Finance Manager Input Sheet'!$AQ$4:$AQ$13, SMALL(IF('Finance Manager Input Sheet'!$BA$4:$BA$13="Customer Accepted", ROW('Finance Manager Input Sheet'!$AQ$4:$AQ$13)-ROW('Finance Manager Input Sheet'!$AQ$4)+1), ROW(A2))), "")} | AC28: {=IFERROR(INDEX('Finance Manager Input Sheet'!$AU$4:$AU$13, SMALL(IF('Finance Manager Input Sheet'!$BB$4:$BB$13="Customer Declined", ROW('Finance Manager Input Sheet'!$AU$4:$AU$13)-ROW('Finance Manager Input Sheet'!$AU$4)+1), ROW(C2))), "")}
C29: =AA29 | Q29: =AC29 | AA29: {=IFERROR(INDEX('Finance Manager Input Sheet'!$AQ$4:$AQ$13, SMALL(IF('Finance Manager Input Sheet'!$BA$4:$BA$13="Customer Accepted", ROW('Finance Manager Input Sheet'!$AQ$4:$AQ$13)-ROW('Finance Manager Input Sheet'!$AQ$4)+1), ROW(A3))), "")} | AC29: {=IFERROR(INDEX('Finance Manager Input Sheet'!$AU$4:$AU$13, SMALL(IF('Finance Manager Input Sheet'!$BB$4:$BB$13="Customer Declined", ROW('Finance Manager Input Sheet'!$AU$4:$AU$13)-ROW('Finance Manager Input Sheet'!$AU$4)+1), ROW(C3))), "")}
C30: =AA30 | Q30: =AC30 | AA30: {=IFERROR(INDEX('Finance Manager Input Sheet'!$AQ$4:$AQ$13, SMALL(IF('Finance Manager Input Sheet'!$BA$4:$BA$13="Customer Accepted", ROW('Finance Manager Input Sheet'!$AQ$4:$AQ$13)-ROW('Finance Manager Input Sheet'!$AQ$4)+1), ROW(A4))), "")} | AC30: {=IFERROR(INDEX('Finance Manager Input Sheet'!$AU$4:$AU$13, SMALL(IF('Finance Manager Input Sheet'!$BB$4:$BB$13="Customer Declined", ROW('Finance Manager Input Sheet'!$AU$4:$AU$13)-ROW('Finance Manager Input Sheet'!$AU$4)+1), ROW(C4))), "")}
C31: =AA31 | Q31: =AC31 | AA31: {=IFERROR(INDEX('Finance Manager Input Sheet'!$AQ$4:$AQ$13, SMALL(IF('Finance Manager Input Sheet'!$BA$4:$BA$13="Customer Accepted", ROW('Finance Manager Input Sheet'!$AQ$4:$AQ$13)-ROW('Finance Manager Input Sheet'!$AQ$4)+1), ROW(A5))), "")} | AC31: {=IFERROR(INDEX('Finance Manager Input Sheet'!$AU$4:$AU$13, SMALL(IF('Finance Manager Input Sheet'!$BB$4:$BB$13="Customer Declined", ROW('Finance Manager Input Sheet'!$AU$4:$AU$13)-ROW('Finance Manager Input Sheet'!$AU$4)+1), ROW(C5))), "")}
C32: =AA32 | Q32: =AC32 | AA32: {=IFERROR(INDEX('Finance Manager Input Sheet'!$AQ$4:$AQ$13, SMALL(IF('Finance Manager Input Sheet'!$BA$4:$BA$13="Customer Accepted", ROW('Finance Manager Input Sheet'!$AQ$4:$AQ$13)-ROW('Finance Manager Input Sheet'!$AQ$4)+1), ROW(A6))), "")} | AC32: {=IFERROR(INDEX('Finance Manager Input Sheet'!$AU$4:$AU$13, SMALL(IF('Finance Manager Input Sheet'!$BB$4:$BB$13="Customer Declined", ROW('Finance Manager Input Sheet'!$AU$4:$AU$13)-ROW('Finance Manager Input Sheet'!$AU$4)+1), ROW(C6))), "")}
C33: =AA33 | Q33: =AC33 | AA33: {=IFERROR(INDEX('Finance Manager Input Sheet'!$AQ$4:$AQ$13, SMALL(IF('Finance Manager Input Sheet'!$BA$4:$BA$13="Customer Accepted", ROW('Finance Manager Input Sheet'!$AQ$4:$AQ$13)-ROW('Finance Manager Input Sheet'!$AQ$4)+1), ROW(A7))), "")} | AC33: {=IFERROR(INDEX('Finance Manager Input Sheet'!$AU$4:$AU$13, SMALL(IF('Finance Manager Input Sheet'!$BB$4:$BB$13="Customer Declined", ROW('Finance Manager Input Sheet'!$AU$4:$AU$13)-ROW('Finance Manager Input Sheet'!$AU$4)+1), ROW(C7))), "")}
C34: =AA34 | Q34: =AC34 | AA34: {=IFERROR(INDEX('Finance Manager Input Sheet'!$AQ$4:$AQ$13, SMALL(IF('Finance Manager Input Sheet'!$BA$4:$BA$13="Customer Accepted", ROW('Finance Manager Input Sheet'!$AQ$4:$AQ$13)-ROW('Finance Manager Input Sheet'!$AQ$4)+1), ROW(A8))), "")} | AC34: {=IFERROR(INDEX('Finance Manager Input Sheet'!$AU$4:$AU$13, SMALL(IF('Finance Manager Input Sheet'!$BB$4:$BB$13="Customer Declined", ROW('Finance Manager Input Sheet'!$AU$4:$AU$13)-ROW('Finance Manager Input Sheet'!$AU$4)+1), ROW(C8))), "")}
C35: =AA35 | Q35: =AC35 | AA35: {=IFERROR(INDEX('Finance Manager Input Sheet'!$AQ$4:$AQ$13, SMALL(IF('Finance Manager Input Sheet'!$BA$4:$BA$13="Customer Accepted", ROW('Finance Manager Input Sheet'!$AQ$4:$AQ$13)-ROW('Finance Manager Input Sheet'!$AQ$4)+1), ROW(A9))), "")} | AC35: {=IFERROR(INDEX('Finance Manager Input Sheet'!$AU$4:$AU$13, SMALL(IF('Finance Manager Input Sheet'!$BB$4:$BB$13="Customer Declined", ROW('Finance Manager Input Sheet'!$AU$4:$AU$13)-ROW('Finance Manager Input Sheet'!$AU$4)+1), ROW(C9))), "")}
C36: =AA36 | Q36: =AC36 | AA36: {=IFERROR(INDEX('Finance Manager Input Sheet'!$AQ$4:$AQ$13, SMALL(IF('Finance Manager Input Sheet'!$BA$4:$BA$13="Customer Accepted", ROW('Finance Manager Input Sheet'!$AQ$4:$AQ$13)-ROW('Finance Manager Input Sheet'!$AQ$4)+1), ROW(A10))), "")} | AC36: {=IFERROR(INDEX('Finance Manager Input Sheet'!$AU$4:$AU$13, SMALL(IF('Finance Manager Input Sheet'!$BB$4:$BB$13="Customer Declined", ROW('Finance Manager Input Sheet'!$AU$4:$AU$13)-ROW('Finance Manager Input Sheet'!$AU$4)+1), ROW(C10))), "")}
AA37: {=IFERROR(INDEX('Finance Manager Input Sheet'!$AQ$4:$AQ$13, SMALL(IF('Finance Manager Input Sheet'!$BA$4:$BA$13="Customer Accepted", ROW('Finance Manager Input Sheet'!$AQ$4:$AQ$13)-ROW('Finance Manager Input Sheet'!$AQ$4)+1), ROW(A11))), "")} | AC37: {=IFERROR(INDEX('Finance Manager Input Sheet'!$AU$4:$AU$13, SMALL(IF('Finance Manager Input Sheet'!$BB$4:$BB$13="Customer Declined", ROW('Finance Manager Input Sheet'!$AU$4:$AU$13)-ROW('Finance Manager Input Sheet'!$AU$4)+1), ROW(C11))), "")}
C38: =UPPER(_xlfn.CONCAT("PURCHASE PRICE FOR ",'Finance Manager Input Sheet'!AQ3," IS:")) -> PURCHASE PRICE FOR CUSTOMER ACCEPTED PROTECTION OPTIONS IS: | Q38: =Calculations!B722 | AC38: {=IFERROR(INDEX('Finance Manager Input Sheet'!$AQ$4:$AQ$13, SMALL(IF('Finance Manager Input Sheet'!$BA$4:$BA$13="Customer Accepted", ROW('Finance Manager Input Sheet'!$AQ$4:$AQ$13)-ROW('Finance Manager Input Sheet'!$AQ$4)+1), ROW(C12))), "")}
C39: Price | D39: ='Finance Manager Input Sheet'!AR14 -> 0 | Q39: CUSTOMER HAS DECLINED THE ABOVE PROTECTION OPTIONS | AC39: {=IFERROR(INDEX('Finance Manager Input Sheet'!$AQ$4:$AQ$13, SMALL(IF('Finance Manager Input Sheet'!$BA$4:$BA$13="Customer Declined", ROW('Finance Manager Input Sheet'!$AQ$4:$AQ$13)-ROW('Finance Manager Input Sheet'!$AQ$4)+1), ROW(C13))), "")}
C40: Tax | D40: =+D41-D39 -> 0 | Q40: ='Customer Input Screen'!C32 -> [Customer Signature]
C41: Total Package Price | D41: ='Finance Manager Input Sheet'!AS14 -> 0 | Q41: Customer
B45: We make available to all of our customers optional products and plans that provide additional protection in connection with the purchase and/or financing of your equipment. Each of these optional products is described in detail in separate contracts and all forms and contracts are available for your review prior to purchase. You are not required to buy any of the products in order to obtain financing. The "Accepted Protection" column means that you have purchased these protection options. (If you accepted a protection package, each individual product is itemized.) The "Declined Protection" column means that you have chosen not to purchase any of the declined products or packages, and you will not be eligible for the benefits associated with the declined products/packages. If you accept, you may choose to pay cash for the plan or it can be financed through your Promissory Note/Security Agreement (PNSA), lease or retail installment contract with the approval of the financial institution. The dealership is compensated for providing financial products and services. I understand that this Menu tool is not a legal contract and that these payments are estimates. Complete terms and conditions of each optional products is detailed in the agreements itself.
B49: =Calculations!B614 -> For presentation purposes and submitting for approval of financing, payments are based upon a month term at an annual interest rate of 0.00%. Actual term and rates may vary based upon financing available based upon customers credit and other factors.
B51: ='Customer Input Screen'!C32 -> [Customer Signature]
B52: Customer | U52: Prepared by | V52: ='Finance Manager Input Sheet'!G2 -> 0
U53: %(Invoice Date)%

Sheet Delayed Payment Agmt
B1: CAIRO, GA | CHIEFLAND,FL. | DELAND, FL. | L1: CRYSTAL | R1: =+Calculations!$B$568
B3: HASTINGS, FL | HOMOSASSA, FL | JACKSONVILLE, FL | LECANTO, FL | R3: =+Calculations!$B$569
B5: LEESBURG, FL. | LIVE OAK, FL. | MADISON, FL | L5: TRACTOR & EQUIPMENT | R5: =Calculations!B570
B7: MIAMI, FL. | PALATKA, FL. | PANAMA CITY, FL | OCALA, FL
B9: SPRING HILL, FL. | STARKE, FL. | TALLAHASSEE, FL | L9: =+Calculations!B572 -> CRYSTALTRACTOR.COM | R9: =Calculations!B571
C11: Quote Number | D11: =+'Sales Input Sheet'!$C$11 -> 0 | S11: Sales Person | V11: =IF('Sales Input Sheet'!C15<>"",UPPER('Sales Input Sheet'!C15),"")
C12: =+Calculations!$B$597 | S12: INVOICE DATE | V12: ='Costing Sheet'!C11 -> 0
C13: =+Calculations!B598
B15: DELAYED PAYMENT AGREEMENT
B17: TRANSACTION SUMMARY
B18: SELLING PRICE, NET OF DISCOUNTS | M18: =+Calculations!B312 -> 0 | Q18: Accepted Products | X18: =+Calculations!B321+Calculations!B421 -> 0
B19: Net Trade Value | M19: =-Calculations!B315+Calculations!B316 -> 0 | Q19: Sales Tax | X19: =+Calculations!$B$405+Calculations!$B$412+Calculations!$B$413+Calculations!$B$407 -> 0
B20: Dealer Based Fees for Documents, Freight and Prep | M20: =+Calculations!B302+'Costing Sheet'!Q3+'Costing Sheet'!Q5 -> 0 | Q20: MANUFACTURER REBATE | X20: =-Calculations!B318 -> 0
B21: Governmental Fees | M21: =+Calculations!B386+Calculations!B385+Calculations!B439+'Costing Sheet'!Q13+'Costing Sheet'!Q15 -> 0 | Q21: TOTAL DUE FROM CUSTOMER, plus Kubota Insurance, if applicable, as shown below | X21: =+Calculations!B436 -> 0
B23: DATE PAYMENT IS DUE IN FULL | E23: =+'Finance Manager Input Sheet'!P19 -> 0
B25: CUSTOMER ACKNOWLEDGES THAT IT HAS AGREED TO PAY THE TOTAL DUE FROM CUSTOMER ON OR BEFORE THE DATE PAYMENT IS DUE IN FULL AND THAT CRYSTAL TRACTOR AND AFFILIATES RETAIN A FIRST LIEN AND SECURITY INTEREST IN ALL EQUIPMENT DELIVERED HEREUNDER UNITL PAYMENT IN FULL IS RECEIEVD BY THE SELLER.
B27: ='Customer Input Screen'!C32 -> [Customer Signature]
B28: Customer

Sheet Recap
B1: =+B$149 -> RECAP | D1: =+D$149 | J1: LOAN NUMBER | N1: =+'Finance Manager Input Sheet'!C$28 -> 0
B2: =+B$150 -> Invoice Number | D2: =+D$150 -> 0 | J2: QUOTE NUMBER | N2: ='Sales Input Sheet'!C$11 -> 0
B3: =+B$154 -> Customer Name | D3: =+D$154 | J3: INVOICE DATE | N3: ='Costing Sheet'!C$11 -> 0
B4: Stock Number | D4: Net Selling Price | F4: COST AT TIME OF TRANSACTION | N4: Total Cost | P4: Front Margin | R4: 2 Cycle Margin
B6: =+'Sales Input Sheet'!A19 -> 0 | D6: =+Calculations!B526 -> 0 | E6: =IF('Sales Input Sheet'!W19="N","NEW",IF('Sales Input Sheet'!W19="U","USED","")) | F6: =Calculations!B11 -> 0 | H6: Incentive | J6: =-'Costing Sheet'!Q22 -> 0 | L6: =+UPPER(_xlfn.CONCAT('Costing Sheet'!U22," ",'Costing Sheet'!AS22))
B7: =+Calculations!B8 | H7: We Owe | J7: =+'Costing Sheet'!AI22 -> 0 | L7: =UPPER(_xlfn.CONCAT('Costing Sheet'!AK22," ",'Costing Sheet'!AM22)) | N7: Acct Adj | P7: =+'Costing Sheet'!AO22 -> 0 | R7: =_xlfn.CONCAT(+'Costing Sheet'!AQ22," ",AW22)
H8: Cost Adj. | J8: ='Costing Sheet'!AE22 -> 0 | L8: =UPPER('Costing Sheet'!AG22) | N8: =+Calculations!B573 -> 0 | P8: =IF('Sales Input Sheet'!$U19="2CYCLE",0,+Calculations!$B14) -> 0 | R8: =IF('Sales Input Sheet'!$U19="2CYCLE",+Calculations!$B14,0) -> 0
B10: =+'Sales Input Sheet'!A20 -> 0 | D10: =+Calculations!B527 -> 0 | E10: =IF('Sales Input Sheet'!W20="N","NEW",IF('Sales Input Sheet'!W20="U","USED","")) | F10: =Calculations!B23 -> 0 | H10: Incentive | J10: =-'Costing Sheet'!Q23 -> 0 | L10: =+UPPER(_xlfn.CONCAT('Costing Sheet'!U23," ",'Costing Sheet'!AS23))
B11: =+Calculations!B20 | H11: We Owe | J11: =+'Costing Sheet'!AI23 -> 0 | L11: =Calculations!B629 | N11: Acct Adj | P11: =+'Costing Sheet'!AO23 -> 0 | R11: =_xlfn.CONCAT(+'Costing Sheet'!AQ23," ",AW23)
H12: Cost Adj. | J12: ='Costing Sheet'!AE23 -> 0 | L12: =UPPER('Costing Sheet'!AG23) | N12: =+Calculations!B574 -> 0 | P12: =IF('Sales Input Sheet'!$U20="2CYCLE",0,+Calculations!$B26) -> 0 | R12: =IF('Sales Input Sheet'!$U20="2CYCLE",+Calculations!$B26,0) -> 0
B14: =+'Sales Input Sheet'!A21 -> 0 | D14: =+Calculations!B528 -> 0 | E14: =IF('Sales Input Sheet'!W21="N","NEW",IF('Sales Input Sheet'!W21="U","USED","")) | F14: =Calculations!B35 -> 0 | H14: Incentive | J14: =-'Costing Sheet'!Q24 -> 0 | L14: =+UPPER(_xlfn.CONCAT('Costing Sheet'!U24," ",'Costing Sheet'!AS24))
B15: =+Calculations!B32 | H15: We Owe | J15: =+'Costing Sheet'!AI24 -> 0 | L15: =Calculations!B630 | N15: Acct Adj | P15: =+'Costing Sheet'!AO24 -> 0 | R15: =_xlfn.CONCAT(+'Costing Sheet'!AQ24," ",AW24)
H16: Cost Adj. | J16: ='Costing Sheet'!AE24 -> 0 | L16: =UPPER('Costing Sheet'!AG24) | N16: =+Calculations!B575 -> 0 | P16: =IF('Sales Input Sheet'!$U21="2CYCLE",0,+Calculations!$B38) -> 0 | R16: =IF('Sales Input Sheet'!$U21="2CYCLE",+Calculations!$B38,0) -> 0
B18: =+'Sales Input Sheet'!A22 -> 0 | D18: =+Calculations!B529 -> 0 | E18: =IF('Sales Input Sheet'!W22="N","NEW",IF('Sales Input Sheet'!W22="U","USED","")) | F18: =Calculations!B47 -> 0 | H18: Incentive | J18: =-'Costing Sheet'!Q25 -> 0 | L18: =+UPPER(_xlfn.CONCAT('Costing Sheet'!U25," ",'Costing Sheet'!AS25))
B19: =+Calculations!B44 | H19: We Owe | J19: =+'Costing Sheet'!AI25 -> 0 | L19: =Calculations!B631 | N19: Acct Adj | P19: =+'Costing Sheet'!AO25 -> 0 | R19: =_xlfn.CONCAT(+'Costing Sheet'!AQ25," ",AW25)
H20: Cost Adj. | J20: ='Costing Sheet'!AE25 -> 0 | L20: =UPPER('Costing Sheet'!AG25) | N20: =+Calculations!B576 -> 0 | P20: =IF('Sales Input Sheet'!$U22="2CYCLE",0,+Calculations!$B50) -> 0 | R20: =IF('Sales Input Sheet'!$U22="2CYCLE",+Calculations!$B50,0) -> 0
B22: =+'Sales Input Sheet'!A23 -> 0 | D22: =+Calculations!B530 -> 0 | E22: =IF('Sales Input Sheet'!W23="N","NEW",IF('Sales Input Sheet'!W23="U","USED","")) | F22: =Calculations!B59 -> 0 | H22: Incentive | J22: =-'Costing Sheet'!Q26 -> 0 | L22: =+UPPER(_xlfn.CONCAT('Costing Sheet'!U26," ",'Costing Sheet'!AS26))
B23: =+Calculations!B56 | H23: We Owe | J23: =+'Costing Sheet'!AI26 -> 0 | L23: =Calculations!B632 | N23: Acct Adj | P23: =+'Costing Sheet'!AO26 -> 0 | R23: =_xlfn.CONCAT(+'Costing Sheet'!AQ26," ",AW26)
H24: Cost Adj. | J24: ='Costing Sheet'!AE26 -> 0 | L24: =UPPER('Costing Sheet'!AG26) | N24: =+Calculations!B577 -> 0 | P24: =IF('Sales Input Sheet'!$U23="2CYCLE",0,+Calculations!$B62) -> 0 | R24: =IF('Sales Input Sheet'!$U23="2CYCLE",+Calculations!$B62,0) -> 0
B26: =+'Sales Input Sheet'!A24 -> 0 | D26: =+Calculations!B531 -> 0 | E26: =IF('Sales Input Sheet'!W24="N","NEW",IF('Sales Input Sheet'!W24="U","USED","")) | F26: =Calculations!B71 -> 0 | H26: Incentive | J26: =-'Costing Sheet'!Q27 -> 0 | L26: =+UPPER(_xlfn.CONCAT('Costing Sheet'!U27," ",'Costing Sheet'!AS27))
B27: =+Calculations!B68 | H27: We Owe | J27: =+'Costing Sheet'!AI27 -> 0 | L27: =Calculations!B633 | N27: Acct Adj | P27: =+'Costing Sheet'!AO27 -> 0 | R27: =_xlfn.CONCAT(+'Costing Sheet'!AQ27," ",AW27)
H28: Cost Adj. | J28: ='Costing Sheet'!AE27 -> 0 | L28: =UPPER('Costing Sheet'!AG27) | N28: =+Calculations!B578 -> 0 | P28: =IF('Sales Input Sheet'!$U24="2CYCLE",0,+Calculations!$B74) -> 0 | R28: =IF('Sales Input Sheet'!$U24="2CYCLE",+Calculations!$B74,0) -> 0
B30: =+'Sales Input Sheet'!A25 -> 0 | D30: =+Calculations!B532 -> 0 | E30: =IF('Sales Input Sheet'!W25="N","NEW",IF('Sales Input Sheet'!W25="U","USED","")) | F30: =Calculations!B83 -> 0 | H30: Incentive | J30: =-'Costing Sheet'!Q28 -> 0 | L30: =+UPPER(_xlfn.CONCAT('Costing Sheet'!U28," ",'Costing Sheet'!AS28))
B31: =+Calculations!B80 | H31: We Owe | J31: =+'Costing Sheet'!AI28 -> 0 | L31: =Calculations!B634 | N31: Acct Adj | P31: =+'Costing Sheet'!AO28 -> 0 | R31: =_xlfn.CONCAT(+'Costing Sheet'!AQ28," ",AW28)
H32: Cost Adj. | J32: ='Costing Sheet'!AE28 -> 0 | L32: =UPPER('Costing Sheet'!AG28) | N32: =+Calculations!B579 -> 0 | P32: =IF('Sales Input Sheet'!$U25="2CYCLE",0,+Calculations!$B86) -> 0 | R32: =IF('Sales Input Sheet'!$U25="2CYCLE",+Calculations!$B86,0) -> 0
B34: =+'Sales Input Sheet'!A26 -> 0 | D34: =+Calculations!B533 -> 0 | E34: =IF('Sales Input Sheet'!W26="N","NEW",IF('Sales Input Sheet'!W26="U","USED","")) | F34: =Calculations!B95 -> 0 | H34: Incentive | J34: =-'Costing Sheet'!Q29 -> 0 | L34: =+UPPER(_xlfn.CONCAT('Costing Sheet'!U29," ",'Costing Sheet'!AS29))
B35: =+Calculations!B92 | H35: We Owe | J35: =+'Costing Sheet'!AI29 -> 0 | L35: =Calculations!B635 | N35: Acct Adj | P35: =+'Costing Sheet'!AO29 -> 0 | R35: =_xlfn.CONCAT(+'Costing Sheet'!AQ29," ",AW29)
H36: Cost Adj. | J36: ='Costing Sheet'!AE29 -> 0 | L36: =UPPER('Costing Sheet'!AG29) | N36: =+Calculations!B580 -> 0 | P36: =IF('Sales Input Sheet'!$U26="2CYCLE",0,+Calculations!$B98) -> 0 | R36: =IF('Sales Input Sheet'!$U26="2CYCLE",+Calculations!$B98,0) -> 0
B38: =+'Sales Input Sheet'!A27 -> 0 | D38: =+Calculations!B534 -> 0 | E38: =IF('Sales Input Sheet'!W27="N","NEW",IF('Sales Input Sheet'!W27="U","USED","")) | F38: =Calculations!B107 -> 0 | H38: Incentive | J38: =-'Costing Sheet'!Q30 -> 0 | L38: =+UPPER(_xlfn.CONCAT('Costing Sheet'!U30," ",'Costing Sheet'!AS30))
B39: =+Calculations!B104 | H39: We Owe | J39: =+'Costing Sheet'!AI30 -> 0 | L39: =Calculations!B636 | N39: Acct Adj | P39: =+'Costing Sheet'!AO30 -> 0 | R39: =_xlfn.CONCAT(+'Costing Sheet'!AQ30," ",AW30)
H40: Cost Adj. | J40: ='Costing Sheet'!AE30 -> 0 | L40: =UPPER('Costing Sheet'!AG30) | N40: =+Calculations!B581 -> 0 | P40: =IF('Sales Input Sheet'!$U27="2CYCLE",0,+Calculations!$B110) -> 0 | R40: =IF('Sales Input Sheet'!$U27="2CYCLE",+Calculations!$B110,0) -> 0
B42: =+'Sales Input Sheet'!A28 -> 0 | D42: =+Calculations!B535 -> 0 | E42: =IF('Sales Input Sheet'!W28="N","NEW",IF('Sales Input Sheet'!W28="U","USED","")) | F42: =Calculations!B119 -> 0 | H42: Incentive | J42: =-'Costing Sheet'!Q31 -> 0 | L42: =+UPPER(_xlfn.CONCAT('Costing Sheet'!U31," ",'Costing Sheet'!AS31))
B43: =+Calculations!B116 | H43: We Owe | J43: =+'Costing Sheet'!AI31 -> 0 | L43: =Calculations!B637 | N43: Acct Adj | P43: =+'Costing Sheet'!AO31 -> 0 | R43: =_xlfn.CONCAT(+'Costing Sheet'!AQ31," ",AW31)
H44: Cost Adj. | J44: ='Costing Sheet'!AE31 -> 0 | L44: =UPPER('Costing Sheet'!AG31) | N44: =+Calculations!B582 -> 0 | P44: =IF('Sales Input Sheet'!$U28="2CYCLE",0,+Calculations!$B122) -> 0 | R44: =IF('Sales Input Sheet'!$U28="2CYCLE",+Calculations!$B122,0) -> 0
B46: =+B$149 -> RECAP | D46: =+D$149 | J46: LOAN NUMBER | N46: =+'Finance Manager Input Sheet'!C$28 -> 0
B47: =+B$150 -> Invoice Number | D47: =+D$150 -> 0 | J47: QUOTE NUMBER | N47: ='Sales Input Sheet'!C$11 -> 0
B48: =+B$154 -> Customer Name | D48: =+D$154 | J48: INVOICE DATE | N48: ='Costing Sheet'!C$11 -> 0
B50: Not in Stock Items
B52: Serial Number | D52: Net Selling Price | F52: COST AT TIME OF TRANSACTION | N52: Total Cost | P52: Front Margin | R52: 2 Cycle Margin
B53: ='Sales Input Sheet'!G31 -> 0 | D53: =+Calculations!B536 -> 0 | F53: =+'Costing Sheet'!O34 -> 0 | H53: Incentive | J53: =-'Costing Sheet'!Q34 -> 0 | L53: =UPPER(_xlfn.CONCAT('Costing Sheet'!U34," ",'Costing Sheet'!AS34)) | N53: =+Calculations!B583 -> 0 | P53: =Calculations!B126 -> 0
H54: Acctg Cost Adj | J54: =+'Costing Sheet'!AE34 -> 0 | L54: =_xlfn.CONCAT(+'Costing Sheet'!AG34," ",AW34)
B55: ='Sales Input Sheet'!G32 -> 0 | D55: =+Calculations!B537 -> 0 | F55: =+'Costing Sheet'!O35 -> 0 | H55: Incentive | J55: =-'Costing Sheet'!Q35 -> 0 | L55: =UPPER(_xlfn.CONCAT('Costing Sheet'!U35," ",'Costing Sheet'!AS35)) | N55: =+Calculations!B584 -> 0 | P55: =Calculations!B130 -> 0
H56: Acctg Cost Adj | J56: =+'Costing Sheet'!AE35 -> 0 | L56: =_xlfn.CONCAT(+'Costing Sheet'!AG35," ",AW35)
B57: ='Sales Input Sheet'!G33 -> 0 | D57: =+Calculations!B538 -> 0 | F57: =+'Costing Sheet'!O36 -> 0 | H57: Incentive | J57: =-'Costing Sheet'!Q36 -> 0 | L57: =UPPER(_xlfn.CONCAT('Costing Sheet'!U36," ",'Costing Sheet'!AS36)) | N57: =+Calculations!B585 -> 0 | P57: =Calculations!B134 -> 0
H58: Acctg Cost Adj | J58: =+'Costing Sheet'!AE36 -> 0 | L58: =_xlfn.CONCAT(+'Costing Sheet'!AG36," ",AW36)
B59: ='Sales Input Sheet'!G34 -> 0 | D59: =+Calculations!B539 -> 0 | F59: =+'Costing Sheet'!O37 -> 0 | H59: Incentive | J59: =-'Costing Sheet'!Q37 -> 0 | L59: =UPPER(_xlfn.CONCAT('Costing Sheet'!U37," ",'Costing Sheet'!AS37)) | N59: =+Calculations!B586 -> 0 | P59: =Calculations!B138 -> 0
H60: Acctg Cost Adj | J60: =+'Costing Sheet'!AE37 -> 0 | L60: =_xlfn.CONCAT(+'Costing Sheet'!AG37," ",AW37)
B61: ='Sales Input Sheet'!G35 -> 0 | D61: =+Calculations!B540 -> 0 | F61: =+'Costing Sheet'!O38 -> 0 | H61: Incentive | J61: =-'Costing Sheet'!Q38 -> 0 | L61: =UPPER(_xlfn.CONCAT('Costing Sheet'!U38," ",'Costing Sheet'!AS38)) | N61: =+Calculations!B587 -> 0 | P61: =Calculations!B142 -> 0
H62: Acctg Cost Adj | J62: =+'Costing Sheet'!AE38 -> 0 | L62: =_xlfn.CONCAT(+'Costing Sheet'!AG38," ",AW38)
B64: Non Serialized Items
B65: Part Number | D65: Quantity | F65: Net Price Per Item | J65: Per Item Cost | L65: Net Extended Selling Price | N65: Total Extended Cost | P65: Front Margin | R65: 2 Cycle Margin
B66: =+'Sales Input Sheet'!I38 -> 0 | D66: =+'Sales Input Sheet'!A38 -> 0 | F66: =+'Costing Sheet'!I42-'Costing Sheet'!K42 -> 0 | J66: =+'Costing Sheet'!O42 -> 0 | L66: =+Calculations!B541 -> 0 | N66: =+Calculations!B588 -> 0 | P66: =Calculations!B146 -> 0
B67: =+'Sales Input Sheet'!I39 -> 0 | D67: =+'Sales Input Sheet'!A39 -> 0 | F67: =+'Costing Sheet'!I43-'Costing Sheet'!K43 -> 0 | J67: =+'Costing Sheet'!O43 -> 0 | L67: =+Calculations!B542 -> 0 | N67: =+Calculations!B589 -> 0 | P67: =Calculations!B154 -> 0
B68: =+'Sales Input Sheet'!I40 -> 0 | D68: =+'Sales Input Sheet'!A40 -> 0 | F68: =+'Costing Sheet'!I44-'Costing Sheet'!K44 -> 0 | J68: =+'Costing Sheet'!O44 -> 0 | L68: =+Calculations!B543 -> 0 | N68: =+Calculations!B590 -> 0 | P68: =Calculations!B162 -> 0
B69: =+'Sales Input Sheet'!I41 -> 0 | D69: =+'Sales Input Sheet'!A41 -> 0 | F69: =+'Costing Sheet'!I45-'Costing Sheet'!K45 -> 0 | J69: =+'Costing Sheet'!O45 -> 0 | L69: =+Calculations!B544 -> 0 | N69: =+Calculations!B591 -> 0 | P69: =Calculations!B170 -> 0
B70: =+'Sales Input Sheet'!I42 -> 0 | D70: =+'Sales Input Sheet'!A42 -> 0 | F70: =+'Costing Sheet'!I46-'Costing Sheet'!K46 -> 0 | J70: =+'Costing Sheet'!O46 -> 0 | L70: =+Calculations!B545 -> 0 | N70: =+Calculations!B592 -> 0 | P70: =Calculations!B178 -> 0
B72: =+B$149 -> RECAP | D72: =+D$149 | J72: LOAN NUMBER | N72: =+'Finance Manager Input Sheet'!C$28 -> 0
B73: =+B$150 -> Invoice Number | D73: =+D$150 -> 0 | J73: QUOTE NUMBER | N73: ='Sales Input Sheet'!C$11 -> 0
B74: =+B$154 -> Customer Name | D74: =+D$154 | J74: INVOICE DATE | N74: ='Costing Sheet'!C$11 -> 0
B75: Trade In
B76: Serial Number | D76: Trade Allowance | F76: Trade ACV Value | J76: Disposition Plan | P76: Margin
B77: =+'Sales Input Sheet'!G45 -> 0 | D77: ='Costing Sheet'!I49 -> 0 | F77: =+'Costing Sheet'!O49 -> 0 | J77: =UPPER('Costing Sheet'!U49) | L77: ='Costing Sheet'!AA49 -> 0 | P77: =+Calculations!B185 -> 0
B78: =+'Sales Input Sheet'!G46 -> 0 | D78: ='Costing Sheet'!I50 -> 0 | F78: =+'Costing Sheet'!O50 -> 0 | J78: =UPPER('Costing Sheet'!U50) | L78: ='Costing Sheet'!AA50 -> 0 | P78: =+Calculations!B186 -> 0
B79: =+'Sales Input Sheet'!G47 -> 0 | D79: ='Costing Sheet'!I51 -> 0 | F79: =+'Costing Sheet'!O51 -> 0 | J79: =UPPER('Costing Sheet'!U51) | L79: ='Costing Sheet'!AA51 -> 0 | P79: =+Calculations!B666 -> 0
B80: =+'Sales Input Sheet'!G48 -> 0 | D80: ='Costing Sheet'!I52 -> 0 | F80: =+'Costing Sheet'!O52 -> 0 | J80: =UPPER('Costing Sheet'!U52) | L80: ='Costing Sheet'!AA52 -> 0 | P80: =+Calculations!B669 -> 0
B81: =+'Sales Input Sheet'!G49 -> 0 | D81: ='Costing Sheet'!I53 -> 0 | F81: =+'Costing Sheet'!O53 -> 0 | J81: =UPPER('Costing Sheet'!U53) | L81: ='Costing Sheet'!AA53 -> 0 | P81: =+Calculations!B672 -> 0
B82: =+'Sales Input Sheet'!G50 -> 0 | D82: ='Costing Sheet'!I54 -> 0 | F82: =+'Costing Sheet'!O54 -> 0 | J82: =UPPER('Costing Sheet'!U54) | L82: ='Costing Sheet'!AA54 -> 0 | P82: =+Calculations!B675 -> 0
B83: TRADE 1 PAYOFF | D83: =_xlfn.CONCAT("SERIAL # -",'Sales Input Sheet'!G45) -> SERIAL # - | F83: ='Sales Input Sheet'!K45 -> 0 | J83: ='Sales Input Sheet'!M45 -> 0 | L83: =UPPER('Sales Input Sheet'!I45)
B84: TRADE 2 PAYOFF | D84: =_xlfn.CONCAT("SERIAL # -",'Sales Input Sheet'!G46) -> SERIAL # - | F84: ='Sales Input Sheet'!K46 -> 0 | J84: ='Sales Input Sheet'!M46 -> 0 | L84: =UPPER('Sales Input Sheet'!I46)
B85: TRADE 3 PAYOFF | D85: =_xlfn.CONCAT("SERIAL # -",'Sales Input Sheet'!G47) -> SERIAL # - | F85: ='Sales Input Sheet'!K47 -> 0 | J85: ='Sales Input Sheet'!M47 -> 0 | L85: =UPPER('Sales Input Sheet'!I47)
B86: TRADE 4 PAYOFF | D86: =_xlfn.CONCAT("SERIAL # -",'Sales Input Sheet'!G48) -> SERIAL # - | F86: ='Sales Input Sheet'!K48 -> 0 | J86: ='Sales Input Sheet'!M48 -> 0 | L86: =UPPER('Sales Input Sheet'!I48)
B87: TRADE 5 PAYOFF | D87: =_xlfn.CONCAT("SERIAL # -",'Sales Input Sheet'!G49) -> SERIAL # - | F87: ='Sales Input Sheet'!K49 -> 0 | J87: ='Sales Input Sheet'!M49 -> 0 | L87: =UPPER('Sales Input Sheet'!I49)
B88: TRADE 6 PAYOFF | D88: =_xlfn.CONCAT("SERIAL # -",'Sales Input Sheet'!G50) -> SERIAL # - | F88: ='Sales Input Sheet'!K50 -> 0 | J88: ='Sales Input Sheet'!M50 -> 0 | L88: =UPPER('Sales Input Sheet'!I50)
B89: ADDITIONAL WE OWE
B90: Stock Number | F90: Cost to Fill We Owe | J90: We Owe Desctiption | P90: Margin
B91: =+'Costing Sheet'!K57 -> 0 | D91: We Owe | F91: =+'Costing Sheet'!O57 -> 0 | J91: =UPPER(Calculations!B196) | P91: =+Calculations!B191 -> 0
B92: =+'Costing Sheet'!K58 -> 0 | D92: We Owe | F92: =+'Costing Sheet'!O58 -> 0 | J92: =UPPER(Calculations!B197) | P92: =+Calculations!B192 -> 0
B93: =+'Costing Sheet'!K59 -> 0 | D93: We Owe | F93: =+'Costing Sheet'!O59 -> 0 | J93: =UPPER(Calculations!B198) | P93: =+Calculations!B193 -> 0
B94: =+'Costing Sheet'!K60 -> 0 | D94: We Owe | F94: =+'Costing Sheet'!O60 -> 0 | J94: =UPPER(Calculations!B199) | P94: =+Calculations!B194 -> 0
B95: =+'Costing Sheet'!K61 -> 0 | D95: We Owe | F95: =+'Costing Sheet'!O61 -> 0 | J95: =UPPER(Calculations!B200) | N95: =+Calculations!B195 -> 0 | P95: =+Calculations!B195 -> 0
P96: Front End Margin | R96: 2 Cycle Margin
B97: Extended Selling Price | D97: =Calculations!B312 -> 0 | L97: TOTAL COST | N97: =+Calculations!B595 -> 0 | P97: =Calculations!$B201-SUM(R53:R76)-R8-R12-R16-R20-R24-R28-R32-R36-R40-R44 -> 0 | R97: =Calculations!$B201-P97 -> 0
B99: =+B$149 -> RECAP | D99: =+D$149 | J99: LOAN NUMBER | N99: =+'Finance Manager Input Sheet'!C$28 -> 0
B100: =+B$150 -> Invoice Number | D100: =+D$150 -> 0 | J100: QUOTE NUMBER | N100: ='Sales Input Sheet'!C$11 -> 0
B101: =+B$154 -> Customer Name | D101: =+D$154 | J101: INVOICE DATE | N101: ='Costing Sheet'!C$11 -> 0
B103: Protection Plan | F103: Provider | J103: Selling Price | L103: Cost | P103: Margin
B104: =IF('Finance Manager Input Sheet'!$N4="customer accepted",'Finance Manager Input Sheet'!C4,"") | F104: =IF('Finance Manager Input Sheet'!$N4="customer accepted",UPPER('Finance Manager Input Sheet'!G4),"") | J104: =IF('Finance Manager Input Sheet'!$N4="customer accepted",'Finance Manager Input Sheet'!I4,"") | L104: =IF('Finance Manager Input Sheet'!$N4="customer accepted",'Finance Manager Input Sheet'!K4,"") | P104: =Calculations!B516 -> 0
B105: =IF('Finance Manager Input Sheet'!$N5="customer accepted",'Finance Manager Input Sheet'!C5,"") | F105: =IF('Finance Manager Input Sheet'!$N5="customer accepted",UPPER('Finance Manager Input Sheet'!G5),"") | J105: =IF('Finance Manager Input Sheet'!$N5="customer accepted",'Finance Manager Input Sheet'!I5,"") | L105: =IF('Finance Manager Input Sheet'!$N5="customer accepted",'Finance Manager Input Sheet'!K5,"") | P105: =Calculations!B517 -> 0
B106: =IF('Finance Manager Input Sheet'!$N6="customer accepted",'Finance Manager Input Sheet'!C6,"") | F106: =IF('Finance Manager Input Sheet'!$N6="customer accepted",UPPER('Finance Manager Input Sheet'!G6),"") | J106: =IF('Finance Manager Input Sheet'!$N6="customer accepted",'Finance Manager Input Sheet'!I6,"") | L106: =IF('Finance Manager Input Sheet'!$N6="customer accepted",'Finance Manager Input Sheet'!K6,"") | P106: =Calculations!B518 -> 0
B107: =IF('Finance Manager Input Sheet'!$N7="customer accepted",'Finance Manager Input Sheet'!C7,"") | F107: =IF('Finance Manager Input Sheet'!$N7="customer accepted",UPPER('Finance Manager Input Sheet'!G7),"") | J107: =IF('Finance Manager Input Sheet'!$N7="customer accepted",'Finance Manager Input Sheet'!I7,"") | L107: =IF('Finance Manager Input Sheet'!$N7="customer accepted",'Finance Manager Input Sheet'!K7,"") | P107: =Calculations!B519 -> 0
B108: =IF('Finance Manager Input Sheet'!$N8="customer accepted",'Finance Manager Input Sheet'!C8,"") | F108: =IF('Finance Manager Input Sheet'!$N8="customer accepted",UPPER('Finance Manager Input Sheet'!G8),"") | J108: =IF('Finance Manager Input Sheet'!$N8="customer accepted",'Finance Manager Input Sheet'!I8,"") | L108: =IF('Finance Manager Input Sheet'!$N8="customer accepted",'Finance Manager Input Sheet'!K8,"") | P108: =Calculations!B520 -> 0
B109: =IF('Finance Manager Input Sheet'!$N9="customer accepted",'Finance Manager Input Sheet'!C9,"") | F109: =IF('Finance Manager Input Sheet'!$N9="customer accepted",UPPER('Finance Manager Input Sheet'!G9),"") | I109: =+Calculations!$B$405 -> 0 | J109: =IF('Finance Manager Input Sheet'!$N9="customer accepted",'Finance Manager Input Sheet'!I9,"") | L109: =IF('Finance Manager Input Sheet'!$N9="customer accepted",'Finance Manager Input Sheet'!K9,"") | P109: =Calculations!B521 -> 0
B110: =IF('Finance Manager Input Sheet'!$N10="customer accepted",'Finance Manager Input Sheet'!C10,"") | F110: =IF('Finance Manager Input Sheet'!$N10="customer accepted",UPPER('Finance Manager Input Sheet'!G10),"") | I110: =+Calculations!$B$412 -> 0 | J110: =IF('Finance Manager Input Sheet'!$N10="customer accepted",'Finance Manager Input Sheet'!I10,"") | L110: =IF('Finance Manager Input Sheet'!$N10="customer accepted",'Finance Manager Input Sheet'!K10,"") | P110: =Calculations!B522 -> 0
B111: =IF('Finance Manager Input Sheet'!$N11="customer accepted",'Finance Manager Input Sheet'!C11,"") | F111: =IF('Finance Manager Input Sheet'!$N11="customer accepted",UPPER('Finance Manager Input Sheet'!G11),"") | I111: =+Calculations!$B$413 -> 0 | J111: =IF('Finance Manager Input Sheet'!$N11="customer accepted",'Finance Manager Input Sheet'!I11,"") | L111: =IF('Finance Manager Input Sheet'!$N11="customer accepted",'Finance Manager Input Sheet'!K11,"") | P111: =Calculations!B523 -> 0
B112: =IF('Finance Manager Input Sheet'!$N12="customer accepted",'Finance Manager Input Sheet'!C12,"") | F112: =IF('Finance Manager Input Sheet'!$N12="customer accepted",UPPER('Finance Manager Input Sheet'!G12),"") | I112: =+Calculations!$B$407 -> 0 | J112: =IF('Finance Manager Input Sheet'!$N12="customer accepted",'Finance Manager Input Sheet'!I12,"") | L112: =IF('Finance Manager Input Sheet'!$N12="customer accepted",'Finance Manager Input Sheet'!K12,"") | P112: =Calculations!B524 -> 0
B113: =IF('Finance Manager Input Sheet'!$N13="customer accepted",'Finance Manager Input Sheet'!C13,"") | F113: =IF('Finance Manager Input Sheet'!$N13="customer accepted",UPPER('Finance Manager Input Sheet'!G13),"") | J113: =IF('Finance Manager Input Sheet'!$N13="customer accepted",'Finance Manager Input Sheet'!I13,"") | L113: =IF('Finance Manager Input Sheet'!$N13="customer accepted",'Finance Manager Input Sheet'!K13,"") | P113: =Calculations!B525 -> 0
B115: =+Calculations!B417 | J115: =+Calculations!B421 -> 0 | L115: =+Calculations!B654 -> 0 | P115: =+Calculations!B655 -> 0
B118: Buy Down Cost
B119: Rate Split | P119: =-'Finance Manager Input Sheet'!C26 -> 0
B120: Flat Fee From Bank | P120: =+'Finance Manager Input Sheet'!P22 -> 0
...

Sheet Extra Cells Not used
A1: Cost Adjustment | C1: Cost Adjustment Description
E2: Serialized 1
E3: Serialized 2
E4: Serialized 3
E5: Serialized 4
E6: Serialized 5
E7: Serialized 6
E8: Serialized 7
E9: Serialized 8
E10: Serialized 9
E11: Serialized 10
A15: Cost Adjustment | C15: Cost Adjustment Description
E16: Write In 1
E17: Write In 2
E18: Write In 3
E19: Write In 4
E20: Write In 5
A23: Cost Adjustment per item | C23: Cost Adjustment Description
E24: Non Serialized 1
E25: Non Serialized 2
E26: Non Serialized 3
E27: Non Serialized 4
E28: Non Serialized 5
A31: Term 1 Low Rate | B31: =IF('Costing Sheet'!M$19="Regular Equipment Rate",'Extra Cells Not used'!B46,IF('Costing Sheet'!M19="Mower And UTV Rate",'Extra Cells Not used'!D46,0)) -> 0
A32: Term 2 Low Rate | B32: =IF('Costing Sheet'!M$19="Regular Equipment Rate",'Extra Cells Not used'!B47,IF('Costing Sheet'!M19="Mower and UTV Rate",'Extra Cells Not used'!D47,0)) -> 0
A33: Term 3 Low Rate | B33: =IF('Costing Sheet'!M$19="Regular Equipment Rate",'Extra Cells Not used'!B48,IF('Costing Sheet'!M19="Mower and UTV Rate",'Extra Cells Not used'!D48,0)) -> 0
A36: Payment with Low Down PMT Term 1& Low Rate | B36: =IF(Calculations!B$435>Calculations!B$429,-PMT('Extra Cells Not used'!B$31/12,'Rates for Quote'!B$4,(Calculations!B$435+IF('Costing Sheet'!M$17="Include Kubota Insurance",Calculations!B$422,0)-Calculations!B$429)),0) -> 0
A37: Payment with Low Down PMT Term 2 & Low Rate | B37: =IF(Calculations!B$435>Calculations!B$429,-PMT('Extra Cells Not used'!B$32/12,'Rates for Quote'!B$6,(Calculations!B$435+IF('Costing Sheet'!M$17="Include Kubota Insurance",Calculations!B$423,0)-Calculations!B$429)),0) -> 0
A38: Payment with Low Down PMT Term 3 & Low Rate | B38: =IF(Calculations!B$435>Calculations!B$429,-PMT('Extra Cells Not used'!B$33/12,'Rates for Quote'!B$8,(Calculations!B$435+IF('Costing Sheet'!M$17="Include Kubota Insurance",Calculations!B$424,0)-Calculations!B$429)),0) -> 0
A39: Payment with MId Down PMT Term 1& Low Rate | B39: =IF(Calculations!B$435>Calculations!B$430,-PMT('Extra Cells Not used'!B$31/12,'Rates for Quote'!B$4,(Calculations!B$435+IF('Costing Sheet'!M$17="Include Kubota Insurance",Calculations!B$422,0)-Calculations!B$430)),0) -> 0
A40: Payment with MId Down PMT Term 2 & Low Rate | B40: =IF(Calculations!B$435>Calculations!B$430,-PMT('Extra Cells Not used'!B$32/12,'Rates for Quote'!B$6,(Calculations!B$435+IF('Costing Sheet'!M$17="Include Kubota Insurance",Calculations!B$423,0)-Calculations!B$430)),0) -> 0
A41: Payment with MId Down PMT Term 3 & Low Rate | B41: =IF(Calculations!B$435>Calculations!B$430,-PMT('Extra Cells Not used'!B$33/12,'Rates for Quote'!B$8,(Calculations!B$435+IF('Costing Sheet'!M$17="Include Kubota Insurance",Calculations!B$424,0)-Calculations!B$430)),0) -> 0
A42: Payment with High Down PMT Term 1& Low Rate | B42: =IF(Calculations!B$435>Calculations!B$431,-PMT('Extra Cells Not used'!B$31/12,'Rates for Quote'!B$4,(Calculations!B$435+IF('Costing Sheet'!M$17="Include Kubota Insurance",Calculations!B$422,0)-Calculations!B$431)),0) -> 0
A43: Payment with High Down PMT Term 2 & Low Rate | B43: =IF(Calculations!B$435>Calculations!B$431,-PMT('Extra Cells Not used'!B$32/12,'Rates for Quote'!B$6,(Calculations!B$435+IF('Costing Sheet'!M$17="Include Kubota Insurance",Calculations!B$423,0)-Calculations!B$431)),0) -> 0
A44: Payment with High Down PMT Term 3 & Low Rate | B44: =IF(Calculations!B$435>Calculations!B$431,-PMT('Extra Cells Not used'!B$33/12,'Rates for Quote'!B$8,(Calculations!B$435+IF('Costing Sheet'!M$17="Include Kubota Insurance",Calculations!B$424,0)-Calculations!B$431)),0) -> 0
A46: =+'Rates for Quote'!B4&" LOW RATE" -> LOW RATE | B46: =IFERROR(VLOOKUP('Rates for Quote'!$A$1,'Store LOCATIONS'!$A:$AG,22,FALSE),0) -> 0 | D46: =IFERROR(VLOOKUP('Rates for Quote'!$A$1,'Store LOCATIONS'!$A:$AG,28,FALSE),0) -> 0
A47: =+'Rates for Quote'!B6&" LOW RATE" -> LOW RATE | B47: =IFERROR(VLOOKUP('Rates for Quote'!$A$1,'Store LOCATIONS'!$A:$AG,23,FALSE),0) -> 0 | D47: =IFERROR(VLOOKUP('Rates for Quote'!$A$1,'Store LOCATIONS'!$A:$AG,29,FALSE),0) -> 0
A48: =+'Rates for Quote'!B8&" LOW RATE" -> LOW RATE | B48: =IFERROR(VLOOKUP('Rates for Quote'!$A$1,'Store LOCATIONS'!$A:$AG,24,FALSE),0) -> 0 | D48: =IFERROR(VLOOKUP('Rates for Quote'!$A$1,'Store LOCATIONS'!$A:$AG,30,FALSE),0) -> 0
B50: Taxable
A51: Serialized 1
A52: Serialized 2
A53: Serialized 3
A54: Serialized 4
A55: Serialized 5
B57: Taxable
A58: Write In 1
A59: Write In 2
A60: Write In 3
A61: Write In 4
A62: Write In 5
B65: Taxable
A66: Non Serialized 1
A67: Non Serialized 2
A68: Non Serialized 3
A69: Non Serialized 4
A70: Non Serialized 5

Sheet Customer List
E1: 1 | F1: 2 | G1: 3 | H1: 4 | I1: 5 | J1: 6 | K1: 7 | L1: 8 | M1: 9 | N1: 10 | O1: 11 | P1: 12 | Q1: 13
A2: Phone Number | B2: Search 1 | C2: Combined Search | D2: Branch | E2: Customer Number: | F2: Sold To Customer Name | G2: First | H2: Mid | I2: Last Name | J2: Sold To Address 1 | K2: Sold To Address 2 | L2: City | M2: Prv/St | N2: County | O2: Sold To Postal/Zip Code | P2: Phone # | Q2: Cell Phone Number | R2: Status | S2: Certificate Of Insurance | T2: Search 2 | U2: Fst Ex # | V2: Pst Ex # | W2: Date Last Modified | X2: Date Added | Y2: Date Last Billed | Z2: Business Email Address | AA2: Home Email Address
A3: 3214424490 | B3: . | C3: 3214424490. | D3: 03 | E3: .001 | F3: CARL SCHAEFER | G3: CARL | I3: SCHAEFER | J3: ***DO NOT USE*** | L3: KISSIMMEE | M3: FL | N3: 097 | O3: 34745 | P3: 3214424490 | R3: D | S3: N | W3: 20221022 | X3: 20190226 | Y3: 0

Sheet Calculations
A2: Quote Expiration | B2: =+#REF!+'Costing Sheet'!C9 -> #REF!
A3: Merge Last Name | B3: =UPPER('Customer Input Screen'!I11&" "&'Customer Input Screen'!I12&" "&'Customer Input Screen'!I13)
A4: Commision Split to second Sales Person | B4: =1-'Costing Sheet'!I7 -> 1
A5: Make Code First Line of Equipment | B5: =IF('Sales Input Sheet'!A$19<>"",IFERROR(VLOOKUP('Sales Input Sheet'!A$19,'Inventory Data'!$B$1:$J$12000,3,FALSE),"Not Found"),"")
A6: Make First Line of Equipment | B6: =IF(B5<>"",IFERROR(VLOOKUP(Calculations!$B5,Brands!$A$1:$B$200,2,FALSE),"OTHER"),"")
A7: Model First Line of Equipment | B7: =IF('Sales Input Sheet'!A$19<>"",IFERROR(VLOOKUP('Sales Input Sheet'!A$19,'Inventory Data'!$B$1:$J$12000,4,FALSE),"Not Found"),"")
A8: Serial Number First Line of Equipment | B8: =IF('Sales Input Sheet'!A$19<>"",IFERROR(VLOOKUP('Sales Input Sheet'!A$19,'Inventory Data'!$B$1:$J$12000,6,FALSE),"Not Found"),"")
A9: Description First Line of Equipment | B9: =IF('Sales Input Sheet'!A$19<>"",IFERROR(VLOOKUP('Sales Input Sheet'!A$19,'Inventory Data'!$B$1:$J$12000,5,FALSE),"Not Found"),"")
A10: Floorplan First Line of Equipment | B10: =IF('Sales Input Sheet'!A$19<>"",IFERROR(VLOOKUP('Sales Input Sheet'!A$19,'Inventory Data'!$B$1:$J$12000,9,FALSE),"Not Found"),"")
A11: Inventory Cost First Line of Equipment | B11: =IF('Sales Input Sheet'!A$19<>"",IFERROR(VLOOKUP('Sales Input Sheet'!A$19,'Inventory Data'!$B$1:$J$12000,8,FALSE),"Not Found"),0) -> 0
A12: Merge Descriptions First Line of Equipment | B12: =UPPER('Sales Input Sheet'!I$19&" "&'Sales Input Sheet'!K$19&" "&'Sales Input Sheet'!M$19&" "&UPPER('Sales Input Sheet'!O$19))
A13: Branch First Line of Equipment | B13: =IF('Sales Input Sheet'!A$19<>"",IFERROR(VLOOKUP('Sales Input Sheet'!A$19,'Inventory Data'!$B$1:$J$12000,2,FALSE),"Not Found"),0) -> 0
A14: Margin First Line of Equipment | B14: ='Costing Sheet'!I$22-'Costing Sheet'!K$22-'Costing Sheet'!AE$22-B11+'Costing Sheet'!Q22-'Costing Sheet'!AI22-'Costing Sheet'!AO22 -> 0
A15: First Line of Equipment Taxable Amount | B15: =IF(B$652="Tax Exempt",0,IF('Extra Cells Not used'!B$51<>"Non Taxable",'Costing Sheet'!I$22-'Costing Sheet'!K$22,0)) -> 0
A16: First Line of Equipment County Taxable Amount | B16: =+Calculations!B15 -> 0
A17: Make Code Second Line of Equipment | B17: =IF('Sales Input Sheet'!A$20<>"",IFERROR(VLOOKUP('Sales Input Sheet'!A$20,'Inventory Data'!$B$1:$J$12000,3,FALSE),"Not Found"),"")
A18: Make Second Line of Equipment | B18: =IF(B17<>"",IFERROR(VLOOKUP(Calculations!$B17,Brands!$A$1:$B$200,2,FALSE),"OTHER"),"")
A19: Model Second Line of Equipment | B19: =IF('Sales Input Sheet'!A$20<>"",IFERROR(VLOOKUP('Sales Input Sheet'!A$20,'Inventory Data'!$B$1:$J$12000,4,FALSE),"Not Found"),"")
A20: Serial Number Second Line of Equipment | B20: =IF('Sales Input Sheet'!A$20<>"",IFERROR(VLOOKUP('Sales Input Sheet'!A$20,'Inventory Data'!$B$1:$J$12000,6,FALSE),"Not Found"),"")
A21: Description Second Line of Equipment | B21: =IF('Sales Input Sheet'!A$20<>"",IFERROR(VLOOKUP('Sales Input Sheet'!A$20,'Inventory Data'!$B$1:$J$12000,5,FALSE),"Not Found"),"")
A22: Floorplan Second Line of Equipment | B22: =IF('Sales Input Sheet'!A$20<>"",IFERROR(VLOOKUP('Sales Input Sheet'!A$20,'Inventory Data'!$B$1:$J$12000,9,FALSE),"Not Found"),"")
A23: Inventory Cost Second Line of Equipment | B23: =IF('Sales Input Sheet'!A$20<>"",IFERROR(VLOOKUP('Sales Input Sheet'!A$20,'Inventory Data'!$B$1:$J$12000,8,FALSE),"Not Found"),0) -> 0
A24: Merge Descriptions Second Line of Equipment | B24: =IF(OR('Sales Input Sheet'!I$20<>"",'Sales Input Sheet'!O$20<>""),"INCLUDES "&'Sales Input Sheet'!I$20&" "&'Sales Input Sheet'!K$20&" "&'Sales Input Sheet'!M$20&" "&UPPER('Sales Input Sheet'!O$20),"")
A25: Branch Second Line of Equipment | B25: =IF('Sales Input Sheet'!A$20<>"",IFERROR(VLOOKUP('Sales Input Sheet'!A$20,'Inventory Data'!$B$1:$J$12000,2,FALSE),"Not Found"),0) -> 0
A26: Margin Second Line of Equipment | B26: ='Costing Sheet'!I$23-'Costing Sheet'!K$23-'Costing Sheet'!AE$23-B23+'Costing Sheet'!Q23-'Costing Sheet'!AI$23-'Costing Sheet'!AO23 -> 0
A27: Second Line of Equipment Taxable Amount | B27: =IF(B$652="Tax Exempt",0,IF('Extra Cells Not used'!B$52<>"Non Taxable",'Costing Sheet'!I$23-'Costing Sheet'!K$23,0)) -> 0
A28: Second Line of Equipment County Taxable Amount | B28: =+Calculations!B27 -> 0
A29: Make Code Third Line of Equipment | B29: =IF('Sales Input Sheet'!A$21<>"",IFERROR(VLOOKUP('Sales Input Sheet'!A$21,'Inventory Data'!$B$1:$J$12000,3,FALSE),"Not Found"),"")
A30: Make Third Line of Equipment | B30: =IF(B29<>"",IFERROR(VLOOKUP(Calculations!$B29,Brands!$A$1:$B$200,2,FALSE),"OTHER"),"")
A31: Model Third Line of Equipment | B31: =IF('Sales Input Sheet'!A$21<>"",IFERROR(VLOOKUP('Sales Input Sheet'!A$21,'Inventory Data'!$B$1:$J$12000,4,FALSE),"Not Found"),"")
A32: Serial Number Third Line of Equipment | B32: =IF('Sales Input Sheet'!A$21<>"",IFERROR(VLOOKUP('Sales Input Sheet'!A$21,'Inventory Data'!$B$1:$J$12000,6,FALSE),"Not Found"),"")
A33: Description Third Line of Equipment | B33: =IF('Sales Input Sheet'!A$21<>"",IFERROR(VLOOKUP('Sales Input Sheet'!A$21,'Inventory Data'!$B$1:$J$12000,5,FALSE),"Not Found"),"")
A34: Floorplan Third Line of Equipment | B34: =IF('Sales Input Sheet'!A$21<>"",IFERROR(VLOOKUP('Sales Input Sheet'!A$21,'Inventory Data'!$B$1:$J$12000,9,FALSE),"Not Found"),"")
A35: Inventory Cost Third Line of Equipment | B35: =IF('Sales Input Sheet'!A$21<>"",IFERROR(VLOOKUP('Sales Input Sheet'!A$21,'Inventory Data'!$B$1:$J$12000,8,FALSE),"Not Found"),0) -> 0
A36: Merge Descriptions Third Line of Equipment | B36: =IF(OR('Sales Input Sheet'!I$21<>"",'Sales Input Sheet'!O$21<>""),"INCLUDES "&'Sales Input Sheet'!I$21&" "&'Sales Input Sheet'!K$21&" "&'Sales Input Sheet'!M$21&" "&UPPER('Sales Input Sheet'!O$21),"")
A37: Branch Third Line of Equipment | B37: =IF('Sales Input Sheet'!A$21<>"",IFERROR(VLOOKUP('Sales Input Sheet'!A$21,'Inventory Data'!$B$1:$J$12000,2,FALSE),"Not Found"),0) -> 0
A38: Margin Third Line of Equipment | B38: ='Costing Sheet'!I$24-'Costing Sheet'!K$24-'Costing Sheet'!AE$24-B35+'Costing Sheet'!Q24-'Costing Sheet'!AI$24-'Costing Sheet'!AO24 -> 0
A39: Third Line of EquipmentTaxable Amount | B39: =IF(B$652="Tax Exempt",0,IF('Extra Cells Not used'!B$53<>"Non Taxable",'Costing Sheet'!I$24-'Costing Sheet'!K$24,0)) -> 0
A40: Third Line of Equipment County Taxable Amount | B40: =+Calculations!B39 -> 0
A41: Make Code Fourth Line of Equipment | B41: =IF('Sales Input Sheet'!A$22<>"",IFERROR(VLOOKUP('Sales Input Sheet'!A$22,'Inventory Data'!$B$1:$J$12000,3,FALSE),"Not Found"),"")
A42: Make Fourth Line of Equipment | B42: =IF(B41<>"",IFERROR(VLOOKUP(Calculations!$B41,Brands!$A$1:$B$200,2,FALSE),"OTHER"),"")
A43: Model Fourth Line of Equipment | B43: =IF('Sales Input Sheet'!A$22<>"",IFERROR(VLOOKUP('Sales Input Sheet'!A$22,'Inventory Data'!$B$1:$J$12000,4,FALSE),"Not Found"),"")
A44: Serial Number Fourth Line of Equipment | B44: =IF('Sales Input Sheet'!A$22<>"",IFERROR(VLOOKUP('Sales Input Sheet'!A$22,'Inventory Data'!$B$1:$J$12000,6,FALSE),"Not Found"),"")
A45: Description Fourth Line of Equipment | B45: =IF('Sales Input Sheet'!A$22<>"",IFERROR(VLOOKUP('Sales Input Sheet'!A$22,'Inventory Data'!$B$1:$J$12000,5,FALSE),"Not Found"),"")
A46: Floorplan Fourth Line of Equipment | B46: =IF('Sales Input Sheet'!A$22<>"",IFERROR(VLOOKUP('Sales Input Sheet'!A$22,'Inventory Data'!$B$1:$J$12000,9,FALSE),"Not Found"),"")
A47: Inventory Cost Fourth Line of Equipment | B47: =IF('Sales Input Sheet'!A$22<>"",IFERROR(VLOOKUP('Sales Input Sheet'!A$22,'Inventory Data'!$B$1:$J$12000,8,FALSE),"Not Found"),0) -> 0
A48: Merge Descriptions Fourth Line of Equipment | B48: =IF(OR('Sales Input Sheet'!I$22<>"",'Sales Input Sheet'!O$22<>""),"INCLUDES "&'Sales Input Sheet'!I$22&" "&'Sales Input Sheet'!K$22&" "&'Sales Input Sheet'!M$22&" "&UPPER('Sales Input Sheet'!O$22),"")
A49: Branch Fourth Line of Equipment | B49: =IF('Sales Input Sheet'!A$22<>"",IFERROR(VLOOKUP('Sales Input Sheet'!A$22,'Inventory Data'!$B$1:$J$12000,2,FALSE),"Not Found"),0) -> 0
A50: Margin Fourth Line of Equipment | B50: ='Costing Sheet'!I$25-'Costing Sheet'!K$25-'Costing Sheet'!AE$25-B47+'Costing Sheet'!Q25-'Costing Sheet'!AI$25-'Costing Sheet'!AO25 -> 0
A51: Fourth Line of Equipment Taxable Amount | B51: =IF(B$652="Tax Exempt",0,IF('Extra Cells Not used'!B$54<>"Non Taxable",'Costing Sheet'!I$25-'Costing Sheet'!K$25,0)) -> 0
A52: Fourth Line of Equipment County Taxable Amount | B52: =+Calculations!B51 -> 0
A53: Make Code Fifth Line of Equipment | B53: =IF('Sales Input Sheet'!A$23<>"",IFERROR(VLOOKUP('Sales Input Sheet'!A$23,'Inventory Data'!$B$1:$J$12000,3,FALSE),"Not Found"),"")
A54: Make Fifth Line of Equipment | B54: =IF(B53<>"",IFERROR(VLOOKUP(Calculations!$B53,Brands!$A$1:$B$200,2,FALSE),"OTHER"),"")
A55: Model Fifth Line of Equipment | B55: =IF('Sales Input Sheet'!A$23<>"",IFERROR(VLOOKUP('Sales Input Sheet'!A$23,'Inventory Data'!$B$1:$J$12000,4,FALSE),"Not Found"),"")
A56: Serial Number Fifth Line of Equipment | B56: =IF('Sales Input Sheet'!A$23<>"",IFERROR(VLOOKUP('Sales Input Sheet'!A$23,'Inventory Data'!$B$1:$J$12000,6,FALSE),"Not Found"),"")
A57: Description Fifth Line of Equipment | B57: =IF('Sales Input Sheet'!A$23<>"",IFERROR(VLOOKUP('Sales Input Sheet'!A$23,'Inventory Data'!$B$1:$J$12000,5,FALSE),"Not Found"),"")
A58: Floorplan Fifth Line of Equipment | B58: =IF('Sales Input Sheet'!A$23<>"",IFERROR(VLOOKUP('Sales Input Sheet'!A$23,'Inventory Data'!$B$1:$J$12000,9,FALSE),"Not Found"),"")
A59: Inventory Cost Fifth Line of Equipment | B59: =IF('Sales Input Sheet'!A$23<>"",IFERROR(VLOOKUP('Sales Input Sheet'!A$23,'Inventory Data'!$B$1:$J$12000,8,FALSE),"Not Found"),0) -> 0
A60: Merge Descriptions Fifth Line of Equipment | B60: =IF(OR('Sales Input Sheet'!I$23<>"",'Sales Input Sheet'!O$23<>""),"INCLUDES "&'Sales Input Sheet'!I$23&" "&'Sales Input Sheet'!K$23&" "&'Sales Input Sheet'!M$23&" "&UPPER('Sales Input Sheet'!O$23),"")
A61: Branch Fifth Line of Equipment | B61: =IF('Sales Input Sheet'!A$23<>"",IFERROR(VLOOKUP('Sales Input Sheet'!A$23,'Inventory Data'!$B$1:$J$12000,2,FALSE),"Not Found"),0) -> 0
A62: Margin Fifth Line of Equipment | B62: ='Costing Sheet'!I$26-'Costing Sheet'!K$26-'Costing Sheet'!AE$26-B59+'Costing Sheet'!Q26-'Costing Sheet'!AI$26-'Costing Sheet'!AO26 -> 0
A63: Fifth Line of Equipment Taxable Amount | B63: =IF(B$652="Tax Exempt",0,IF('Extra Cells Not used'!B$55<>"Non Taxable",'Costing Sheet'!I$26-'Costing Sheet'!K$26,0)) -> 0
A64: Fifth Line of Equipment County Taxable Amount | B64: =+Calculations!B63 -> 0
A65: Make Code Sixth Line of Equipment | B65: =IF('Sales Input Sheet'!A$24<>"",IFERROR(VLOOKUP('Sales Input Sheet'!A$24,'Inventory Data'!$B$1:$J$12000,3,FALSE),"Not Found"),"")
A66: Make Sixth Line of Equipment | B66: =IF(B65<>"",IFERROR(VLOOKUP(Calculations!$B65,Brands!$A$1:$B$200,2,FALSE),"OTHER"),"")
A67: Model Sixth Line of Equipment | B67: =IF('Sales Input Sheet'!A$24<>"",IFERROR(VLOOKUP('Sales Input Sheet'!A$24,'Inventory Data'!$B$1:$J$12000,4,FALSE),"Not Found"),"")
A68: Serial Number Sixth Line of Equipment | B68: =IF('Sales Input Sheet'!A$24<>"",IFERROR(VLOOKUP('Sales Input Sheet'!A$24,'Inventory Data'!$B$1:$J$12000,6,FALSE),"Not Found"),"")
A69: Description Sixth Line of Equipment | B69: =IF('Sales Input Sheet'!A$24<>"",IFERROR(VLOOKUP('Sales Input Sheet'!A$24,'Inventory Data'!$B$1:$J$12000,5,FALSE),"Not Found"),"")
A70: Floorplan Sixth Line of Equipment | B70: =IF('Sales Input Sheet'!A$24<>"",IFERROR(VLOOKUP('Sales Input Sheet'!A$24,'Inventory Data'!$B$1:$J$12000,9,FALSE),"Not Found"),"")
A71: Inventory Cost Sixth Line of Equipment | B71: =IF('Sales Input Sheet'!A$24<>"",IFERROR(VLOOKUP('Sales Input Sheet'!A$24,'Inventory Data'!$B$1:$J$12000,8,FALSE),"Not Found"),0) -> 0
A72: Merge Descriptions Sixth Line of Equipment | B72: =IF(OR('Sales Input Sheet'!I$24<>"",'Sales Input Sheet'!O$24<>""),"INCLUDES "&'Sales Input Sheet'!I$24&" "&'Sales Input Sheet'!K$24&" "&'Sales Input Sheet'!M$24&" "&UPPER('Sales Input Sheet'!O$24),"")
A73: Branch Sixth Line of Equipment | B73: =IF('Sales Input Sheet'!A$24<>"",IFERROR(VLOOKUP('Sales Input Sheet'!A$24,'Inventory Data'!$B$1:$J$12000,2,FALSE),"Not Found"),0) -> 0
A74: Margin Sixth Line of Equipment | B74: ='Costing Sheet'!I$27-'Costing Sheet'!K$27-'Costing Sheet'!AE$27-B71+'Costing Sheet'!Q27-'Costing Sheet'!AI$27-'Costing Sheet'!AO27 -> 0
A75: Sixth Line of Equipment Taxable Amount | B75: =IF(B$652="Tax Exempt",0,IF('Extra Cells Not used'!B$55<>"Non Taxable",'Costing Sheet'!I$27-'Costing Sheet'!K$27,0)) -> 0
A76: Sixth Line of Equipment County Taxable Amount | B76: =+Calculations!B75 -> 0
A77: Make Code Seventh Line of Equipment | B77: =IF('Sales Input Sheet'!A$25<>"",IFERROR(VLOOKUP('Sales Input Sheet'!A$25,'Inventory Data'!$B$1:$J$12000,3,FALSE),"Not Found"),"")
A78: Make Seventh Line of Equipment | B78: =IF(B77<>"",IFERROR(VLOOKUP(Calculations!$B77,Brands!$A$1:$B$200,2,FALSE),"OTHER"),"")
A79: Model Seventh Line of Equipment | B79: =IF('Sales Input Sheet'!A$25<>"",IFERROR(VLOOKUP('Sales Input Sheet'!A$25,'Inventory Data'!$B$1:$J$12000,4,FALSE),"Not Found"),"")
A80: Serial Number Seventh Line of Equipment | B80: =IF('Sales Input Sheet'!A$25<>"",IFERROR(VLOOKUP('Sales Input Sheet'!A$25,'Inventory Data'!$B$1:$J$12000,6,FALSE),"Not Found"),"")
A81: Description Seventh Line of Equipment | B81: =IF('Sales Input Sheet'!A$25<>"",IFERROR(VLOOKUP('Sales Input Sheet'!A$25,'Inventory Data'!$B$1:$J$12000,5,FALSE),"Not Found"),"")
A82: Floorplan Seventh Line of Equipment | B82: =IF('Sales Input Sheet'!A$25<>"",IFERROR(VLOOKUP('Sales Input Sheet'!A$25,'Inventory Data'!$B$1:$J$12000,9,FALSE),"Not Found"),"")
A83: Inventory Cost Seventh Fifth Line of Equipment | B83: =IF('Sales Input Sheet'!A$25<>"",IFERROR(VLOOKUP('Sales Input Sheet'!A$25,'Inventory Data'!$B$1:$J$12000,8,FALSE),"Not Found"),0) -> 0
A84: Merge Descriptions Seventh Line of Equipment | B84: =IF(OR('Sales Input Sheet'!I$25<>"",'Sales Input Sheet'!O$25<>""),"INCLUDES "&'Sales Input Sheet'!I$25&" "&'Sales Input Sheet'!K$25&" "&'Sales Input Sheet'!M$25&" "&UPPER('Sales Input Sheet'!O$25),"")
A85: Branch Seventh Line of Equipment | B85: =IF('Sales Input Sheet'!A$25<>"",IFERROR(VLOOKUP('Sales Input Sheet'!A$25,'Inventory Data'!$B$1:$J$12000,2,FALSE),"Not Found"),0) -> 0
A86: Margin Seventh Line of Equipment | B86: ='Costing Sheet'!I$28-'Costing Sheet'!K$28-'Costing Sheet'!AE$28-B83+'Costing Sheet'!Q28-'Costing Sheet'!AI$28-'Costing Sheet'!AO28 -> 0
A87: Seventh Line of Equipment Taxable Amount | B87: =IF(B$652="Tax Exempt",0,IF('Extra Cells Not used'!B$55<>"Non Taxable",'Costing Sheet'!I$28-'Costing Sheet'!K$28,0)) -> 0
A88: Seventh Line of Equipment County Taxable Amount | B88: =+Calculations!B87 -> 0
A89: Make Code Eighth Line of Equipment | B89: =IF('Sales Input Sheet'!A$26<>"",IFERROR(VLOOKUP('Sales Input Sheet'!A$26,'Inventory Data'!$B$1:$J$12000,3,FALSE),"Not Found"),"")
A90: Make Eighth Line of Equipment | B90: =IF(B89<>"",IFERROR(VLOOKUP(Calculations!$B89,Brands!$A$1:$B$200,2,FALSE),"OTHER"),"")
A91: Model Eighth Line of Equipment | B91: =IF('Sales Input Sheet'!A$26<>"",IFERROR(VLOOKUP('Sales Input Sheet'!A$26,'Inventory Data'!$B$1:$J$12000,4,FALSE),"Not Found"),"")
A92: Serial Number Eighth Line of Equipment | B92: =IF('Sales Input Sheet'!A$26<>"",IFERROR(VLOOKUP('Sales Input Sheet'!A$26,'Inventory Data'!$B$1:$J$12000,6,FALSE),"Not Found"),"")
A93: Description Eighth Line of Equipment | B93: =IF('Sales Input Sheet'!A$26<>"",IFERROR(VLOOKUP('Sales Input Sheet'!A$26,'Inventory Data'!$B$1:$J$12000,5,FALSE),"Not Found"),"")
A94: Floorplan Eighth Line of Equipment | B94: =IF('Sales Input Sheet'!A$26<>"",IFERROR(VLOOKUP('Sales Input Sheet'!A$26,'Inventory Data'!$B$1:$J$12000,9,FALSE),"Not Found"),"")
A95: Inventory Cost Eighth Line of Equipment | B95: =IF('Sales Input Sheet'!A$26<>"",IFERROR(VLOOKUP('Sales Input Sheet'!A$26,'Inventory Data'!$B$1:$J$12000,8,FALSE),"Not Found"),0) -> 0
A96: Merge Descriptions Eighth Line of Equipment | B96: =IF(OR('Sales Input Sheet'!I$26<>"",'Sales Input Sheet'!O$26<>""),"INCLUDES "&'Sales Input Sheet'!I$26&" "&'Sales Input Sheet'!K$26&" "&'Sales Input Sheet'!M$26&" "&UPPER('Sales Input Sheet'!O$26),"")
A97: Branch Eighth Line of Equipment | B97: =IF('Sales Input Sheet'!A$26<>"",IFERROR(VLOOKUP('Sales Input Sheet'!A$26,'Inventory Data'!$B$1:$J$12000,2,FALSE),"Not Found"),0) -> 0
A98: Margin Eighth Line of Equipment | B98: ='Costing Sheet'!I$29-'Costing Sheet'!K$29-'Costing Sheet'!AE$29-B95+'Costing Sheet'!Q29-'Costing Sheet'!AI$29-'Costing Sheet'!AO29 -> 0
A99: Eighth Line of Equipment Taxable Amount | B99: =IF(B$652="Tax Exempt",0,IF('Extra Cells Not used'!B$55<>"Non Taxable",'Costing Sheet'!I$29-'Costing Sheet'!K$29,0)) -> 0
A100: Eighth Line of Equipment County Taxable Amount | B100: =+Calculations!B99 -> 0
A101: Make Code Ninth Line of Equipment | B101: =IF('Sales Input Sheet'!A$27<>"",IFERROR(VLOOKUP('Sales Input Sheet'!A$27,'Inventory Data'!$B$1:$J$12000,3,FALSE),"Not Found"),"")
...

Sheet Descriptions
A2: DESCRIPTIONS
A4: 12 INCH BUCKET
A5: 16 INCH BUCKET
A6: 18 INCH BUCKET
A7: 24 INCH BUCKET
A8: 36 INCH BUCKET
A9: 48 INCH BUCKET
A10: 54 INCH BUCKET
A11: 66 INCH BUCKET
A12: 72 INCH BUCKET
A13: 74 INCH BUCKET
A14: 80 INCH BUCKET
... A39: OPEN STATION

Sheet Sales People
A1: Table | B1: Co# | C1: Div | D1: Br# | E1: Key | F1: Sta | G1: Data | H1: NAME | I1: Key
A2: CMSMN | B2: 01 | C2: 01 | E2: 000 | G2: Unassigned | H2: Unassigned | I2: 000

Sheet Brands
A1: Make Code | B1: Desxcription for Make Code | C1: Desxcription for Make Code
A2: AB | B2: A & B | C2: A & B
A3: AD | B3: ADI | C3: ADI
A4: AR | B4: AG SPRAY | C4: AG SPRAY
A5: AX | B5: AGKNX | C5: AGKNX
A6: AG | B6: AGRIMETAL | C6: AGRIMETAL
A7: AZ | B7: ALTOZ | C7: ALTOZ
A8: AL | B8: ALUMA | C8: ALUMA
A9: AM | B9: AMP TRAILERS | C9: AMP TRAILERS
A10: AN | B10: ANSUNG USA | C10: ANSUNG USA
A11: AI | B11: ARIENS | C11: ARIENS
A12: AS | B12: ASV | C12: ASV
... A149: YA | B149: YAMAHA | C149: YAMAHA

Sheet Inventory Data
A1: Br | B1: Order/Stock Number | C1: Br | D1: Make | E1: Mod | F1: Desc | G1: Machine Serial # | H1: Group Code | I1: CURRCOST | J1: Floor Plan | K1: Finance Start Date | L1: Trans Ser # | M1: Sta | N1: Typ
A2: 04 | B2: C056897A | C2: 04 | D2: TA | E2: BTB13518 | F2: 18'' PIN ON BUCKET WITH TEETH 2.7 CU FT CAP | G2: TI0047563 | H2: 2CYCLE | I2: 851.76 | J2: 0 | K2: 0 | M2: V | N2: N
A3: 15 | B3: CA0707B | C3: 15 | D3: KU | E3: ZD1211L-3-72 | F3: ZD DIESEL 72" DECK | G3: KBGGDCF0LPGL54161 | H3: ZTURN | I3: 17762.2 | J3: -16883.2 | K3: 0 | M3: V | N3: N
A4: 01 | B4: D066304C | C4: 01 | D4: KU | E4: U555R3A | F4: EXCAVATOR W/RUB TKS/AC CAB/ANGLE | G4: KBCDZ57CHR3D14462 | H4: EXC | I4: 0 | J4: 0 | K4: 0 | M4: V | N4: N
A5: 01 | B5: D066395D | C5: 01 | D5: KU | E5: LX2620HSD | F5: 4WD TRACTOR | G5: KBUBFAHRJR1D12917 | H5: TRACTOR | I5: 52 | J5: 0 | K5: 0 | M5: V | N5: U
A6: 01 | B6: D066396E | C6: 01 | D6: KU | E6: LA535 | F6: FRONT END LOADER QC | G6: D9182 | H6: ATTACH | I6: 0 | J6: 0 | K6: 0 | M6: V | N6: N

Sheet States
A1: 1 | B1: Alabama | C1: Ala. | D1: AL
A2: 2 | B2: Alaska | D2: AK
A3: 4 | B3: Arizona | C3: Ariz. | D3: AZ
A4: 5 | B4: Arkansas | C4: Ark. | D4: AR
A5: 6 | B5: California | C5: Calif. | D5: CA
A6: 8 | B6: Colorado | C6: Colo. | D6: CO
A7: 9 | B7: Connecticut | C7: Conn. | D7: CT
A8: 10 | B8: Delaware | C8: Del. | D8: DE
A9: 11 | B9: District of Columbia | C9: D.C. | D9: DC
A10: 12 | B10: Florida | C10: Fla. | D10: FL
A11: 13 | B11: Georgia | C11: Ga. | D11: GA
A12: 15 | B12: Hawaii | D12: HI
A13: 16 | B13: Idaho | D13: ID
A14: 17 | B14: Illinois | C14: Ill. | D14: IL
A15: 18 | B15: Indiana | C15: Ind. | D15: IN
A16: 19 | B16: Iowa | D16: IA
A17: 20 | B17: Kansas | C17: Kans. | D17: KS
A18: 21 | B18: Kentucky | C18: Ky. | D18: KY
A19: 22 | B19: Louisiana | D19: LA
A20: 23 | B20: Maine | C20: Me. | D20: ME
A21: 24 | B21: Maryland | C21: Md. | D21: MD
A22: 25 | B22: Massachusetts | C22: Mass. | D22: MA
A23: 26 | B23: Michigan | C23: Mich. | D23: MI
A24: 27 | B24: Minnesota | C24: Minn. | D24: MN
A25: 28 | B25: Mississippi | C25: Miss. | D25: MS
A26: 29 | B26: Missouri | C26: Mo. | D26: MO
A27: 30 | B27: Montana | C27: Mont. | D27: MT
A28: 31 | B28: Nebraska | C28: Nebr. | D28: NE
A29: 32 | B29: Nevada | C29: Nev. | D29: NV
A30: 33 | B30: New Hampshire | C30: N.H. | D30: NH
A31: 34 | B31: New Jersey | C31: N.J. | D31: NJ
... A34: 37 | B34: North Carolina | C34: N.C. | D34: NC
A35: 38 | B35: North Dakota | D35: ND
A36: 39 | B36: Ohio | D36: OH
A37: 40 | B37: Oklahoma | C37: Okla. | D37: OK
A38: 41 | B38: Oregon | C38: Ore. | D38: OR
A39: 42 | B39: Pennsylvania | C39: Penn. | D39: PA
A40: 44 | B40: Rhode Island | C40: R.I. | D40: RI
A41: 45 | B41: South Carolina | C41: S.C. | D41: SC
A42: 46 | B42: South Dakota | D42: SD
A43: 47 | B43: Tennessee | C43: Tenn. | D43: TN
A44: 48 | B44: Texas | C44: Tex. | D44: TX
A45: 49 | B45: Utah | D45: UT
A46: 50 | B46: Vermont | C46: Vt. | D46: VT
A47: 51 | B47: Virginia | C47: Va. | D47: VA
A48: 53 | B48: Washington | C48: Wash. | D48: WA
A49: 54 | B49: West Virginia | C49: W.Va. | D49: WV
A50: 55 | B50: Wisconsin | C50: Wis. | D50: WI
A51: 56 | B51: Wyoming | C51: Wyo. | D51: WY

Sheet FlSalesSurtaxRates
A1: State of Florida
A2: Department of Revenue
A3: Discretionary Sales Surtax Rates Table
A4: County | B4: Total Surtax Rate
A7: ALACHUA | B7: 1.50%
A8: BAKER | B8: 1.00%
A9: BAY | B9: 1.00%
A10: BRADFORD | B10: 1.00%
A11: BREVARD | B11: 1.00%
A12: BROWARD | B12: 1.00%
A13: CALHOUN | B13: 1.50%
A14: CHARLOTTE | B14: 1.00%
A15: CITRUS | B15: 0.00%
A16: CLAY | B16: 1.50%
A17: COLLIER | B17: 0.00%
... A29: GULF | B29: 1.00%
A30: HAMILTON | B30: 0.02
A31: HARDEE | B31: 1.00%
A32: HENDRY | B32: 1.50%
A33: HERNANDO | B33: 0.50%
A34: HIGHLANDS | B34: 1.50%
A35: HILLSBOROUGH | B35: 0.015
A36: HOLMES | B36: 1.50%
A37: INDIAN RIVER | B37: 1.00%
A38: JACKSON | B38: 1.50%
A39: JEFFERSON | B39: 1.00%
A40: LAFAYETTE | B40: 1.00%
A41: LAKE | B41: 1.00%
A42: LEE | B42: 0.50%
A43: LEON | B43: 1.50%
A44: LEVY | B44: 1.00%
A45: LIBERTY | B45: 1.50%
A46: MADISON | B46: 1.50%
A47: MANATEE | B47: 1.00%
A48: MARION | B48: 0.015
A49: MARTIN | B49: 0.01
A50: MIAMI-DADE | B50: 1.00%
A51: MONROE | B51: 1.50%
A52: NASSAU | B52: 1.00%
A53: OKALOOSA | B53: 1.00%
A54: OKEECHOBEE | B54: 1.00%
A55: ORANGE | B55: 0.50%
A56: OSCEOLA | B56: 1.50%
A57: PALM BEACH | B57: 1.00%
A58: PASCO | B58: 1.00%
A59: PINELLAS | B59: 1.00%
A60: POLK | B60: 1.00%
A61: PUTNAM | B61: 1.00%
... A74: WASHINGTON | B74: 1.50%
A75: Rates shown above are current as of 6/21/2024
A76: Effective and expiration dates for surtax rates are listed on Form DR-15DSS, which is posted on the Department of Revenue's website: www.myflorida.com/dor

Sheet GA DISC TAX
A2: Appling | B2: 0.04
A3: Atkinson | B3: 0.04
A4: Bacon | B4: 0.04
A5: Baker | B5: 0.04
A6: Baldwin | B6: 0.04
A7: Banks | B7: 0.04
A8: Barrow | B8: 0.04
A9: Bartow | B9: 0.03
A10: Ben Hill | B10: 0.04
A11: Berrien | B11: 0.04
A12: Bibb | B12: 0.03
A13: Bleckley | B13: 0.04
... A160: Worth | B160: 0.04

Sheet Store LOCATIONS
A1: Location | B1: Branch Number | P1: Down Payment 1 | Q1: Down Payment 2 | R1: Down Payment 3 | S1: Term 1 | T1: Term 2 | U1: Term 3 | V1: Low Rate Term 1 | W1: Low Rate Term 2 | X1: Low Rate Term 3 | Y1: High Rate Term 1 | Z1: High Rate Term 2 | AA1: High Rate Term 3 | AB1: Mower Low Rate Term 1 | AC1: Mower Low Rate Term 2 | AD1: Mower Low Rate Term 3 | AE1: Mower High Rate Term 1 | AF1: Mower High Rate Term 2 | AG1: Mower High Rate Term 3
A2: DELAND | B2: 01 | C2: 386-734-2119 | D2: 1580 S. WOODLAND BLVD. | E2: DELAND | F2: FL | G2: 32720 | H2: VOLUSIA | I2: DELAND, FL 32720 | J2: CRYSTAL TRACTOR & EQUIPMENT - DELAND | P2: 2000 | Q2: 5000 | R2: 10000 | S2: 48 | T2: 60 | U2: 72 | V2: 0.05 | W2: 0.06 | X2: 0.065 | Y2: 0.099 | Z2: 0.109 | AA2: 0.114 | AB2: 0.099 | AC2: 0.099 | AD2: 0.099 | AE2: 0.149 | AF2: 0.159 | AG2: 0.169
A3: LEESBURG | B3: 02 | C3: 352-787-1234 | D3: 3701 W. MAIN ST. | E3: LEESBURG | F3: FL | G3: 34748 | H3: LAKE | I3: LEESBURG, FL 34748 | J3: CRYSTAL TRACTOR & EQUIPMENT - LEESBURG | P3: 2000 | Q3: 5000 | R3: 10000 | S3: 48 | T3: 60 | U3: 72 | V3: 0.05 | W3: 0.06 | X3: 0.065 | Y3: 0.099 | Z3: 0.109 | AA3: 0.114 | AB3: 0.099 | AC3: 0.099 | AD3: 0.099 | AE3: 0.149 | AF3: 0.159 | AG3: 0.169
A4: CHIEFLAND | B4: 04 | C4: 352-490-7061 | D4: 14811 US 19 | E4: CHIEFLAND | F4: FL | G4: 32626 | H4: LEVY | I4: CHIEFLAND, FL 32626 | J4: CRYSTAL TRACTOR & EQUIPMENT - CHIEFLAND | P4: 2000 | Q4: 5000 | R4: 10000 | S4: 48 | T4: 60 | U4: 72 | V4: 0.05 | W4: 0.06 | X4: 0.065 | Y4: 0.099 | Z4: 0.109 | AA4: 0.114 | AB4: 0.099 | AC4: 0.099 | AD4: 0.099 | AE4: 0.149 | AF4: 0.159 | AG4: 0.169
A5: JACKSONVILLE | B5: 16 | C5: 904-914-8878 | D5: 10628 GENERAL AVE. | E5: JACKSONVILLE | F5: FL | G5: 32220 | H5: DUVAL | I5: JACKSONVILLE, FL 32220 | J5: CRYSTAL TRACTOR & EQUIPMENT - JACKSONVILLE | P5: 2000 | Q5: 5000 | R5: 10000 | S5: 48 | T5: 60 | U5: 72 | V5: 0.05 | W5: 0.06 | X5: 0.065 | Y5: 0.099 | Z5: 0.109 | AA5: 0.114 | AB5: 0.099 | AC5: 0.099 | AD5: 0.099 | AE5: 0.149 | AF5: 0.159 | AG5: 0.169
A6: HASTINGS | B6: 08 | C6: 904-692-3673 | D6: 8515 STATE RD 207 | E6: HASTINGS | F6: FL | G6: 32145 | H6: ST JOHNS | I6: HASTINGS, FL 32145 | J6: CRYSTAL TRACTOR & EQUIPMENT - HASTINGS | P6: 2000 | Q6: 5000 | R6: 10000 | S6: 48 | T6: 60 | U6: 72 | V6: 0.05 | W6: 0.06 | X6: 0.065 | Y6: 0.099 | Z6: 0.109 | AA6: 0.114 | AB6: 0.099 | AC6: 0.099 | AD6: 0.099 | AE6: 0.149 | AF6: 0.159 | AG6: 0.169
A7: MADISON | B7: 12 | C7: 850-973-2245 | D7: 491 SW RANGE AVE | E7: MADISON | F7: FL | G7: 32340 | H7: MADISON | I7: MADISON, FL 32340 | J7: CRYSTAL TRACTOR & EQUIPMENT - MADISON | P7: 2000 | Q7: 5000 | R7: 10000 | S7: 48 | T7: 60 | U7: 72 | V7: 0.05 | W7: 0.06 | X7: 0.065 | Y7: 0.099 | Z7: 0.109 | AA7: 0.114 | AB7: 0.099 | AC7: 0.099 | AD7: 0.099 | AE7: 0.149 | AF7: 0.159 | AG7: 0.169
A8: PANAMA CITY | B8: 13 | C8: 850-763-5441 | D8: 2841 FL-77 | E8: PANAMA CITY | F8: FL | G8: 32405 | H8: BAY | I8: PANAMA CITY, FL 32405 | J8: CRYSTAL TRACTOR & EQUIPMENT - PANAMA CITY | P8: 2000 | Q8: 5000 | R8: 10000 | S8: 48 | T8: 60 | U8: 72 | V8: 0.05 | W8: 0.06 | X8: 0.065 | Y8: 0.099 | Z8: 0.109 | AA8: 0.114 | AB8: 0.099 | AC8: 0.099 | AD8: 0.099 | AE8: 0.149 | AF8: 0.159 | AG8: 0.169
A9: CAIRO, GA | B9: 15 | C9: 229-377-1585 | D9: 1920 US HIGHWAY 84 E | E9: CAIRO | F9: GA | G9: 39828 | H9: GRADY | I9: CAIRO, GA 39828 | J9: CRYSTAL TRACTOR & EQUIPMENT - CAIRO, GA | P9: 2000 | Q9: 5000 | R9: 10000 | S9: 48 | T9: 60 | U9: 72 | V9: 0.05 | W9: 0.06 | X9: 0.065 | Y9: 0.099 | Z9: 0.109 | AA9: 0.114 | AB9: 0.099 | AC9: 0.099 | AD9: 0.099 | AE9: 0.149 | AF9: 0.159 | AG9: 0.169
A10: TALLAHASSEE | B10: 14 | C10: 850-671-2585 | D10: 4017 WOODVILLE HWY | E10: TALLAHASSEE | F10: FL | G10: 32305 | H10: LEON | I10: TALLAHASSEE, FL 32305 | J10: CRYSTAL TRACTOR & EQUIPMENT - TALLAHASSEE | P10: 2000 | Q10: 5000 | R10: 10000 | S10: 48 | T10: 60 | U10: 72 | V10: 0.05 | W10: 0.06 | X10: 0.065 | Y10: 0.099 | Z10: 0.109 | AA10: 0.114 | AB10: 0.099 | AC10: 0.099 | AD10: 0.099 | AE10: 0.149 | AF10: 0.159 | AG10: 0.169
A11: SPRING HILL | B11: 05 | C11: 352-597-4100 | D11: 3477 COMMERCIAL WAY | E11: SPRING HILL | F11: FL | G11: 34606 | H11: HERNANDO | I11: SPRING HILL, FL 34606 | J11: CRYSTAL TRACTOR & EQUIPMENT - SPRING HILL | P11: 2000 | Q11: 5000 | R11: 10000 | S11: 48 | T11: 60 | U11: 72 | V11: 0.05 | W11: 0.06 | X11: 0.065 | Y11: 0.099 | Z11: 0.109 | AA11: 0.114 | AB11: 0.099 | AC11: 0.099 | AD11: 0.099 | AE11: 0.149 | AF11: 0.159 | AG11: 0.169
A12: HOMOSASSA | B12: 07 | C12: 352-835-3110 | D12: 3029 S SUNCOAST BLVD | E12: HOMOSASSA | F12: FL | G12: 34448 | H12: CITRUS | I12: HOMOSASSA, FL 34448 | J12: CRYSTAL TRACTOR & EQUIPMENT - HOMOSASSA | P12: 2000 | Q12: 5000 | R12: 10000 | S12: 48 | T12: 60 | U12: 72 | V12: 0.05 | W12: 0.06 | X12: 0.065 | Y12: 0.099 | Z12: 0.109 | AA12: 0.114 | AB12: 0.099 | AC12: 0.099 | AD12: 0.099 | AE12: 0.149 | AF12: 0.159 | AG12: 0.169
A13: OCALA | B13: 06 | C13: 352-835-3130 | D13: 5400 FL 40 | E13: OCALA | F13: FL | G13: 34482 | H13: MARION | I13: OCALA, FL 34482 | J13: CRYSTAL TRACTOR & EQUIPMENT - OCALA | P13: 2000 | Q13: 5000 | R13: 10000 | S13: 48 | T13: 60 | U13: 72 | V13: 0.05 | W13: 0.06 | X13: 0.065 | Y13: 0.099 | Z13: 0.109 | AA13: 0.114 | AB13: 0.099 | AC13: 0.099 | AD13: 0.099 | AE13: 0.149 | AF13: 0.159 | AG13: 0.169
A14: STARKE | B14: 10 | C14: 904-964-4238 | D14: 11863 US HWY 301 | E14: HAMPTON | F14: FL | G14: 32044 | H14: BRADFORD | I14: HAMPTON, FL 32044 | J14: CRYSTAL TRACTOR & EQUIPMENT - STARKE | P14: 2000 | Q14: 5000 | R14: 10000 | S14: 48 | T14: 60 | U14: 72 | V14: 0.05 | W14: 0.06 | X14: 0.065 | Y14: 0.099 | Z14: 0.109 | AA14: 0.114 | AB14: 0.099 | AC14: 0.099 | AD14: 0.099 | AE14: 0.149 | AF14: 0.159 | AG14: 0.169
A15: PALATKA | B15: 09 | C15: 386-385-5658 | D15: 625 FL-19 | E15: PALATKA | F15: FL | G15: 32177 | H15: PUTNAM | I15: PALATKA, FL 32177 | J15: CRYSTAL TRACTOR & EQUIPMENT - PALATKA | P15: 2000 | Q15: 5000 | R15: 10000 | S15: 48 | T15: 60 | U15: 72 | V15: 0.05 | W15: 0.06 | X15: 0.065 | Y15: 0.099 | Z15: 0.109 | AA15: 0.114 | AB15: 0.099 | AC15: 0.099 | AD15: 0.099 | AE15: 0.149 | AF15: 0.159 | AG15: 0.169
A16: LIVE OAK | B16: 11 | C16: 386-362-1887 | D16: 411 72nd Tr | E16: LIVE OAK | F16: FL | G16: 32060 | H16: SUWANEE | I16: LIVE OAK, FL 32060 | J16: CRYSTAL TRACTOR & EQUIPMENT - LIVE OAK | P16: 2000 | Q16: 5000 | R16: 10000 | S16: 48 | T16: 60 | U16: 72 | V16: 0.05 | W16: 0.06 | X16: 0.065 | Y16: 0.099 | Z16: 0.109 | AA16: 0.114 | AB16: 0.099 | AC16: 0.099 | AD16: 0.099 | AE16: 0.149 | AF16: 0.159 | AG16: 0.169
A17: MIAMI | B17: 18 | E17: MIAMI | F17: FL | H17: DADE | I17: MIAMI, FL | J17: CRYSTAL TRACTOR & EQUIPMENT - SOUTH FLORIDA
A18: LECANTO | B18: 17 | C18: 352-527-2001 | D18: 4016 W SOUTHERN ST. | E18: LECANTO | F18: FL | G18: 34461 | H18: CITRUS | I18: LECANTO, FL 34461 | J18: CRYSTAL TRACTOR & EQUIPMENT - LECANTO | P18: 2000 | Q18: 5000 | R18: 10000 | S18: 48 | T18: 60 | U18: 72 | V18: 0.05 | W18: 0.06 | X18: 0.065 | Y18: 0.099 | Z18: 0.109 | AA18: 0.114 | AB18: 0.099 | AC18: 0.099 | AD18: 0.099 | AE18: 0.149 | AF18: 0.159 | AG18: 0.169
A19: PARTS WAREHOUSE | B19: 03 | C19: 000-000-0000 | D19: 3016 E Norvell Bryant Hwy | E19: HERNANDO | F19: FL | G19: 34442 | H19: CITRUS | I19: HERNANDO, FL 34442 | J19: CRYSTAL TRACTOR & EQUIPMENT - CORPORATE

Sheet Tax Exemption Cert table
A2: Florida Poulty Generator | B2: Generators purchased, rented, or leased for exclusive use on a poultry farm. See the exemption category provided for power farm equipment, as defined in Section 212.02(30), F.S., which includes generators, motors, and similar types of equipment.
A3: Florida Containers used in farm products | B3: Portable containers, or moveable receptacles in which portable containers are placed, that are used for harvesting or processing farm products.
